Workbook

Sheet Valuation >

Sheet IndexVal
B2: Valuing the BSE 100 | H2: Total Yield | I2: EPS Growth | J2: Rf | K2: ERP
B3: Index | C3: Previous Close | D3: Ticker Symbol | E3: Intrinsic Value
H4: 20 Years | I4: 10 Years | J4: 20 Years | K4: 20 Years
B5: BSE 100 | C5: 27577.11 | D5: BSE-100 | E5: =SUM(E16:E26) -> 25391.147 | H5: 15 Years | I5: 10 Years | J5: 15 Years | K5: 20 Years
B6: Key Inputs | D6: Assumptions | E6: =IF(E5>(1.05*D8),"Undervalued",IF(E5<(0.95*D8),"Overvalued","Fairly Valued")) -> Overvalued | H6: 10 Years | I6: 7 Years | J6: 7 Years | K6: 15 Years
B7: Date | C7: =TODAY() -> 46036 | D7: =C7 -> 46036 | H7: 7 Years | I7: 5 Years | J7: 5 Years | K7: 7 Years
B8: Current Index Level | C8: =C5 -> 27577.11 | D8: =C8 -> 27577.11 | E8: ="The Market Implied Fair value of the Index is "&ROUND(E5,0)&". The Index is Currently Trading at "&ROUND(D8,0)&". A "&TEXT(ABS((D8-E5)/D8),"0.00%")&" "&IF(E6="Undervalued","apppreciation",IF(E6="Overvalued","correction","adjustment"))&" can be expected from this level" -> The Market Implied Fair value of the Index is 25391. The Index is Currently Trading at 27577. A 7.93% correction can be expected from this level | H8: 5 Years | I8: 3 Years | J8: Latest | K8: 5 Years
B9: Total Yield | C9: 3 Years | D9: =VLOOKUP(C9,'ExpDiv&BB'!K2:L12,2,0) -> 0.014356551 | H9: 3 Years | K9: Latest
B10: Expected Growth (Earnings) | C10: 10 Years | D10: =VLOOKUP(C10,IndexEPSGrowth!L3:M9,2,0) -> 0.12365602
B11: Risk Free Rate | C11: Latest | D11: =VLOOKUP(C11,RfHistorical!M2:N10,2,0) -> 0.066
B12: Equity Risk Premium | C12: Latest | D12: =VLOOKUP(C12,ERPHistorical!F2:G10,2,0) -> 0.027
B13: Cost of Equity | D13: =SUM(D11:D12) -> 0.093
B15: Year | C15: Expected Dividend and Buyback Yield | D15: Cumulative PV Factor [Risk-free Rate + Equity Rsik Premium] | E15: Present Value of Expected Dividends and Buybacks
B16: 2026 | C16: =$D$8*$D$9*(1+$D$10)^(B16-($B$16-1)) -> 444.8691 | D16: =1/(1+$D$13)^(B16-($B$16-1)) -> 0.91491308 | E16: =C16*D16 -> 407.01656
B17: =B16+1 -> 2027 | C17: =$D$8*$D$9*(1+$D$10)^(B17-($B$16-1)) -> 499.87984 | D17: =1/(1+$D$13)^(B17-($B$16-1)) -> 0.83706595 | E17: =C17*D17 -> 418.4324
B18: =B17+1 -> 2028 | C18: =$D$8*$D$9*(1+$D$10)^(B18-($B$16-1)) -> 561.69299 | D18: =1/(1+$D$13)^(B18-($B$16-1)) -> 0.76584259 | E18: =C18*D18 -> 430.16842
B19: =B18+1 -> 2029 | C19: =$D$8*$D$9*(1+$D$10)^(B19-($B$16-1)) -> 631.14971 | D19: =1/(1+$D$13)^(B19-($B$16-1)) -> 0.7006794 | E19: =C19*D19 -> 442.23361
B20: =B19+1 -> 2030 | C20: =$D$8*$D$9*(1+$D$10)^(B20-($B$16-1)) -> 709.19517 | D20: =1/(1+$D$13)^(B20-($B$16-1)) -> 0.64106075 | E20: =C20*D20 -> 454.63719
B21: =B20+1 -> 2031 | C21: =$D$8*$D$9*(1+$D$10)^(B21-($B$16-1)) -> 796.89142 | D21: =1/(1+$D$13)^(B21-($B$16-1)) -> 0.58651487 | E21: =C21*D21 -> 467.38867
B22: =B21+1 -> 2032 | C22: =$D$8*$D$9*(1+$D$10)^(B22-($B$16-1)) -> 895.43184 | D22: =1/(1+$D$13)^(B22-($B$16-1)) -> 0.53661013 | E22: =C22*D22 -> 480.4978
B23: =B22+1 -> 2033 | C23: =$D$8*$D$9*(1+$D$10)^(B23-($B$16-1)) -> 1006.1574 | D23: =1/(1+$D$13)^(B23-($B$16-1)) -> 0.49095163 | E23: =C23*D23 -> 493.9746
B24: =B23+1 -> 2034 | C24: =$D$8*$D$9*(1+$D$10)^(B24-($B$16-1)) -> 1130.5748 | D24: =1/(1+$D$13)^(B24-($B$16-1)) -> 0.44917807 | E24: =C24*D24 -> 507.8294
B25: =B24+1 -> 2035 | C25: =$D$8*$D$9*(1+$D$10)^(B25-($B$16-1)) -> 1270.3772 | D25: =1/(1+$D$13)^(B25-($B$16-1)) -> 0.41095889 | E25: =C25*D25 -> 522.07279
B26: Terminal Value | C26: =C25*(1+7.4%)/D12 -> 50532.781 | D26: =D25 -> 0.41095889 | E26: =C26*D26 -> 20766.895

Sheet Data >

Sheet RfHistorical
B2: Date | C2: Rate | D2: Open | E2: High | F2: Low | G2: Change % | I2: Year | J2: 10Yr Bond Average Range | L2: Average 10Y Bond Yield - | M2: 20 Years | N2: =AVERAGE(J11:J30) -> 0.074051208
B3: 45992 | C3: 0.06606 | D3: 0.06546 | E3: 0.06668 | F3: 0.06489 | G3: 0.0119 | I3: 1998 | J3: =AVERAGEIFS($C$3:$C$336,$B$3:$B$336,">="&DATE(I3,1,1),$B$3:$B$336,"<="&DATE(I3,12,31)) -> 0.121497
B4: 45962 | C4: 0.06528 | D4: 0.0652 | E4: 0.0655 | F4: 0.0648 | G4: -0.0002 | I4: =I3+1 -> 1999 | J4: =AVERAGEIFS($C$3:$C$336,$B$3:$B$336,">="&DATE(I4,1,1),$B$3:$B$336,"<="&DATE(I4,12,31)) -> 0.11739167 | L4: Average 10Y Bond Yield - | M4: 15 Years | N4: =AVERAGE(J16:J30) -> 0.073223278
B5: 45931 | C5: 0.06529 | D5: 0.0652 | E5: 0.0657 | F5: 0.0648 | G5: -0.0064 | I5: =I4+1 -> 2000 | J5: =AVERAGEIFS($C$3:$C$336,$B$3:$B$336,">="&DATE(I5,1,1),$B$3:$B$336,"<="&DATE(I5,12,31)) -> 0.11044917
B6: 45901 | C6: 0.06571 | D6: 0.0658 | E6: 0.0658 | F6: 0.0645 | G6: -0.0026 | I6: =I5+1 -> 2001 | J6: =AVERAGEIFS($C$3:$C$336,$B$3:$B$336,">="&DATE(I6,1,1),$B$3:$B$336,"<="&DATE(I6,12,31)) -> 0.093700833 | L6: Average 10Y Bond Yield - | M6: 7 Years | N6: =AVERAGE(J24:J30) -> 0.067187619
B7: 45870 | C7: 0.06588 | D7: 0.0636 | E7: 0.0661 | F7: 0.0631 | G7: 0.0332 | I7: =I6+1 -> 2002 | J7: =AVERAGEIFS($C$3:$C$336,$B$3:$B$336,">="&DATE(I7,1,1),$B$3:$B$336,"<="&DATE(I7,12,31)) -> 0.0719525
B8: 45839 | C8: 0.06376 | D8: 0.0629 | E8: 0.0637 | F8: 0.0628 | G8: 0.0095 | I8: =I7+1 -> 2003 | J8: =AVERAGEIFS($C$3:$C$336,$B$3:$B$336,">="&DATE(I8,1,1),$B$3:$B$336,"<="&DATE(I8,12,31)) -> 0.0560475 | L8: Average 10Y Bond Yield - | M8: 5 Years | N8: =AVERAGE(J26:J30) -> 0.068103167
B9: 45809 | C9: 0.06316 | D9: 0.0622 | E9: 0.0631 | F9: 0.0618 | G9: 0.0171 | I9: =I8+1 -> 2004 | J9: =AVERAGEIFS($C$3:$C$336,$B$3:$B$336,">="&DATE(I9,1,1),$B$3:$B$336,"<="&DATE(I9,12,31)) -> 0.059314167
B10: 45778 | C10: 0.0621 | D10: 0.0635 | E10: 0.0639 | F10: 0.0616 | G10: -0.0224 | I10: =I9+1 -> 2005 | J10: =AVERAGEIFS($C$3:$C$336,$B$3:$B$336,">="&DATE(I10,1,1),$B$3:$B$336,"<="&DATE(I10,12,31)) -> 0.06971 | L10: Average 10Y Bond Yield - | M10: Latest | N10: 0.066
B11: 45748 | C11: 0.06352 | D11: 0.0657 | E11: 0.0657 | F11: 0.0631 | G11: -0.0332 | I11: =I10+1 -> 2006 | J11: =AVERAGEIFS($C$3:$C$336,$B$3:$B$336,">="&DATE(I11,1,1),$B$3:$B$336,"<="&DATE(I11,12,31)) -> 0.076628333
B12: 45717 | C12: 0.0657 | D12: 0.0673 | E12: 0.0674 | F12: 0.0657 | G12: -0.0223 | I12: =I11+1 -> 2007 | J12: =AVERAGEIFS($C$3:$C$336,$B$3:$B$336,">="&DATE(I12,1,1),$B$3:$B$336,"<="&DATE(I12,12,31)) -> 0.079529167
B13: 45689 | C13: 0.0672 | D13: 0.0666 | E13: 0.0672 | F13: 0.0665 | G13: 0.0045 | I13: =I12+1 -> 2008 | J13: =AVERAGEIFS($C$3:$C$336,$B$3:$B$336,">="&DATE(I13,1,1),$B$3:$B$336,"<="&DATE(I13,12,31)) -> 0.078546667
B14: 45658 | C14: 0.0669 | D14: 0.0678 | E14: 0.0684 | F14: 0.0667 | G14: -0.0104 | I14: =I13+1 -> 2009 | J14: =AVERAGEIFS($C$3:$C$336,$B$3:$B$336,">="&DATE(I14,1,1),$B$3:$B$336,"<="&DATE(I14,12,31)) -> 0.069485833
B15: 45627 | C15: 0.0676 | D15: 0.06802 | E15: 0.06807 | F15: 0.06668 | G15: 0.0013 | I15: =I14+1 -> 2010 | J15: =AVERAGEIFS($C$3:$C$336,$B$3:$B$336,">="&DATE(I15,1,1),$B$3:$B$336,"<="&DATE(I15,12,31)) -> 0.078485
B16: 45597 | C16: 0.06751 | D16: 0.06831 | E16: 0.06863 | F16: 0.06739 | G16: -0.0132 | I16: =I15+1 -> 2011 | J16: =AVERAGEIFS($C$3:$C$336,$B$3:$B$336,">="&DATE(I16,1,1),$B$3:$B$336,"<="&DATE(I16,12,31)) -> 0.0836575
B17: 45566 | C17: 0.06841 | D17: 0.06759 | E17: 0.06875 | F17: 0.0673 | G17: 0.0135 | I17: =I16+1 -> 2012 | J17: =AVERAGEIFS($C$3:$C$336,$B$3:$B$336,">="&DATE(I17,1,1),$B$3:$B$336,"<="&DATE(I17,12,31)) -> 0.08295
B18: 45536 | C18: 0.0675 | D18: 0.06877 | E18: 0.06885 | F18: 0.06706 | G18: -0.0165 | I18: =I17+1 -> 2013 | J18: =AVERAGEIFS($C$3:$C$336,$B$3:$B$336,">="&DATE(I18,1,1),$B$3:$B$336,"<="&DATE(I18,12,31)) -> 0.081975833
B19: 45505 | C19: 0.06863 | D19: 0.06912 | E19: 0.06919 | F19: 0.06843 | G19: -0.0088 | I19: =I18+1 -> 2014 | J19: =AVERAGEIFS($C$3:$C$336,$B$3:$B$336,">="&DATE(I19,1,1),$B$3:$B$336,"<="&DATE(I19,12,31)) -> 0.085550833
B20: 45474 | C20: 0.06924 | D20: 0.07023 | E20: 0.07024 | F20: 0.0691 | G20: -0.012 | I20: =I19+1 -> 2015 | J20: =AVERAGEIFS($C$3:$C$336,$B$3:$B$336,">="&DATE(I20,1,1),$B$3:$B$336,"<="&DATE(I20,12,31)) -> 0.077501667
B21: 45444 | C21: 0.07008 | D21: 0.06955 | E21: 0.07062 | F21: 0.06945 | G21: 0.0031 | I21: =I20+1 -> 2016 | J21: =AVERAGEIFS($C$3:$C$336,$B$3:$B$336,">="&DATE(I21,1,1),$B$3:$B$336,"<="&DATE(I21,12,31)) -> 0.071738333
B22: 45413 | C22: 0.06986 | D22: 0.0717 | E22: 0.07173 | F22: 0.06967 | G22: -0.029 | I22: =I21+1 -> 2017 | J22: =AVERAGEIFS($C$3:$C$336,$B$3:$B$336,">="&DATE(I22,1,1),$B$3:$B$336,"<="&DATE(I22,12,31)) -> 0.0674725
... B30: 45170 | C30: 0.0721 | D30: 0.07174 | E30: 0.07241 | F30: 0.07086 | G30: 0.0061 | I30: =I29+1 -> 2025 | J30: =AVERAGEIFS($C$3:$C$336,$B$3:$B$336,">="&DATE(I30,1,1),$B$3:$B$336,"<="&DATE(I30,12,31)) -> 0.065046667
B31: 45139 | C31: 0.07166 | D31: 0.07186 | E31: 0.07256 | F31: 0.07147 | G31: -0.0008
B32: 45108 | C32: 0.07172 | D32: 0.07113 | E32: 0.07185 | F32: 0.07047 | G32: 0.0087 | I32: Source: Investing.com
B33: 45078 | C33: 0.0711 | D33: 0.07019 | E33: 0.07117 | F33: 0.06963 | G33: 0.0173
B34: 45047 | C34: 0.06989 | D34: 0.07135 | E34: 0.07138 | F34: 0.06947 | G34: -0.0178
B35: 45017 | C35: 0.07116 | D35: 0.0737 | E35: 0.0737 | F35: 0.07077 | G35: -0.0272
B36: 44986 | C36: 0.07315 | D36: 0.07468 | E36: 0.07473 | F36: 0.0728 | G36: -0.019
B37: 44958 | C37: 0.07457 | D37: 0.07416 | E37: 0.07465 | F37: 0.07245 | G37: 0.0155
B38: 44927 | C38: 0.07343 | D38: 0.07346 | E38: 0.07407 | F38: 0.07266 | G38: 0.0022
B39: 44896 | C39: 0.07327 | D39: 0.07255 | E39: 0.07344 | F39: 0.07181 | G39: 0.0065
B40: 44866 | C40: 0.0728 | D40: 0.07435 | E40: 0.07497 | F40: 0.07235 | G40: -0.0222
B41: 44835 | C41: 0.07445 | D41: 0.07403 | E41: 0.07541 | F41: 0.07361 | G41: 0.0064
B42: 44805 | C42: 0.07398 | D42: 0.0723 | E42: 0.07423 | F42: 0.07106 | G42: 0.0292
B43: 44774 | C43: 0.07188 | D43: 0.07357 | E43: 0.07366 | F43: 0.0711 | G43: -0.018
B44: 44743 | C44: 0.0732 | D44: 0.07427 | E44: 0.07475 | F44: 0.07255 | G44: -0.0174
... B336: 35855 | C336: 0.12086 | D336: 0.12086 | E336: 0.12086 | F336: 0.12086 | G336: -0.0527

Sheet ERPHistorical
B2: Year | C2: Implied ERP | E2: Average implied ERP - | F2: 20 Years | G2: =AVERAGE(C12:C31) -> 0.025095
B3: 1997 | C3: 0.02
B4: 1998 | C4: 0.02 | E4: Average implied ERP - | F4: 15 Years | G4: =AVERAGE(C17:C31) -> 0.0226
B5: 1999 | C5: 0.0197
B6: 2000 | C6: 0.0199 | E6: Average implied ERP - | F6: 7 Years | G6: =AVERAGE(C25:C31) -> 0.0179
B7: 2001 | C7: 0.055
B8: 2002 | C8: 0.0492 | E8: Average implied ERP - | F8: 5 Years | G8: =AVERAGE(C27:C31) -> 0.01658
B9: 2003 | C9: 0.0708
B10: 2004 | C10: 0.0456 | E10: Average implied ERP - | F10: Latest | G10: 0.027
B11: 2005 | C11: 0.0486
B12: 2006 | C12: 0.0318 | E12: Source: Market Premia
B13: 2007 | C13: 0.0308
B14: 2008 | C14: 0.0411
B15: 2009 | C15: 0.0322
B16: 2010 | C16: 0.027
B17: 2011 | C17: 0.0366
B18: 2012 | C18: 0.0365
B19: 2013 | C19: 0.0282
B20: 2014 | C20: 0.0236
B21: 2015 | C21: 0.0256
B22: 2016 | C22: 0.0238
B23: 2017 | C23: 0.0193
B24: 2018 | C24: 0.0201
... B31: 2025 | C31: 0.0167

Sheet 2025-BBdata
B2: Industry name | C2: Number of firms | D2: Dividends | E2: Dividends + Buybacks | F2: Buybacks | G2: Buyback%Dividend | I2: Mean | J2: =AVERAGE(G3:G98) -> 0.36204952
B3: Advertising | C3: 26 | D3: 2.105 | E3: 4.45 | F3: =IF(D3>E3,0,E3-D3) -> 2.345 | G3: =IFERROR(F3/D3,0) -> 1.1140143 | I3: Trimmed Mean | J3: =TRIMMEAN(G3:G96,0.05) -> 0.17037099
B4: Aerospace/Defense | C4: 20 | D4: 585.913 | E4: 585.913 | F4: =IF(D4>E4,0,E4-D4) -> 0 | G4: =IFERROR(F4/D4,0) -> 0
B5: Air Transport | C5: 4 | D5: 0.9558 | E5: 0 | F5: =IF(D5>E5,0,E5-D5) -> 0 | G5: =IFERROR(F5/D5,0) -> 0 | I5: Source: Damodaran
B6: Apparel | C6: 366 | D6: 411.7725 | E6: 549.282 | F6: =IF(D6>E6,0,E6-D6) -> 137.5095 | G6: =IFERROR(F6/D6,0) -> 0.33394532
B7: Auto & Truck | C7: 14 | D7: 3123.5 | E7: 3735.56 | F7: =IF(D7>E7,0,E7-D7) -> 612.06 | G7: =IFERROR(F7/D7,0) -> 0.19595326
B8: Auto Parts | C8: 117 | D8: 584.9963 | E8: 637.278 | F8: =IF(D8>E8,0,E8-D8) -> 52.2817 | G8: =IFERROR(F8/D8,0) -> 0.089370993
B9: Bank (Money Center) | C9: 35 | D9: 6540.409 | E9: 6540.409 | F9: =IF(D9>E9,0,E9-D9) -> 0 | G9: =IFERROR(F9/D9,0) -> 0
B10: Banks (Regional) | C10: 6 | D10: 69.416 | E10: 69.416 | F10: =IF(D10>E10,0,E10-D10) -> 0 | G10: =IFERROR(F10/D10,0) -> 0
B11: Beverage (Alcoholic) | C11: 19 | D11: 129.829 | E11: 129.829 | F11: =IF(D11>E11,0,E11-D11) -> 0 | G11: =IFERROR(F11/D11,0) -> 0
B12: Beverage (Soft) | C12: 5 | D12: 40.578 | E12: 0 | F12: =IF(D12>E12,0,E12-D12) -> 0 | G12: =IFERROR(F12/D12,0) -> 0
B13: Broadcasting | C13: 19 | D13: 91.328 | E13: 79.802 | F13: =IF(D13>E13,0,E13-D13) -> 0 | G13: =IFERROR(F13/D13,0) -> 0
B14: Brokerage & Investment Banking | C14: 176 | D14: 225.75952 | E14: 229.323 | F14: =IF(D14>E14,0,E14-D14) -> 3.56348 | G14: =IFERROR(F14/D14,0) -> 0.015784406
B15: Building Materials | C15: 57 | D15: 90.729 | E15: 128.633 | F15: =IF(D15>E15,0,E15-D15) -> 37.904 | G15: =IFERROR(F15/D15,0) -> 0.41777161
B16: Business & Consumer Services | C16: 72 | D16: 235.686 | E16: 246.02 | F16: =IF(D16>E16,0,E16-D16) -> 10.334 | G16: =IFERROR(F16/D16,0) -> 0.043846474
B17: Cable TV | C17: 8 | D17: 5.772 | E17: 5.772 | F17: =IF(D17>E17,0,E17-D17) -> 0 | G17: =IFERROR(F17/D17,0) -> 0
... B96: Utility (Water) | C96: 1 | D96: 0 | E96: 0 | F96: =IF(D96>E96,0,E96-D96) -> 0 | G96: =IFERROR(F96/D96,0) -> 0

Sheet ExpDiv&BB
B2: Year | C2: Sensex Average Range | D2: Dividend Yield | E2: Dividend Amount | F2: BB Amount | G2: Total Earnings | H2: Sensex Total Earning Yield | J2: Average Sensex Earning Yield - | K2: 20 Years | L2: =AVERAGE(H11:H30) -> 0.014746674
B3: 1998 | C3: =IndexHistorical!G3 -> 847.81545 | D3: =(IndexEPSGrowth!H33)/100 -> 0.023 | E3: =D3*C3 -> 19.499755 | F3: =E3*'2025-BBdata'!$J$3 -> 3.3221926 | G3: =SUM(E3:F3) -> 22.821948 | H3: =G3/C3 -> 0.026918533
B4: 1999 | C4: 1107.6842 | D4: =(IndexEPSGrowth!H34)/100 -> 0.0122 | E4: =D4*C4 -> 13.513747 | F4: =E4*'2025-BBdata'!$J$3 -> 2.3023504 | G4: =SUM(E4:F4) -> 15.816097 | H4: =G4/C4 -> 0.014278526 | J4: Average Sensex Earning Yield - | K4: 15 Years | L4: =AVERAGE(H16:H30) -> 0.015089983
B5: 2000 | C5: 1380.7133 | D5: =(IndexEPSGrowth!H35)/100 -> 0.0124 | E5: =D5*C5 -> 17.120845 | F5: =E5*'2025-BBdata'!$J$3 -> 2.9168953 | G5: =SUM(E5:F5) -> 20.037741 | H5: =G5/C5 -> 0.0145126
B6: 2001 | C6: 968.17583 | D6: =(IndexEPSGrowth!H36)/100 -> 0.021 | E6: =D6*C6 -> 20.331692 | F6: =E6*'2025-BBdata'!$J$3 -> 3.4639305 | G6: =SUM(E6:F6) -> 23.795623 | H6: =G6/C6 -> 0.024577791 | J6: Average Sensex Earning Yield - | K6: 10 Years | L6: =AVERAGE(H21:H30) -> 0.014477489
B7: 2002 | C7: 928.63333 | D7: =(IndexEPSGrowth!H37)/100 -> 0.0287 | E7: =D7*C7 -> 26.651777 | F7: =E7*'2025-BBdata'!$J$3 -> 4.5406895 | G7: =SUM(E7:F7) -> 31.192466 | H7: =G7/C7 -> 0.033589647
B8: 2003 | C8: 1172.2475 | D8: =(IndexEPSGrowth!H38)/100 -> 0.0253 | E8: =D8*C8 -> 29.657862 | F8: =E8*'2025-BBdata'!$J$3 -> 5.0528392 | G8: =SUM(E8:F8) -> 34.710701 | H8: =G8/C8 -> 0.029610386 | J8: Average Sensex Earning Yield - | K8: 7 Years | L8: =AVERAGE(H24:H30) -> 0.014161489
B9: 2004 | C9: 1712.8558 | D9: =(IndexEPSGrowth!H39)/100 -> 0.0223 | E9: =D9*C9 -> 38.196685 | F9: =E9*'2025-BBdata'!$J$3 -> 6.507607 | G9: =SUM(E9:F9) -> 44.704292 | H9: =G9/C9 -> 0.026099273
B10: 2005 | C10: 2315.9992 | D10: =(IndexEPSGrowth!H40)/100 -> 0.0169 | E10: =D10*C10 -> 39.140386 | F10: =E10*'2025-BBdata'!$J$3 -> 6.6683862 | G10: =SUM(E10:F10) -> 45.808772 | H10: =G10/C10 -> 0.01977927 | J10: Average Sensex Earning Yield - | K10: 5 Years | L10: =AVERAGE(H26:H30) -> 0.014301933
B11: 2006 | C11: 3468.9908 | D11: =(IndexEPSGrowth!H41)/100 -> 0.0137 | E11: =D11*C11 -> 47.525174 | F11: =E11*'2025-BBdata'!$J$3 -> 8.0969109 | G11: =SUM(E11:F11) -> 55.622085 | H11: =G11/C11 -> 0.016034083
B12: 2007 | C12: 4791.0983 | D12: =(IndexEPSGrowth!H42)/100 -> 0.0097 | E12: =D12*C12 -> 46.473654 | F12: =E12*'2025-BBdata'!$J$3 -> 7.9177623 | G12: =SUM(E12:F12) -> 54.391416 | H12: =G12/C12 -> 0.011352599 | J12: Average Sensex Earning Yield - | K12: 3 Years | L12: =AVERAGE(H28:H30) -> 0.014356551
B13: 2008 | C13: 4269.5325 | D13: =(IndexEPSGrowth!H43)/100 -> 0.0143 | E13: =D13*C13 -> 61.054315 | F13: =E13*'2025-BBdata'!$J$3 -> 10.401884 | G13: =SUM(E13:F13) -> 71.456199 | H13: =G13/C13 -> 0.016736305
B14: 2009 | C14: 4207.6492 | D14: =(IndexEPSGrowth!H44)/100 -> 0.0111 | E14: =D14*C14 -> 46.704906 | F14: =E14*'2025-BBdata'!$J$3 -> 7.9571609 | G14: =SUM(E14:F14) -> 54.662067 | H14: =G14/C14 -> 0.012991118
B15: 2010 | C15: 5608.4517 | D15: =(IndexEPSGrowth!H45)/100 -> 0.0098 | E15: =D15*C15 -> 54.962826 | F15: =E15*'2025-BBdata'!$J$3 -> 9.364071 | G15: =SUM(E15:F15) -> 64.326897 | H15: =G15/C15 -> 0.011469636
B16: 2011 | C16: 5354.1158 | D16: =(IndexEPSGrowth!H46)/100 -> 0.0133 | E16: =D16*C16 -> 71.209741 | F16: =E16*'2025-BBdata'!$J$3 -> 12.132074 | G16: =SUM(E16:F16) -> 83.341814 | H16: =G16/C16 -> 0.015565934
B17: 2012 | C17: 5425.1117 | D17: =(IndexEPSGrowth!H47)/100 -> 0.0158 | E17: =D17*C17 -> 85.716764 | F17: =E17*'2025-BBdata'!$J$3 -> 14.60365 | G17: =SUM(E17:F17) -> 100.32041 | H17: =G17/C17 -> 0.018491862
B18: 2013 | C18: 5906.4958 | D18: =(IndexEPSGrowth!H48)/100 -> 0.0149 | E18: =D18*C18 -> 88.006788 | F18: =E18*'2025-BBdata'!$J$3 -> 14.993803 | G18: =SUM(E18:F18) -> 103.00059 | H18: =G18/C18 -> 0.017438528
B19: 2014 | C19: 7503.9292 | D19: =(IndexEPSGrowth!H49)/100 -> 0.0122 | E19: =D19*C19 -> 91.547936 | F19: =E19*'2025-BBdata'!$J$3 -> 15.597112 | G19: =SUM(E19:F19) -> 107.14505 | H19: =G19/C19 -> 0.014278526
B20: 2015 | C20: 8422.1225 | D20: =(IndexEPSGrowth!H50)/100 -> 0.0135 | E20: =D20*C20 -> 113.69865 | F20: =E20*'2025-BBdata'!$J$3 -> 19.370952 | G20: =SUM(E20:F20) -> 133.06961 | H20: =G20/C20 -> 0.015800008
B21: 2016 | C21: 8314.9083 | D21: =(IndexEPSGrowth!H51)/100 -> 0.0135 | E21: =D21*C21 -> 112.25126 | F21: =E21*'2025-BBdata'!$J$3 -> 19.124358 | G21: =SUM(E21:F21) -> 131.37562 | H21: =G21/C21 -> 0.015800008
B22: 2017 | C22: 10033.375 | D22: =(IndexEPSGrowth!H52)/100 -> 0.0129 | E22: =D22*C22 -> 129.43054 | F22: =E22*'2025-BBdata'!$J$3 -> 22.051208 | G22: =SUM(E22:F22) -> 151.48175 | H22: =G22/C22 -> 0.015097786
B23: 2018 | C23: 11141.15 | D23: =(IndexEPSGrowth!H53)/100 -> 0.0126 | E23: =D23*C23 -> 140.37849 | F23: =E23*'2025-BBdata'!$J$3 -> 23.916422 | G23: =SUM(E23:F23) -> 164.29491 | H23: =G23/C23 -> 0.014746674
B24: 2019 | C24: 11665.345 | D24: =(IndexEPSGrowth!H54)/100 -> 0.0127 | E24: =D24*C24 -> 148.14988 | F24: =E24*'2025-BBdata'!$J$3 -> 25.240442 | G24: =SUM(E24:F24) -> 173.39032 | H24: =G24/C24 -> 0.014863712
... B30: 2025 | C30: 25778.28 | D30: =(IndexEPSGrowth!H60)/100 -> 0.012 | E30: =D30*C30 -> 309.33936 | F30: =E30*'2025-BBdata'!$J$3 -> 52.702452 | G30: =SUM(E30:F30) -> 362.04181 | H30: =G30/C30 -> 0.014044452
F32: BB Yield
B33: CAGR | F33: =F3/C3 -> 0.0039185327
F34: =F4/C4 -> 0.002078526
F35: =F5/C5 -> 0.0021126002
F36: =F6/C6 -> 0.0035777907
F37: =F7/C7 -> 0.0048896473
F38: =F8/C8 -> 0.004310386
F39: =F9/C9 -> 0.003799273
F40: =F10/C10 -> 0.0028792697
F41: =F11/C11 -> 0.0023340825
F42: =F12/C12 -> 0.0016525986
F43: =F13/C13 -> 0.0024363051
F44: =F14/C14 -> 0.001891118
F45: =F15/C15 -> 0.0016696357
... F60: =F30/C30 -> 0.0020444518

Sheet IndexEPSGrowth
B2: Year | C2: Index Average Range | D2: PE Ratios | E2: Index EPS | F2: EPS CAGR 3Yr | G2: EPS CAGR 5Yr | H2: EPS CAGR 7Yr | I2: EPS CAGR 10Yr
B3: 1998 | C3: =IndexHistorical!G3 -> 847.81545 | D3: =F33 -> 11.43 | E3: =C3/D3 -> 74.17458 | K3: Average EPS CAGR - | L3: 10 Years | M3: =AVERAGE(F6:F30) -> 0.12365602
B4: 1999 | C4: =IndexHistorical!G4 -> 1107.6842 | D4: =F34 -> 23.57 | E4: =C4/D4 -> 46.99551
B5: 2000 | C5: =IndexHistorical!G5 -> 1380.7133 | D5: =F35 -> 24.2 | E5: =C5/D5 -> 57.05427 | K5: Average EPS CAGR - | L5: 7 Years | M5: =AVERAGE(G7:G30) -> 0.12232652
B6: 2001 | C6: =IndexHistorical!G6 -> 968.17583 | D6: =F36 -> 15.1 | E6: =C6/D6 -> 64.117605 | F6: =_xlfn.RRI(3,E3,E6) -> -0.047406975
B7: 2002 | C7: =IndexHistorical!G7 -> 928.63333 | D7: =F37 -> 12.49 | E7: =C7/D7 -> 74.350147 | F7: =_xlfn.RRI(3,E4,E7) -> 0.1652215 | K7: Average EPS CAGR - | L7: 5 Years | M7: =AVERAGE(H6:H30) -> 0.11590327
B8: 2003 | C8: =IndexHistorical!G8 -> 1172.2475 | D8: =F38 -> 14.19 | E8: =C8/D8 -> 82.610817 | F8: =_xlfn.RRI(3,E5,E8) -> 0.13131338 | G8: =_xlfn.RRI(5,E3,E8) -> 0.021777569
B9: 2004 | C9: =IndexHistorical!G9 -> 1712.8558 | D9: =F39 -> 14.04 | E9: =C9/D9 -> 121.99828 | F9: =_xlfn.RRI(3,E6,E9) -> 0.23915454 | G9: =_xlfn.RRI(5,E4,E9) -> 0.21020646 | K9: Average EPS CAGR - | L9: 3 Years | M9: =AVERAGE(I6:I30) -> 0.10884144
B10: 2005 | C10: =IndexHistorical!G10 -> 2315.9992 | D10: =F40 -> 15.3 | E10: =C10/D10 -> 151.37249 | F10: =_xlfn.RRI(3,E7,E10) -> 0.26742338 | G10: =_xlfn.RRI(5,E5,E10) -> 0.21549104 | H10: =_xlfn.RRI(7,E3,E10) -> 0.10727624 | K10: Source: BSE
B11: 2006 | C11: =IndexHistorical!G11 -> 3468.9908 | D11: =F41 -> 19.08 | E11: =C11/D11 -> 181.81294 | F11: =_xlfn.RRI(3,E8,E11) -> 0.30075635 | G11: =_xlfn.RRI(5,E6,E11) -> 0.23176965 | H11: =_xlfn.RRI(7,E4,E11) -> 0.2132166
B12: 2007 | C12: =IndexHistorical!G12 -> 4791.0983 | D12: =F42 -> 22.43 | E12: =C12/D12 -> 213.60224 | F12: =_xlfn.RRI(3,E9,E12) -> 0.20526914 | G12: =_xlfn.RRI(5,E7,E12) -> 0.23499385 | H12: =_xlfn.RRI(7,E5,E12) -> 0.20754277
B13: 2008 | C13: =IndexHistorical!G13 -> 4269.5325 | D13: =F43 -> 16.72 | E13: =C13/D13 -> 255.35481 | F13: =_xlfn.RRI(3,E10,E13) -> 0.19041675 | G13: =_xlfn.RRI(5,E8,E13) -> 0.253203 | H13: =_xlfn.RRI(7,E6,E13) -> 0.21825474 | I13: =_xlfn.RRI(10,E3,E13) -> 0.13158946
B14: 2009 | C14: =IndexHistorical!G14 -> 4207.6492 | D14: =F44 -> 21.27 | E14: =C14/D14 -> 197.82084 | F14: =_xlfn.RRI(3,E11,E14) -> 0.028527125 | G14: =_xlfn.RRI(5,E9,E14) -> 0.10149788 | H14: =_xlfn.RRI(7,E7,E14) -> 0.15003984 | I14: =_xlfn.RRI(10,E4,E14) -> 0.15457345
B15: 2010 | C15: =IndexHistorical!G15 -> 5608.4517 | D15: =F45 -> 21.91 | E15: =C15/D15 -> 255.9768 | F15: =_xlfn.RRI(3,E12,E15) -> 0.062180354 | G15: =_xlfn.RRI(5,E10,E15) -> 0.11078684 | H15: =_xlfn.RRI(7,E8,E15) -> 0.17534737 | I15: =_xlfn.RRI(10,E5,E15) -> 0.16196018
B16: 2011 | C16: =IndexHistorical!G16 -> 5354.1158 | D16: =F46 -> 18.68 | E16: =C16/D16 -> 286.6229 | F16: =_xlfn.RRI(3,E13,E16) -> 0.039255377 | G16: =_xlfn.RRI(5,E11,E16) -> 0.095310426 | H16: =_xlfn.RRI(7,E9,E16) -> 0.12978 | I16: =_xlfn.RRI(10,E6,E16) -> 0.16153783
B17: 2012 | C17: =IndexHistorical!G17 -> 5425.1117 | D17: =F47 -> 17.94 | E17: =C17/D17 -> 302.4031 | F17: =_xlfn.RRI(3,E14,E17) -> 0.15196178 | G17: =_xlfn.RRI(5,E12,E17) -> 0.072003212 | H17: =_xlfn.RRI(7,E10,E17) -> 0.10391131 | I17: =_xlfn.RRI(10,E7,E17) -> 0.15061609
B18: 2013 | C18: =IndexHistorical!G18 -> 5906.4958 | D18: =F48 -> 16.47 | E18: =C18/D18 -> 358.62148 | F18: =_xlfn.RRI(3,E15,E18) -> 0.11895314 | G18: =_xlfn.RRI(5,E13,E18) -> 0.070282564 | H18: =_xlfn.RRI(7,E11,E18) -> 0.10190589 | I18: =_xlfn.RRI(10,E8,E18) -> 0.158137
B19: 2014 | C19: =IndexHistorical!G19 -> 7503.9292 | D19: =F49 -> 18.81 | E19: =C19/D19 -> 398.93297 | F19: =_xlfn.RRI(3,E16,E19) -> 0.11651102 | G19: =_xlfn.RRI(5,E14,E19) -> 0.15060321 | H19: =_xlfn.RRI(7,E12,E19) -> 0.093342683 | I19: =_xlfn.RRI(10,E9,E19) -> 0.12578284
B20: 2015 | C20: =IndexHistorical!G20 -> 8422.1225 | D20: =F50 -> 20.63 | E20: =C20/D20 -> 408.24636 | F20: =_xlfn.RRI(3,E17,E20) -> 0.10521141 | G20: =_xlfn.RRI(5,E15,E20) -> 0.097853383 | H20: =_xlfn.RRI(7,E13,E20) -> 0.069328599 | I20: =_xlfn.RRI(10,E10,E20) -> 0.10430118
B21: 2016 | C21: =IndexHistorical!G21 -> 8314.9083 | D21: =F51 -> 22.63 | E21: =C21/D21 -> 367.42856 | F21: =_xlfn.RRI(3,E18,E21) -> 0.0081199356 | G21: =_xlfn.RRI(5,E16,E21) -> 0.050926647 | H21: =_xlfn.RRI(7,E14,E21) -> 0.092482305 | I21: =_xlfn.RRI(10,E11,E21) -> 0.07288905
B22: 2017 | C22: =IndexHistorical!G22 -> 10033.375 | D22: =F52 -> 24.01 | E22: =C22/D22 -> 417.88317 | F22: =_xlfn.RRI(3,E19,E22) -> 0.015589771 | G22: =_xlfn.RRI(5,E17,E22) -> 0.066826336 | H22: =_xlfn.RRI(7,E15,E22) -> 0.072525815 | I22: =_xlfn.RRI(10,E12,E22) -> 0.069411641
B23: 2018 | C23: =IndexHistorical!G23 -> 11141.15 | D23: =F53 -> 22.94 | E23: =C23/D23 -> 485.66478 | F23: =_xlfn.RRI(3,E20,E23) -> 0.059590593 | G23: =_xlfn.RRI(5,E18,E23) -> 0.062527211 | H23: =_xlfn.RRI(7,E16,E23) -> 0.078246258 | I23: =_xlfn.RRI(10,E13,E23) -> 0.066397837
B24: 2019 | C24: =IndexHistorical!G24 -> 11665.345 | D24: =F54 -> 24.41 | E24: =C24/D24 -> 477.89205 | F24: =_xlfn.RRI(3,E21,E24) -> 0.091571778 | G24: =_xlfn.RRI(5,E19,E24) -> 0.036778483 | H24: =_xlfn.RRI(7,E17,E24) -> 0.067559127 | I24: =_xlfn.RRI(10,E14,E24) -> 0.092209067
... B30: 2025 | C30: =IndexHistorical!G30 -> 25778.28 | D30: =F60 -> 22.91 | E30: =C30/D30 -> 1125.1977 | F30: =_xlfn.RRI(3,E27,E30) -> 0.13239173 | G30: =_xlfn.RRI(5,E25,E30) -> 0.23096167 | H30: =_xlfn.RRI(7,E23,E30) -> 0.12752833 | I30: =_xlfn.RRI(10,E20,E30) -> 0.10670189
B32: Year | C32: High | D32: Low | E32: Close | F32: PE Ratios | G32: PB Ratios | H32: Dividend Yield
B33: 1998 | C33: 1107.06 | D33: 711.47 | E33: 957.79 | F33: 11.43 | G33: 1.47 | H33: 2.3
B34: 1999 | C34: 2265.72 | D34: 800.23 | E34: 1683.28 | F34: 23.57 | G34: 2.81 | H34: 1.22
B35: 2000 | C35: 1771.98 | D35: 947.66 | E35: 981.19 | F35: 24.2 | G35: 2.59 | H35: 1.24
B36: 2001 | C36: 1061.97 | D36: 701.76 | E36: 995.44 | F36: 15.1 | G36: 1.72 | H36: 2.1
B37: 2002 | C37: 1022.82 | D37: 818.57 | E37: 870.42 | F37: 12.49 | G37: 1.71 | H37: 2.87
B38: 2003 | C38: 1956.48 | D38: 838.99 | E38: 1720.46 | F38: 14.19 | G38: 2.51 | H38: 2.53
B39: 2004 | C39: 2178.52 | D39: 1291.29 | E39: 2019.48 | F39: 14.04 | G39: 2.92 | H39: 2.23
B40: 2005 | C40: 3447.13 | D40: 1914.25 | E40: 3424.42 | F40: 15.3 | G40: 3.56 | H40: 1.69
B41: 2006 | C41: 4317.68 | D41: 2593.48 | E41: 3820.58 | F41: 19.08 | G41: 4.24 | H41: 1.37
B42: 2007 | C42: 6760.43 | D42: 3637.16 | E42: 4775.04 | F42: 22.43 | G42: 5.35 | H42: 0.97
B43: 2008 | C43: 5470.85 | D43: 2290.5 | E43: 2866.66 | F43: 16.72 | G43: 3.3 | H43: 1.43
B44: 2009 | C44: 5479.32 | D44: 2825.37 | E44: 5394.12 | F44: 21.27 | G44: 3.77 | H44: 1.11
... B60: 2025 | C60: 27592.55 | D60: 22539.11 | E60: 27577.11 | F60: 22.91 | G60: 4.15 | H60: 1.2

Sheet IndexHistorical
B2: Month | C2: Closing Price | D2: Monthly Returns | F2: Year | G2: Sensex Average Range | H2: Average Returns | J2: CAGR Sensex Returns - | K2: 20 Years | L2: =_xlfn.RRI(20,G10,$G$30) -> 0.12804332
B3: 35796 | C3: 812.8 | F3: 1998 | G3: =AVERAGEIFS($C$4:$C$338,$B$4:$B$338,">="&DATE(F3,1,1),$B$4:$B$338,"<="&DATE(F3,12,31)) -> 847.81545
B4: 35827 | C4: 909.92 | D4: =C4/C3-1 -> 0.11948819 | F4: =F3+1 -> 1999 | G4: =AVERAGEIFS($C$4:$C$338,$B$4:$B$338,">="&DATE(F4,1,1),$B$4:$B$338,"<="&DATE(F4,12,31)) -> 1107.6842 | H4: =G4/G3-1 -> 0.30651566 | J4: CAGR Sensex Returns - | K4: 15 Years | L4: =_xlfn.RRI(15,G15,$G$30) -> 0.10703342
B5: 35855 | C5: 984.34 | D5: =C5/C4-1 -> 0.08178741 | F5: =F4+1 -> 2000 | G5: =AVERAGEIFS($C$4:$C$338,$B$4:$B$338,">="&DATE(F5,1,1),$B$4:$B$338,"<="&DATE(F5,12,31)) -> 1380.7133 | H5: =G5/G4-1 -> 0.24648648
B6: 35886 | C6: 1021.36 | D6: =C6/C5-1 -> 0.037608956 | F6: =F5+1 -> 2001 | G6: =AVERAGEIFS($C$4:$C$338,$B$4:$B$338,">="&DATE(F6,1,1),$B$4:$B$338,"<="&DATE(F6,12,31)) -> 968.17583 | H6: =G6/G5-1 -> -0.29878577 | J6: CAGR Sensex Returns - | K6: 10 Years | L6: =_xlfn.RRI(10,G20,$G$30) -> 0.11836415
B7: 35916 | C7: 953.6 | D7: =C7/C6-1 -> -0.066342915 | F7: =F6+1 -> 2002 | G7: =AVERAGEIFS($C$4:$C$338,$B$4:$B$338,">="&DATE(F7,1,1),$B$4:$B$338,"<="&DATE(F7,12,31)) -> 928.63333 | H7: =G7/G6-1 -> -0.040842271
B8: 35947 | C8: 827.79 | D8: =C8/C7-1 -> -0.13193163 | F8: =F7+1 -> 2003 | G8: =AVERAGEIFS($C$4:$C$338,$B$4:$B$338,">="&DATE(F8,1,1),$B$4:$B$338,"<="&DATE(F8,12,31)) -> 1172.2475 | H8: =G8/G7-1 -> 0.26233623 | J8: CAGR Sensex Returns - | K8: 7 Years | L8: =_xlfn.RRI(7,G23,$G$30) -> 0.12731756
B9: 35977 | C9: 821.67 | D9: =C9/C8-1 -> -0.0073931794 | F9: =F8+1 -> 2004 | G9: =AVERAGEIFS($C$4:$C$338,$B$4:$B$338,">="&DATE(F9,1,1),$B$4:$B$338,"<="&DATE(F9,12,31)) -> 1712.8558 | H9: =G9/G8-1 -> 0.46117252
B10: 36008 | C10: 760.15 | D10: =C10/C9-1 -> -0.074871907 | F10: =F9+1 -> 2005 | G10: =AVERAGEIFS($C$4:$C$338,$B$4:$B$338,">="&DATE(F10,1,1),$B$4:$B$338,"<="&DATE(F10,12,31)) -> 2315.9992 | H10: =G10/G9-1 -> 0.35212732 | J10: CAGR Sensex Returns - | K10: 5 Years | L10: =_xlfn.RRI(5,G25,$G$30) -> 0.18036172
B11: 36039 | C11: 800.27 | D11: =C11/C10-1 -> 0.052779057 | F11: =F10+1 -> 2006 | G11: =AVERAGEIFS($C$4:$C$338,$B$4:$B$338,">="&DATE(F11,1,1),$B$4:$B$338,"<="&DATE(F11,12,31)) -> 3468.9908 | H11: =G11/G10-1 -> 0.49783769 | J11: Source: BSE
B12: 36069 | C12: 731.25 | D12: =C12/C11-1 -> -0.086245892 | F12: =F11+1 -> 2007 | G12: =AVERAGEIFS($C$4:$C$338,$B$4:$B$338,">="&DATE(F12,1,1),$B$4:$B$338,"<="&DATE(F12,12,31)) -> 4791.0983 | H12: =G12/G11-1 -> 0.38112165
B13: 36100 | C13: 727.38 | D13: =C13/C12-1 -> -0.0052923077 | F13: =F12+1 -> 2008 | G13: =AVERAGEIFS($C$4:$C$338,$B$4:$B$338,">="&DATE(F13,1,1),$B$4:$B$338,"<="&DATE(F13,12,31)) -> 4269.5325 | H13: =G13/G12-1 -> -0.10886143
B14: 36130 | C14: 788.24 | D14: =C14/C13-1 -> 0.083670159 | F14: =F13+1 -> 2009 | G14: =AVERAGEIFS($C$4:$C$338,$B$4:$B$338,">="&DATE(F14,1,1),$B$4:$B$338,"<="&DATE(F14,12,31)) -> 4207.6492 | H14: =G14/G13-1 -> -0.014494171
B15: 36161 | C15: 847.68 | D15: =C15/C14-1 -> 0.075408505 | F15: =F14+1 -> 2010 | G15: =AVERAGEIFS($C$4:$C$338,$B$4:$B$338,">="&DATE(F15,1,1),$B$4:$B$338,"<="&DATE(F15,12,31)) -> 5608.4517 | H15: =G15/G14-1 -> 0.33291808
B16: 36192 | C16: 874.03 | D16: =C16/C15-1 -> 0.031084843 | F16: =F15+1 -> 2011 | G16: =AVERAGEIFS($C$4:$C$338,$B$4:$B$338,">="&DATE(F16,1,1),$B$4:$B$338,"<="&DATE(F16,12,31)) -> 5354.1158 | H16: =G16/G15-1 -> -0.045348672
B17: 36220 | C17: 957.79 | D17: =C17/C16-1 -> 0.095831951 | F17: =F16+1 -> 2012 | G17: =AVERAGEIFS($C$4:$C$338,$B$4:$B$338,">="&DATE(F17,1,1),$B$4:$B$338,"<="&DATE(F17,12,31)) -> 5425.1117 | H17: =G17/G16-1 -> 0.013260048
B18: 36251 | C18: 840.79 | D18: =C18/C17-1 -> -0.12215621 | F18: =F17+1 -> 2013 | G18: =AVERAGEIFS($C$4:$C$338,$B$4:$B$338,">="&DATE(F18,1,1),$B$4:$B$338,"<="&DATE(F18,12,31)) -> 5906.4958 | H18: =G18/G17-1 -> 0.088732582
B19: 36281 | C19: 994.13 | D19: =C19/C18-1 -> 0.1823761 | F19: =F18+1 -> 2014 | G19: =AVERAGEIFS($C$4:$C$338,$B$4:$B$338,">="&DATE(F19,1,1),$B$4:$B$338,"<="&DATE(F19,12,31)) -> 7503.9292 | H19: =G19/G18-1 -> 0.27045365
B20: 36312 | C20: 1038.5 | D20: =C20/C19-1 -> 0.04463199 | F20: =F19+1 -> 2015 | G20: =AVERAGEIFS($C$4:$C$338,$B$4:$B$338,">="&DATE(F20,1,1),$B$4:$B$338,"<="&DATE(F20,12,31)) -> 8422.1225 | H20: =G20/G19-1 -> 0.12236167
B21: 36342 | C21: 1153.07 | D21: =C21/C20-1 -> 0.11032258 | F21: =F20+1 -> 2016 | G21: =AVERAGEIFS($C$4:$C$338,$B$4:$B$338,">="&DATE(F21,1,1),$B$4:$B$338,"<="&DATE(F21,12,31)) -> 8314.9083 | H21: =G21/G20-1 -> -0.012730065
B22: 36373 | C22: 1271.91 | D22: =C22/C21-1 -> 0.10306399 | F22: =F21+1 -> 2017 | G22: =AVERAGEIFS($C$4:$C$338,$B$4:$B$338,">="&DATE(F22,1,1),$B$4:$B$338,"<="&DATE(F22,12,31)) -> 10033.375 | H22: =G22/G21-1 -> 0.20667295
B23: 36404 | C23: 1283.73 | D23: =C23/C22-1 -> 0.0092931104 | F23: =F22+1 -> 2018 | G23: =AVERAGEIFS($C$4:$C$338,$B$4:$B$338,">="&DATE(F23,1,1),$B$4:$B$338,"<="&DATE(F23,12,31)) -> 11141.15 | H23: =G23/G22-1 -> 0.11040901
... B30: 36617 | C30: 1389.81 | D30: =C30/C29-1 -> -0.17434414 | F30: =F29+1 -> 2025 | G30: =AVERAGEIFS($C$4:$C$338,$B$4:$B$338,">="&DATE(F30,1,1),$B$4:$B$338,"<="&DATE(F30,12,31)) -> 25778.28 | H30: =G30/G29-1 -> 0.037036535
B31: 36647 | C31: 1251.05 | D31: =C31/C30-1 -> -0.099840985
B32: 36678 | C32: 1390.29 | D32: =C32/C31-1 -> 0.11129851
B33: 36708 | C33: 1248.89 | D33: =C33/C32-1 -> -0.1017054
B34: 36739 | C34: 1337.52 | D34: =C34/C33-1 -> 0.070967019
B35: 36770 | C35: 1203.89 | D35: =C35/C34-1 -> -0.099908786
B36: 36800 | C36: 1111.85 | D36: =C36/C35-1 -> -0.076452168
B37: 36831 | C37: 1195.48 | D37: =C37/C36-1 -> 0.075216981
B38: 36861 | C38: 1178.68 | D38: =C38/C37-1 -> -0.014052933
B39: 36892 | C39: 1281.4 | D39: =C39/C38-1 -> 0.087148335
B40: 36923 | C40: 1241.04 | D40: =C40/C39-1 -> -0.0314968
B41: 36951 | C41: 981.19 | D41: =C41/C40-1 -> -0.20938084
B42: 36982 | C42: 975.57 | D42: =C42/C41-1 -> -0.0057277388
... B338: 45992 | C338: 27344.72 | D338: =C338/C337-1 -> -0.0025570111
