Workbook

Sheet Comps_Val_ITC
B2: Comparable Company Valuation
B3: =ITC_Data!C3 -> ITC
B4: Amount in crores (INR)
D6: Market Data | J6: Financials | N6: Valuation
B7: Company | D7: Share Price | E7: Shares Outstanding | F7: Equity Value | G7: Net Debt | H7: Enterprise Value | J7: Revenue | K7: EBITDA | L7: Net Income | N7: EV/Revenue | O7: EV/EBITDA | P7: P/E
B9: =ITC_Data!C3 -> ITC | D9: 407 | E9: =ITC_Data!E3 -> 1252.36 | F9: =D9*E9 -> 509710.52 | G9: =ITC_Data!I3 -> -3727.82 | H9: =SUM(F9:G9) -> 505982.7 | J9: =ITC_Data!K3 -> 79040.32 | K9: =ITC_Data!L3 -> 28954.46 | L9: =ITC_Data!M3 -> 35218.9 | N9: =$H9/J9 -> 6.4015771 | O9: =IF($H9/K9>0,$H9/K9,0) -> 17.475121 | P9: =IF(F9/L9>0,F9/L9,"-") -> 14.472642
B10: =ITC_Data!C4 -> Godfrey Phillips | D10: =ITC_Data!D4 -> 8983.5 | E10: =ITC_Data!E4 -> 5.2 | F10: =D10*E10 -> 46714.2 | G10: =ITC_Data!I4 -> 148.66 | H10: =SUM(F10:G10) -> 46862.86 | J10: =ITC_Data!K4 -> 6032.39 | K10: =ITC_Data!L4 -> 1714.83 | L10: =ITC_Data!M4 -> 1200.04 | N10: =$H10/J10 -> 7.7685395 | O10: =IF($H10/K10>0,$H10/K10,0) -> 27.327992 | P10: =IF(F10/L10>0,F10/L10,"-") -> 38.927202
B11: =ITC_Data!C5 -> Elitecon Inter. | D11: =ITC_Data!D5 -> 213.7 | E11: =ITC_Data!E5 -> 159.85 | F11: =D11*E11 -> 34159.945 | G11: =ITC_Data!I5 -> -0.16 | H11: =SUM(F11:G11) -> 34159.785 | J11: =ITC_Data!K5 -> 548.76 | K11: =ITC_Data!L5 -> 71.61 | L11: =ITC_Data!M5 -> 69.65 | N11: =$H11/J11 -> 62.249043 | O11: =IF($H11/K11>0,$H11/K11,0) -> 477.02535 | P11: =IF(F11/L11>0,F11/L11,"-") -> 490.45147
B12: =ITC_Data!C6 -> VST Industries | D12: =ITC_Data!D6 -> 282 | E12: =ITC_Data!E6 -> 16.99 | F12: =D12*E12 -> 4791.18 | G12: =ITC_Data!I6 -> -17.55 | H12: =SUM(F12:G12) -> 4773.63 | J12: =ITC_Data!K6 -> 1374.32 | K12: =ITC_Data!L6 -> 318.99 | L12: =ITC_Data!M6 -> 292.95 | N12: =$H12/J12 -> 3.4734487 | O12: =IF($H12/K12>0,$H12/K12,0) -> 14.964826 | P12: =IF(F12/L12>0,F12/L12,"-") -> 16.354941
B13: =ITC_Data!C7 -> NTC Industries | D13: =ITC_Data!D7 -> 169.7 | E13: =ITC_Data!E7 -> 1.45 | F13: =D13*E13 -> 246.065 | G13: =ITC_Data!I7 -> 75.57 | H13: =SUM(F13:G13) -> 321.635 | J13: =ITC_Data!K7 -> 60.09 | K13: =ITC_Data!L7 -> 21.8 | L13: =ITC_Data!M7 -> 11.37 | N13: =$H13/J13 -> 5.3525545 | O13: =IF($H13/K13>0,$H13/K13,0) -> 14.753899 | P13: =IF(F13/L13>0,F13/L13,0) -> 21.641601
B14: =ITC_Data!C8 -> Sinnar Bidi Udy. | D14: =ITC_Data!D8 -> 997.15 | E14: =ITC_Data!E8 -> 0.04 | F14: =D14*E14 -> 39.886 | G14: =ITC_Data!I8 -> -2.82 | H14: =SUM(F14:G14) -> 37.066 | J14: =ITC_Data!K8 -> 4.73 | K14: =ITC_Data!L8 -> -0.12 | L14: =ITC_Data!M8 -> -0.12 | N14: =$H14/J14 -> 7.8363636 | O14: =IF($H14/K14>0,$H14/K14,0) -> 0 | P14: =IF(F14/L14>0,F14/L14,0) -> 0
B15: =ITC_Data!C9 -> Shanthala FMCG | D15: =ITC_Data!D9 -> 35 | E15: =ITC_Data!E9 -> 0.67 | F15: =D15*E15 -> 23.45 | G15: =ITC_Data!I9 -> -2.06 | H15: =SUM(F15:G15) -> 21.39 | J15: =ITC_Data!K9 -> 52.75 | K15: =ITC_Data!L9 -> 1.37 | L15: =ITC_Data!M9 -> 0.97 | N15: =$H15/J15 -> 0.40549763 | O15: =IF($H15/K15>0,$H15/K15,0) -> 15.613139 | P15: =IF(F15/L15>0,F15/L15,"-") -> 24.175258
B16: =ITC_Data!C10 -> Raghunath Intl. | D16: =ITC_Data!D10 -> 13.3 | E16: =ITC_Data!E10 -> 0.5 | F16: =D16*E16 -> 6.65 | G16: =ITC_Data!I10 -> -0.22 | H16: =SUM(F16:G16) -> 6.43 | J16: =ITC_Data!K10 -> 0.28 | K16: =ITC_Data!L10 -> 3.04 | L16: =ITC_Data!M10 -> 2.53 | N16: =$H16/J16 -> 22.964286 | O16: =IF($H16/K16>0,$H16/K16,0) -> 2.1151316 | P16: =IF(F16/L16>0,F16/L16,"-") -> 2.6284585
B17: =ITC_Data!C11 -> Shanthala FMCG | D17: =ITC_Data!D11 -> 35 | E17: =ITC_Data!E11 -> 0.67 | F17: =D17*E17 -> 23.45 | G17: =ITC_Data!I11 -> -2.06 | H17: =SUM(F17:G17) -> 21.39 | J17: =ITC_Data!K11 -> 52.75 | K17: =ITC_Data!L11 -> 1.37 | L17: =ITC_Data!M11 -> 0.97 | N17: =$H17/J17 -> 0.40549763 | O17: =IF($H17/K17>0,$H17/K17,0) -> 15.613139 | P17: =IF(F17/L17>0,F17/L17,"-") -> 24.175258
B18: =ITC_Data!C12 -> Raghunath Intl. | D18: =ITC_Data!D12 -> 13.3 | E18: =ITC_Data!E12 -> 0.5 | F18: =D18*E18 -> 6.65 | G18: =ITC_Data!I12 -> -0.22 | H18: =SUM(F18:G18) -> 6.43 | J18: =ITC_Data!K12 -> 0.28 | K18: =ITC_Data!L12 -> 3.04 | L18: =ITC_Data!M12 -> 2.53 | N18: =$H18/J18 -> 22.964286 | O18: =IF($H18/K18>0,$H18/K18,0) -> 2.1151316 | P18: =IF(F18/L18>0,F18/L18,"-") -> 2.6284585
B20: High | N20: =MAX(N$9:N$18) -> 62.249043 | O20: =MAX(O$9:O$18) -> 477.02535 | P20: =MAX(P$9:P$18) -> 490.45147
B21: 75th Percentile | N21: =QUARTILE(N$9:N$18,3) -> 19.182305 | O21: =QUARTILE(O$9:O$18,3) -> 17.009626 | P21: =QUARTILE(P$9:P$18,3) -> 24.175258
B22: Average | N22: =AVERAGE(N$9:N$18) -> 13.982109 | O22: =AVERAGE(O$9:O$18) -> 58.700372 | P22: =AVERAGE(P$9:P$18) -> 63.545529
B23: Median | N23: =MEDIAN(N$9:N$18) -> 7.0850583 | O23: =MEDIAN(O$9:O$18) -> 15.288983 | P23: =MEDIAN(P$9:P$18) -> 18.998271
B24: 25th Percentile | N24: =QUARTILE(N$9:N$18,1) -> 3.9432251 | O24: =QUARTILE(O$9:O$18,1) -> 5.2748235 | P24: =QUARTILE(P$9:P$18,1) -> 5.5895043
B25: Low | N25: =MIN(N$9:N$18) -> 0.40549763 | O25: =MIN(O$9:O$18) -> 0 | P25: =MIN(P$9:P$18) -> 0
B27: ITC Comparable Valuation | N27: EV/Revenue | O27: EV/EBITDA | P27: P/E
B29: Implied Enterprise Value | N29: =N23*J9 -> 560005.27 | O29: =O23*K9 -> 442684.23 | P29: =P31+P30 -> 665370.38
B30: Net Debt | N30: =$G$9 -> -3727.82 | O30: =$G$9 -> -3727.82 | P30: =$G$9 -> -3727.82
B31: Implied Market Value | N31: =N29-N30 -> 563733.09 | O31: =O29-O30 -> 446412.05 | P31: =P23*L9 -> 669098.2
B32: Shares Outstanding | N32: =$E$9 -> 1252.36 | O32: =$E$9 -> 1252.36 | P32: =$E$9 -> 1252.36
B34: Implied Value per Share | N34: =N31/N32 -> 450.13662 | O34: =O31/O32 -> 356.45665 | P34: =P31/P32 -> 534.26986
N36: =IF(N34>$D$9,"Undervalued","Overvalued") -> Undervalued | O36: =IF(O34>$D$9,"Undervalued","Overvalued") -> Overvalued | P36: =IF(P34>$D$9,"Undervalued","Overvalued") -> Undervalued

Sheet ITC_Data
B2: S.No. | C2: Name | D2: CMP Rs. | E2: No. Eq. Shares Cr. | F2: Market Cap | G2: Debt Rs.Cr. | H2: Cash End Rs.Cr. | I2: Net Debt | J2: EV | K2: Sales Rs.Cr. | L2: EBITDA | M2: NP 12M Rs.Cr.
B3: 1 | C3: ITC | D3: 407 | E3: 1252.36 | F3: =D3*E3 -> 509710.52 | G3: 284.54 | H3: 4012.36 | I3: =G3-H3 -> -3727.82 | J3: =F3+G3-H3 -> 505982.7 | K3: 79040.32 | L3: 28954.46 | M3: 35218.9
B4: 2 | C4: Godfrey Phillips | D4: 8983.5 | E4: 5.2 | F4: =D4*E4 -> 46714.2 | G4: 178.97 | H4: 30.31 | I4: =G4-H4 -> 148.66 | J4: =F4+G4-H4 -> 46862.86 | K4: 6032.39 | L4: 1714.83 | M4: 1200.04
B5: 3 | C5: Elitecon Inter. | D5: 213.7 | E5: 159.85 | F5: =D5*E5 -> 34159.945 | G5: 2.51 | H5: 2.67 | I5: =G5-H5 -> -0.16 | J5: =F5+G5-H5 -> 34159.785 | K5: 548.76 | L5: 71.61 | M5: 69.65
B6: 4 | C6: VST Industries | D6: 282 | E6: 16.99 | F6: =D6*E6 -> 4791.18 | G6: 0 | H6: 17.55 | I6: =G6-H6 -> -17.55 | J6: =F6+G6-H6 -> 4773.63 | K6: 1374.32 | L6: 318.99 | M6: 292.95
B7: 5 | C7: NTC Industries | D7: 169.7 | E7: 1.45 | F7: =D7*E7 -> 246.065 | G7: 77.08 | H7: 1.51 | I7: =G7-H7 -> 75.57 | J7: =F7+G7-H7 -> 321.635 | K7: 60.09 | L7: 21.8 | M7: 11.37
B8: 6 | C8: Sinnar Bidi Udy. | D8: 997.15 | E8: 0.04 | F8: =D8*E8 -> 39.886 | G8: 0 | H8: 2.82 | I8: =G8-H8 -> -2.82 | J8: =F8+G8-H8 -> 37.066 | K8: 4.73 | L8: -0.12 | M8: -0.12
B9: 7 | C9: Shanthala FMCG | D9: 35 | E9: 0.67 | F9: =D9*E9 -> 23.45 | G9: 0.11 | H9: 2.17 | I9: =G9-H9 -> -2.06 | J9: =F9+G9-H9 -> 21.39 | K9: 52.75 | L9: 1.37 | M9: 0.97
B10: 8 | C10: Raghunath Intl. | D10: 13.3 | E10: 0.5 | F10: =D10*E10 -> 6.65 | G10: 0 | H10: 0.22 | I10: =G10-H10 -> -0.22 | J10: =F10+G10-H10 -> 6.43 | K10: 0.28 | L10: 3.04 | M10: 2.53
B11: 9 | C11: Shanthala FMCG | D11: 35 | E11: 0.67 | F11: =D11*E11 -> 23.45 | G11: 0.11 | H11: 2.17 | I11: =G11-H11 -> -2.06 | J11: =F11+G11-H11 -> 21.39 | K11: 52.75 | L11: 1.37 | M11: 0.97
B12: 10 | C12: Raghunath Intl. | D12: 13.3 | E12: 0.5 | F12: =D12*E12 -> 6.65 | G12: 0 | H12: 0.22 | I12: =G12-H12 -> -0.22 | J12: =F12+G12-H12 -> 6.43 | K12: 0.28 | L12: 3.04 | M12: 2.53
