Workbook
Name IQ_CH: 110000
Name IQ_CQ: 5000
Name IQ_CY: 10000
Name IQ_DAILY: 500000
Name IQ_FH: 100000
Name IQ_FQ: 500
Name IQ_FY: 1000
Name IQ_LTM: 2000
Name IQ_MONTH: 15000
Name IQ_NTM: 6000
Name IQ_WEEK: 50000
Name IQ_YTD: 3000
Name UPDATE: '[1]Data Sheet'!$E$1
Name UPDATE: 'Data Sheet'!$E$1

Sheet Financials

Sheet Historical FS
B2: Historical Financial Statements
B3: ='Data Sheet'!B1 -> ITC LTD
B5: Particulars | C5: ='Data Sheet'!B16 -> 42460 | D5: ='Data Sheet'!C16 -> 42825 | E5: ='Data Sheet'!D16 -> 43190 | F5: ='Data Sheet'!E16 -> 43555 | G5: ='Data Sheet'!F16 -> 43921 | H5: ='Data Sheet'!G16 -> 44286 | I5: ='Data Sheet'!H16 -> 44651 | J5: ='Data Sheet'!I16 -> 45016 | ... L5: ='Data Sheet'!K16 -> 45747 | M5: LTM
A7: # | B7: Income Statement
B8: Sales | C8: =IFERROR('Data Sheet'!B17,0) -> 39192.1 | D8: =IFERROR('Data Sheet'!C17,0) -> 42767.6 | E8: =IFERROR('Data Sheet'!D17,0) -> 43448.94 | F8: =IFERROR('Data Sheet'!E17,0) -> 48339.58 | G8: =IFERROR('Data Sheet'!F17,0) -> 49387.7 | H8: =IFERROR('Data Sheet'!G17,0) -> 49257.45 | I8: =IFERROR('Data Sheet'!H17,0) -> 60644.54 | J8: =IFERROR('Data Sheet'!I17,0) -> 70919.03 | ... L8: =IFERROR('Data Sheet'!K17,0) -> 75323.34 | M8: =IFERROR(SUM('Data Sheet'!H42:K42),0) -> 79040.32
B9: Sales Growth | C9: - | D9: =D8/C8-1 -> 0.09123012 | E9: =E8/D8-1 -> 0.015931219 | F9: =F8/E8-1 -> 0.11256063 | G9: =G8/F8-1 -> 0.021682439 | H9: =H8/G8-1 -> -0.0026372963 | I9: =I8/H8-1 -> 0.23117498 | J9: =J8/I8-1 -> 0.16942152 | K9: =K8/J8-1 -> -0.042119724 | ... M9: =M8/L8-1 -> 0.049346989
B11: COGS | C11: =IFERROR(SUM('Data Sheet'!B18,'Data Sheet'!B20:B22)-1*'Data Sheet'!B19,0) -> 19162.94 | D11: =IFERROR(SUM('Data Sheet'!C18,'Data Sheet'!C20:C22)-1*'Data Sheet'!C19,0) -> 21949.12 | E11: =IFERROR(SUM('Data Sheet'!D18,'Data Sheet'!D20:D22)-1*'Data Sheet'!D19,0) -> 21967.5 | F11: =IFERROR(SUM('Data Sheet'!E18,'Data Sheet'!E20:E22)-1*'Data Sheet'!E19,0) -> 24215.95 | G11: =IFERROR(SUM('Data Sheet'!F18,'Data Sheet'!F20:F22)-1*'Data Sheet'!F19,0) -> 24330.4 | H11: =IFERROR(SUM('Data Sheet'!G18,'Data Sheet'!G20:G22)-1*'Data Sheet'!G19,0) -> 26881.51 | I11: =IFERROR(SUM('Data Sheet'!H18,'Data Sheet'!H20:H22)-1*'Data Sheet'!H19,0) -> 34053.06 | J11: =IFERROR(SUM('Data Sheet'!I18,'Data Sheet'!I20:I22)-1*'Data Sheet'!I19,0) -> 38302.13 | ... L11: =IFERROR(SUM('Data Sheet'!K18,'Data Sheet'!K20:K22)-1*'Data Sheet'!K19,0) -> 41469.21 | M11: =IFERROR(SUM('Data Sheet'!H43:K43),0) -> 52790.48
B12: COGS % Sales | C12: =C11/C8 -> 0.48894905 | D12: =D11/D8 -> 0.51321842 | E12: =E11/E8 -> 0.50559346 | F12: =F11/F8 -> 0.50095491 | G12: =G11/G8 -> 0.49264088 | H12: =H11/H8 -> 0.54573491 | I12: =I11/I8 -> 0.56151898 | J12: =J11/J8 -> 0.54008254 | ... M12: =M11/M8 -> 0.66789304
B14: Gross Profit | C14: =C8-C11 -> 20029.16 | D14: =D8-D11 -> 20818.48 | E14: =E8-E11 -> 21481.44 | F14: =F8-F11 -> 24123.63 | G14: =G8-G11 -> 25057.3 | H14: =H8-H11 -> 22375.94 | I14: =I8-I11 -> 26591.48 | J14: =J8-J11 -> 32616.9 | ... M14: =M8-M11 -> 26249.84
B15: Gross Margins | C15: =C14/C8 -> 0.51105095 | D15: =D14/D8 -> 0.48678158 | E15: =E14/E8 -> 0.49440654 | F15: =F14/F8 -> 0.49904509 | G15: =G14/G8 -> 0.50735912 | H15: =H14/H8 -> 0.45426509 | I15: =I14/I8 -> 0.43848102 | J15: =J14/J8 -> 0.45991746 | ... M15: =M14/M8 -> 0.33210696
B17: Selling & General Expenses | C17: =IFERROR(SUM('Data Sheet'!B23:B24),0) -> 5497.67 | D17: =IFERROR(SUM('Data Sheet'!C23:C24),0) -> 5348.97 | E17: =IFERROR(SUM('Data Sheet'!D23:D24),0) -> 4960.85 | F17: =IFERROR(SUM('Data Sheet'!E23:E24),0) -> 5586.24 | G17: =IFERROR(SUM('Data Sheet'!F23:F24),0) -> 5713.76 | H17: =IFERROR(SUM('Data Sheet'!G23:G24),0) -> 5311.16 | I17: =IFERROR(SUM('Data Sheet'!H23:H24),0) -> 5968.33 | J17: =IFERROR(SUM('Data Sheet'!I23:I24),0) -> 6912.64 | ... L17: =IFERROR(SUM('Data Sheet'!K23:K24),0) -> 8014.68
B18: S&G Exp % Sales | C18: =C17/C11 -> 0.28689074 | D18: =D17/D11 -> 0.24369861 | E18: =E17/E11 -> 0.22582679 | F18: =F17/F11 -> 0.23068432 | G18: =G17/G11 -> 0.23484036 | H18: =H17/H11 -> 0.1975767 | I18: =I17/I11 -> 0.1752656 | J18: =J17/J11 -> 0.18047665 | ... M18: =M17/M11 -> 0
B20: Other Income | C20: =IFERROR('Data Sheet'!B25,0) -> 1483.11 | D20: =IFERROR('Data Sheet'!C25,0) -> 1758.63 | E20: =IFERROR('Data Sheet'!D25,0) -> 2239.81 | F20: =IFERROR('Data Sheet'!E25,0) -> 2080.44 | G20: =IFERROR('Data Sheet'!F25,0) -> 2417.32 | H20: =IFERROR('Data Sheet'!G25,0) -> 2576.95 | I20: =IFERROR('Data Sheet'!H25,0) -> 1909.72 | J20: =IFERROR('Data Sheet'!I25,0) -> 2097.64 | ... L20: =IFERROR('Data Sheet'!K25,0) -> 17794.88
B21: Other Income % Sales | C21: =C20/C8 -> 0.037842065 | D21: =D20/D8 -> 0.041120615 | E21: =E20/E8 -> 0.051550395 | F21: =F20/F8 -> 0.043038024 | G21: =G20/G8 -> 0.04894579 | H21: =H20/H8 -> 0.052315944 | I21: =I20/I8 -> 0.031490386 | J21: =J20/J8 -> 0.029577957 | ... M21: =M20/M8 -> 0
B23: EBITDA | C23: =C14-C17+C20 -> 16014.6 | D23: =D14-D17+D20 -> 17228.14 | E23: =E14-E17+E20 -> 18760.4 | F23: =F14-F17+F20 -> 20617.83 | G23: =G14-G17+G20 -> 21760.86 | H23: =H14-H17+H20 -> 19641.73 | I23: =I14-I17+I20 -> 22532.87 | J23: =J14-J17+J20 -> 27801.9 | ... M23: =M14-M17+M20 -> 26249.84
B24: EBITDA Margins | C24: =C23/C8 -> 0.40861806 | D24: =D23/D8 -> 0.40283158 | E24: =E23/E8 -> 0.43178038 | F24: =F23/F8 -> 0.42652067 | G24: =G23/G8 -> 0.44061295 | H24: =H23/H8 -> 0.39875653 | I24: =I23/I8 -> 0.37155645 | J24: =J23/J8 -> 0.39202313 | ... M24: =M23/M8 -> 0.33210696
B26: Interest | C26: =IFERROR('Data Sheet'!B27,0) -> 78.13 | D26: =IFERROR('Data Sheet'!C27,0) -> 49.03 | E26: =IFERROR('Data Sheet'!D27,0) -> 115.01 | F26: =IFERROR('Data Sheet'!E27,0) -> 71.4 | G26: =IFERROR('Data Sheet'!F27,0) -> 81.38 | H26: =IFERROR('Data Sheet'!G27,0) -> 57.97 | I26: =IFERROR('Data Sheet'!H27,0) -> 59.99 | J26: =IFERROR('Data Sheet'!I27,0) -> 77.77 | ... L26: =IFERROR('Data Sheet'!K27,0) -> 45.06 | M26: =IFERROR(SUM('Data Sheet'!H46:K46),0) -> 51.93
B27: Interest % Sales | C27: =C26/C8 -> 0.001993514 | D27: =D26/D8 -> 0.0011464286 | E27: =E26/E8 -> 0.0026470151 | F27: =F26/F8 -> 0.0014770505 | G27: =G26/G8 -> 0.0016477787 | H27: =H26/H8 -> 0.0011768778 | I27: =I26/I8 -> 0.00098920694 | J27: =J26/J8 -> 0.0010966027 | ... M27: =M26/M8 -> 0.00065700645
B29: Depreciation | C29: =IFERROR('Data Sheet'!B26,0) -> 1077.4 | D29: =IFERROR('Data Sheet'!C26,0) -> 1152.79 | E29: =IFERROR('Data Sheet'!D26,0) -> 1236.28 | F29: =IFERROR('Data Sheet'!E26,0) -> 1396.61 | G29: =IFERROR('Data Sheet'!F26,0) -> 1644.91 | H29: =IFERROR('Data Sheet'!G26,0) -> 1645.59 | I29: =IFERROR('Data Sheet'!H26,0) -> 1732.41 | J29: =IFERROR('Data Sheet'!I26,0) -> 1809.01 | ... L29: =IFERROR('Data Sheet'!K26,0) -> 1646.32 | M29: =IFERROR(SUM('Data Sheet'!H45:K45),0) -> 1666.15
B30: Depreciation%Sales | C30: =C29/C8 -> 0.027490234 | D30: =D29/D8 -> 0.026954751 | E30: =E29/E8 -> 0.028453629 | F30: =F29/F8 -> 0.028891645 | G30: =G29/G8 -> 0.033306066 | H30: =H29/H8 -> 0.033407941 | I30: =I29/I8 -> 0.028566628 | J30: =J29/J8 -> 0.025508104 | ... M30: =M29/M8 -> 0.021079748
B32: Earnings Before Tax | C32: =IFERROR(C23-SUM(C29,C26),0) -> 14859.07 | D32: =IFERROR(D23-SUM(D29,D26),0) -> 16026.32 | E32: =IFERROR(E23-SUM(E29,E26),0) -> 17409.11 | F32: =IFERROR(F23-SUM(F29,F26),0) -> 19149.82 | G32: =IFERROR(G23-SUM(G29,G26),0) -> 20034.57 | H32: =IFERROR(H23-SUM(H29,H26),0) -> 17938.17 | I32: =IFERROR(I23-SUM(I29,I26),0) -> 20740.47 | J32: =IFERROR(J23-SUM(J29,J26),0) -> 25915.12 | ... M32: =IFERROR(M23-SUM(M29,M26),0) -> 24531.76
B33: EBT % Sales | C33: =C32/C8 -> 0.37913432 | D33: =D32/D8 -> 0.3747304 | E33: =E32/E8 -> 0.40067974 | F33: =F32/F8 -> 0.39615197 | G33: =G32/G8 -> 0.4056591 | H33: =H32/H8 -> 0.36417171 | I33: =I32/I8 -> 0.34200062 | J33: =J32/J8 -> 0.36541842 | ... M33: =M32/M8 -> 0.3103702
B35: Tax | C35: =IFERROR('Data Sheet'!B29,0) -> 5358.21 | D35: =IFERROR('Data Sheet'!C29,0) -> 5549.09 | E35: =IFERROR('Data Sheet'!D29,0) -> 5916.43 | F35: =IFERROR('Data Sheet'!E29,0) -> 6313.92 | G35: =IFERROR('Data Sheet'!F29,0) -> 4441.79 | H35: =IFERROR('Data Sheet'!G29,0) -> 4555.29 | I35: =IFERROR('Data Sheet'!H29,0) -> 5237.34 | J35: =IFERROR('Data Sheet'!I29,0) -> 6438.4 | ... L35: =IFERROR('Data Sheet'!K29,0) -> 6890.47 | M35: =IFERROR(SUM('Data Sheet'!H48:K48),0) -> 6948.82
B36: Effective Tax Rate | C36: =C35/C32 -> 0.36060198 | D36: =D35/D32 -> 0.34624855 | E36: =E35/E32 -> 0.33984678 | F36: =F35/F32 -> 0.32971172 | G36: =G35/G32 -> 0.22170628 | H36: =H35/H32 -> 0.25394396 | I36: =I35/I32 -> 0.2525179 | J36: =J35/J32 -> 0.24844184 | ... M36: =M35/M32 -> 0.28325811
B38: Net Profit | C38: =C32-C35 -> 9500.86 | D38: =D32-D35 -> 10477.23 | E38: =E32-E35 -> 11492.68 | F38: =F32-F35 -> 12835.9 | G38: =G32-G35 -> 15592.78 | H38: =H32-H35 -> 13382.88 | I38: =I32-I35 -> 15503.13 | J38: =J32-J35 -> 19476.72 | ... L38: =L32-L35 -> 35052.48 | M38: =IFERROR(SUM('Data Sheet'!H49:K49),0) -> 34899.24
B39: Net Margins | C39: =C38/C8 -> 0.24241773 | D39: =D38/D8 -> 0.24498055 | E39: =E38/E8 -> 0.26451002 | F39: =F38/F8 -> 0.26553603 | G39: =G38/G8 -> 0.31572193 | H39: =H38/H8 -> 0.27169251 | I39: =I38/I8 -> 0.25563934 | J39: =J38/J8 -> 0.2746332 | ... M39: =M38/M8 -> 0.44153718
B41: No of Equity Shares | C41: =IFERROR('Data Sheet'!B93,0) -> 1207.08 | D41: =IFERROR('Data Sheet'!C93,0) -> 1214.74 | E41: =IFERROR('Data Sheet'!D93,0) -> 1220.43 | F41: =IFERROR('Data Sheet'!E93,0) -> 1225.86 | G41: =IFERROR('Data Sheet'!F93,0) -> 1229.22 | H41: =IFERROR('Data Sheet'!G93,0) -> 1230.88 | I41: =IFERROR('Data Sheet'!H93,0) -> 1232.33 | J41: =IFERROR('Data Sheet'!I93,0) -> 1242.8 | ... L41: =IFERROR('Data Sheet'!K93,0) -> 1251.41 | M41: -
B43: Earnings per Share | C43: =C38/C41 -> 7.8709448 | D43: =D38/D41 -> 8.6250803 | E43: =E38/E41 -> 9.4169104 | F43: =F38/F41 -> 10.470935 | G43: =G38/G41 -> 12.685101 | H43: =H38/H41 -> 10.872611 | I43: =I38/I41 -> 12.58034 | J43: =J38/J41 -> 15.671645 | ... L43: =L38/L41 -> 28.010388 | M43: -
B44: EPS Growth % | C44: - | D44: =D43/C43-1 -> 0.095812578 | E44: =E43/D43-1 -> 0.091805542 | F44: =F43/E43-1 -> 0.11192888 | G44: =G43/F43-1 -> 0.21145834 | H44: =H43/G43-1 -> -0.14288334 | I44: =I43/H43-1 -> 0.15706698 | J44: =J43/I43-1 -> 0.24572508 | K44: =K43/J43-1 -> 0.060605506 | L44: =L43/K43-1 -> 0.68519699 | M44: -
B46: Dividend per Share | C46: =IFERROR('Data Sheet'!B31,0)/C41 -> 5.6666667 | D46: =IFERROR('Data Sheet'!C31,0)/D41 -> 4.7500041 | E46: =IFERROR('Data Sheet'!D31,0)/E41 -> 5.1499963 | F46: =IFERROR('Data Sheet'!E31,0)/F41 -> 5.7500041 | G46: =IFERROR('Data Sheet'!F31,0)/G41 -> 10.149998 | H46: =IFERROR('Data Sheet'!G31,0)/H41 -> 10.75 | I46: =IFERROR('Data Sheet'!H31,0)/I41 -> 11.500004 | J46: =IFERROR('Data Sheet'!I31,0)/J41 -> 15.5 | ... L46: =IFERROR('Data Sheet'!K31,0)/L41 -> 14.349997 | M46: -
B47: Dividend payout ratio | C47: =IFERROR(C46/C43,0) -> 0.71994746 | D47: =IFERROR(D46/D43,0) -> 0.55071999 | E47: =IFERROR(E46/E43,0) -> 0.54688811 | F47: =IFERROR(F46/F43,0) -> 0.54913952 | G47: =IFERROR(G46/G43,0) -> 0.8001511 | H47: =IFERROR(H46/H43,0) -> 0.98872291 | I47: =IFERROR(I46/I43,0) -> 0.91412508 | J47: =IFERROR(J46/J43,0) -> 0.98904744 | ... L47: =IFERROR(L46/L43,0) -> 0.51230983 | M47: -
B49: Retained Earnings | C49: =IFERROR(IF(C43>C46,1-C47,0),0) -> 0.28005254 | D49: =IFERROR(IF(D43>D46,1-D47,0),0) -> 0.44928001 | E49: =IFERROR(IF(E43>E46,1-E47,0),0) -> 0.45311189 | F49: =IFERROR(IF(F43>F46,1-F47,0),0) -> 0.45086048 | G49: =IFERROR(IF(G43>G46,1-G47,0),0) -> 0.1998489 | H49: =IFERROR(IF(H43>H46,1-H47,0),0) -> 0.011277094 | I49: =IFERROR(IF(I43>I46,1-I47,0),0) -> 0.085874917 | J49: =IFERROR(IF(J43>J46,1-J47,0),0) -> 0.010952563 | ... L49: =IFERROR(IF(L43>L46,1-L47,0),0) -> 0.48769017 | M49: -
A50: #
B51: Balance Sheet
B52: Equity Share Capital | C52: =IFERROR('Data Sheet'!B57,0) -> 804.72 | D52: =IFERROR('Data Sheet'!C57,0) -> 1214.74 | E52: =IFERROR('Data Sheet'!D57,0) -> 1220.43 | F52: =IFERROR('Data Sheet'!E57,0) -> 1225.86 | G52: =IFERROR('Data Sheet'!F57,0) -> 1229.22 | H52: =IFERROR('Data Sheet'!G57,0) -> 1230.88 | I52: =IFERROR('Data Sheet'!H57,0) -> 1232.33 | J52: =IFERROR('Data Sheet'!I57,0) -> 1242.8 | ... L52: =IFERROR('Data Sheet'!K57,0) -> 1251.41 | M52: -
B53: Reserves | C53: =IFERROR('Data Sheet'!B58,0) -> 41874.8 | D53: =IFERROR('Data Sheet'!C58,0) -> 45198.19 | E53: =IFERROR('Data Sheet'!D58,0) -> 51289.68 | F53: =IFERROR('Data Sheet'!E58,0) -> 57915.01 | G53: =IFERROR('Data Sheet'!F58,0) -> 64044.04 | H53: =IFERROR('Data Sheet'!G58,0) -> 59116.46 | I53: =IFERROR('Data Sheet'!H58,0) -> 61223.24 | J53: =IFERROR('Data Sheet'!I58,0) -> 67912.46 | ... L53: =IFERROR('Data Sheet'!K58,0) -> 68778.64 | M53: -
B54: Borrowings | C54: =IFERROR('Data Sheet'!B59,0) -> 83.78 | D54: =IFERROR('Data Sheet'!C59,0) -> 45.72 | E54: =IFERROR('Data Sheet'!D59,0) -> 35.92 | F54: =IFERROR('Data Sheet'!E59,0) -> 13.44 | G54: =IFERROR('Data Sheet'!F59,0) -> 277.45 | H54: =IFERROR('Data Sheet'!G59,0) -> 270.83 | I54: =IFERROR('Data Sheet'!H59,0) -> 249.44 | J54: =IFERROR('Data Sheet'!I59,0) -> 306.04 | ... L54: =IFERROR('Data Sheet'!K59,0) -> 284.54 | M54: -
B55: Other Liabilities | C55: =IFERROR('Data Sheet'!B60,0) -> 8888.04 | D55: =IFERROR('Data Sheet'!C60,0) -> 9439.67 | E55: =IFERROR('Data Sheet'!D60,0) -> 11694.85 | F55: =IFERROR('Data Sheet'!E60,0) -> 12584.73 | G55: =IFERROR('Data Sheet'!F60,0) -> 11760.04 | H55: =IFERROR('Data Sheet'!G60,0) -> 13142.59 | I55: =IFERROR('Data Sheet'!H60,0) -> 14491.01 | J55: =IFERROR('Data Sheet'!I60,0) -> 16369.66 | ... L55: =IFERROR('Data Sheet'!K60,0) -> 17688.11 | M55: -
B56: Total Liabilities | C56: =IFERROR('Data Sheet'!B61,0) -> 51651.34 | D56: =IFERROR('Data Sheet'!C61,0) -> 55898.32 | E56: =IFERROR('Data Sheet'!D61,0) -> 64240.88 | F56: =IFERROR('Data Sheet'!E61,0) -> 71739.04 | G56: =IFERROR('Data Sheet'!F61,0) -> 77310.75 | H56: =IFERROR('Data Sheet'!G61,0) -> 73760.76 | I56: =IFERROR('Data Sheet'!H61,0) -> 77196.02 | J56: =IFERROR('Data Sheet'!I61,0) -> 85830.96 | ... L56: =IFERROR('Data Sheet'!K61,0) -> 88002.7 | M56: -
B58: Fixed Assets Net Block | C58: =IFERROR('Data Sheet'!B62,0) -> 15106.63 | D58: =IFERROR('Data Sheet'!C62,0) -> 15893.48 | E58: =IFERROR('Data Sheet'!D62,0) -> 16523.96 | F58: =IFERROR('Data Sheet'!E62,0) -> 19374.19 | G58: =IFERROR('Data Sheet'!F62,0) -> 21713.34 | H58: =IFERROR('Data Sheet'!G62,0) -> 23298.48 | I58: =IFERROR('Data Sheet'!H62,0) -> 24231.59 | J58: =IFERROR('Data Sheet'!I62,0) -> 25851.27 | ... L58: =IFERROR('Data Sheet'!K62,0) -> 21954.85 | M58: -
B59: Capital Work in Progress | C59: =IFERROR('Data Sheet'!B63,0) -> 2559.72 | D59: =IFERROR('Data Sheet'!C63,0) -> 3729.89 | E59: =IFERROR('Data Sheet'!D63,0) -> 5508.33 | F59: =IFERROR('Data Sheet'!E63,0) -> 4136.42 | G59: =IFERROR('Data Sheet'!F63,0) -> 3256.46 | H59: =IFERROR('Data Sheet'!G63,0) -> 4011.29 | I59: =IFERROR('Data Sheet'!H63,0) -> 3225.54 | J59: =IFERROR('Data Sheet'!I63,0) -> 3003.3 | ... L59: =IFERROR('Data Sheet'!K63,0) -> 1090.91 | M59: -
B60: Investments | C60: =IFERROR('Data Sheet'!B64,0) -> 11747.59 | D60: =IFERROR('Data Sheet'!C64,0) -> 17581.38 | E60: =IFERROR('Data Sheet'!D64,0) -> 22052.86 | F60: =IFERROR('Data Sheet'!E64,0) -> 25043.49 | G60: =IFERROR('Data Sheet'!F64,0) -> 28663.35 | H60: =IFERROR('Data Sheet'!G64,0) -> 24870.87 | I60: =IFERROR('Data Sheet'!H64,0) -> 24841.01 | J60: =IFERROR('Data Sheet'!I64,0) -> 29415.02 | ... L60: =IFERROR('Data Sheet'!K64,0) -> 34719.82 | M60: -
B61: Other Assets | C61: =IFERROR('Data Sheet'!B65-SUM('Data Sheet'!B67:B69),0) -> 5194.82 | D61: =IFERROR('Data Sheet'!C65-SUM('Data Sheet'!C67:C69),0) -> 5135.78 | E61: =IFERROR('Data Sheet'!D65-SUM('Data Sheet'!D67:D69),0) -> 7078.75 | F61: =IFERROR('Data Sheet'!E65-SUM('Data Sheet'!E67:E69),0) -> 7138.07 | G61: =IFERROR('Data Sheet'!F65-SUM('Data Sheet'!F67:F69),0) -> 4958.45 | H61: =IFERROR('Data Sheet'!G65-SUM('Data Sheet'!G67:G69),0) -> 4022.24 | I61: =IFERROR('Data Sheet'!H65-SUM('Data Sheet'!H67:H69),0) -> 6917.41 | J61: =IFERROR('Data Sheet'!I65-SUM('Data Sheet'!I67:I69),0) -> 7953.85 | ... L61: =IFERROR('Data Sheet'!K65-SUM('Data Sheet'!K67:K69),0) -> 5867.53 | M61: -
B62: Total Non Current Assets | C62: =SUM(C58:C61) -> 34608.76 | D62: =SUM(D58:D61) -> 42340.53 | E62: =SUM(E58:E61) -> 51163.9 | F62: =SUM(F58:F61) -> 55692.17 | G62: =SUM(G58:G61) -> 58591.6 | H62: =SUM(H58:H61) -> 56202.88 | I62: =SUM(I58:I61) -> 59215.55 | J62: =SUM(J58:J61) -> 66223.44 | ... L62: =SUM(L58:L61) -> 63633.11 | M62: -
B64: Receivables | C64: =IFERROR('Data Sheet'!B67,0) -> 1917.18 | D64: =IFERROR('Data Sheet'!C67,0) -> 2474.29 | E64: =IFERROR('Data Sheet'!D67,0) -> 2682.29 | F64: =IFERROR('Data Sheet'!E67,0) -> 4035.28 | G64: =IFERROR('Data Sheet'!F67,0) -> 2562.48 | H64: =IFERROR('Data Sheet'!G67,0) -> 2501.7 | I64: =IFERROR('Data Sheet'!H67,0) -> 2461.9 | J64: =IFERROR('Data Sheet'!I67,0) -> 2956.17 | ... L64: =IFERROR('Data Sheet'!K67,0) -> 4719.67 | M64: -
B65: Inventory | C65: =IFERROR('Data Sheet'!B68,0) -> 9062.1 | D65: =IFERROR('Data Sheet'!C68,0) -> 8116.1 | E65: =IFERROR('Data Sheet'!D68,0) -> 7495.09 | F65: =IFERROR('Data Sheet'!E68,0) -> 7859.56 | G65: =IFERROR('Data Sheet'!F68,0) -> 8879.33 | H65: =IFERROR('Data Sheet'!G68,0) -> 10397.16 | I65: =IFERROR('Data Sheet'!H68,0) -> 10864.15 | J65: =IFERROR('Data Sheet'!I68,0) -> 11771.16 | ... L65: =IFERROR('Data Sheet'!K68,0) -> 15637.56 | M65: -
B66: Cash & Bank | C66: =IFERROR('Data Sheet'!B69,0) -> 6063.3 | D66: =IFERROR('Data Sheet'!C69,0) -> 2967.4 | E66: =IFERROR('Data Sheet'!D69,0) -> 2899.6 | F66: =IFERROR('Data Sheet'!E69,0) -> 4152.03 | G66: =IFERROR('Data Sheet'!F69,0) -> 7277.34 | H66: =IFERROR('Data Sheet'!G69,0) -> 4659.02 | I66: =IFERROR('Data Sheet'!H69,0) -> 4654.42 | J66: =IFERROR('Data Sheet'!I69,0) -> 4880.19 | ... L66: =IFERROR('Data Sheet'!K69,0) -> 4012.36 | M66: -
B67: Total Current Assets | C67: =SUM(C64:C66) -> 17042.58 | D67: =SUM(D64:D66) -> 13557.79 | E67: =SUM(E64:E66) -> 13076.98 | F67: =SUM(F64:F66) -> 16046.87 | G67: =SUM(G64:G66) -> 18719.15 | H67: =SUM(H64:H66) -> 17557.88 | I67: =SUM(I64:I66) -> 17980.47 | J67: =SUM(J64:J66) -> 19607.52 | ... L67: =SUM(L64:L66) -> 24369.59 | M67: -
B69: Total Assets | C69: =IFERROR(SUM(C67,C62),0) -> 51651.34 | D69: =IFERROR(SUM(D67,D62),0) -> 55898.32 | E69: =IFERROR(SUM(E67,E62),0) -> 64240.88 | F69: =IFERROR(SUM(F67,F62),0) -> 71739.04 | G69: =IFERROR(SUM(G67,G62),0) -> 77310.75 | H69: =IFERROR(SUM(H67,H62),0) -> 73760.76 | I69: =IFERROR(SUM(I67,I62),0) -> 77196.02 | J69: =IFERROR(SUM(J67,J62),0) -> 85830.96 | ... L69: =IFERROR(SUM(L67,L62),0) -> 88002.7 | M69: -
B71: Check | C71: =C69=C56 -> TRUE | D71: =D69=D56 -> TRUE | E71: =E69=E56 -> TRUE | F71: =F69=F56 -> TRUE | G71: =G69=G56 -> TRUE | H71: =H69=H56 -> TRUE | I71: =I69=I56 -> TRUE | J71: =J69=J56 -> TRUE | ... L71: =L69=L56 -> TRUE | M71: -
A72: #
B73: Cash Flow Statements
B75: Cash from Operating Activities | C75: ='Data Sheet'!B82 -> 9799.04 | D75: ='Data Sheet'!C82 -> 10627.31 | E75: ='Data Sheet'!D82 -> 13169.4 | F75: ='Data Sheet'!E82 -> 12583.41 | G75: ='Data Sheet'!F82 -> 14689.66 | H75: ='Data Sheet'!G82 -> 12526.97 | I75: ='Data Sheet'!H82 -> 15775.51 | J75: ='Data Sheet'!I82 -> 18877.55 | ... L75: ='Data Sheet'!K82 -> 17627.04 | M75: -
B77: Cash from Investing Activities | C77: ='Data Sheet'!B83 -> -3920.73 | D77: ='Data Sheet'!C83 -> -3250.93 | E77: ='Data Sheet'!D83 -> -7113.89 | F77: ='Data Sheet'!E83 -> -5545.68 | G77: ='Data Sheet'!F83 -> -6174.02 | H77: ='Data Sheet'!G83 -> 5739.98 | I77: ='Data Sheet'!H83 -> -2238.49 | J77: ='Data Sheet'!I83 -> -5732.29 | ... L77: ='Data Sheet'!K83 -> -563.84 | M77: -
B79: Cash from Financing Activities | C79: ='Data Sheet'!B84 -> -5612.52 | D79: ='Data Sheet'!C84 -> -7301.03 | E79: ='Data Sheet'!D84 -> -6221.13 | F79: ='Data Sheet'!E84 -> -6868.64 | G79: ='Data Sheet'!F84 -> -8181.48 | H79: ='Data Sheet'!G84 -> -18633.83 | I79: ='Data Sheet'!H84 -> -13580.5 | J79: ='Data Sheet'!I84 -> -13006.03 | ... L79: ='Data Sheet'!K84 -> -17037.4 | M79: -
B81: Net Cash Flow | C81: =C79+C77+C75 -> 265.79 | D81: =D79+D77+D75 -> 75.35 | E81: =E79+E77+E75 -> -165.62 | F81: =F79+F77+F75 -> 169.09 | G81: =G79+G77+G75 -> 334.16 | H81: =H79+H77+H75 -> -366.88 | I81: =I79+I77+I75 -> -43.48 | J81: =J79+J77+J75 -> 139.23 | ... L81: =L79+L77+L75 -> 25.8 | M81: -

Sheet Common Size Statement
B2: Common Size Statement
B3: ='Data Sheet'!B1 -> ITC LTD
A5: # | B5: ="Common Size Income Statement"&" "&"- "&'Data Sheet'!$B$1 -> Common Size Income Statement - ITC LTD
B7: Particulars | C7: ='Data Sheet'!B16 -> 42460 | D7: ='Data Sheet'!C16 -> 42825 | E7: ='Data Sheet'!D16 -> 43190 | F7: ='Data Sheet'!E16 -> 43555 | G7: ='Data Sheet'!F16 -> 43921 | H7: ='Data Sheet'!G16 -> 44286 | I7: ='Data Sheet'!H16 -> 44651 | J7: ='Data Sheet'!I16 -> 45016 | ... L7: ='Data Sheet'!K16 -> 45747
B9: ='Data Sheet'!A17 -> Sales | C9: ='Data Sheet'!B17/'Data Sheet'!B$17 -> 1 | D9: ='Data Sheet'!C17/'Data Sheet'!C$17 -> 1 | E9: ='Data Sheet'!D17/'Data Sheet'!D$17 -> 1 | F9: ='Data Sheet'!E17/'Data Sheet'!E$17 -> 1 | G9: ='Data Sheet'!F17/'Data Sheet'!F$17 -> 1 | H9: ='Data Sheet'!G17/'Data Sheet'!G$17 -> 1 | I9: ='Data Sheet'!H17/'Data Sheet'!H$17 -> 1 | J9: ='Data Sheet'!I17/'Data Sheet'!I$17 -> 1 | ... L9: ='Data Sheet'!K17/'Data Sheet'!K$17 -> 1
B10: ='Data Sheet'!A18 -> Raw Material Cost | C10: ='Data Sheet'!B18/'Data Sheet'!B$17 -> 0.35119016 | D10: ='Data Sheet'!C18/'Data Sheet'!C$17 -> 0.36140887 | E10: ='Data Sheet'!D18/'Data Sheet'!D$17 -> 0.3412677 | F10: ='Data Sheet'!E18/'Data Sheet'!E$17 -> 0.36457743 | G10: ='Data Sheet'!F18/'Data Sheet'!F$17 -> 0.36544727 | H10: ='Data Sheet'!G18/'Data Sheet'!G$17 -> 0.42179833 | I10: ='Data Sheet'!H18/'Data Sheet'!H$17 -> 0.44638924 | J10: ='Data Sheet'!I18/'Data Sheet'!I$17 -> 0.41405473 | ... L10: ='Data Sheet'!K18/'Data Sheet'!K$17 -> 0.4341864
B11: ='Data Sheet'!A19 -> Change in Inventory | C11: ='Data Sheet'!B19/'Data Sheet'!B$17 -> 0.0049851883 | D11: ='Data Sheet'!C19/'Data Sheet'!C$17 -> -0.013855582 | E11: ='Data Sheet'!D19/'Data Sheet'!D$17 -> -0.023654432 | F11: ='Data Sheet'!E19/'Data Sheet'!E$17 -> 0.0042033878 | G11: ='Data Sheet'!F19/'Data Sheet'!F$17 -> 0.014236946 | H11: ='Data Sheet'!G19/'Data Sheet'!G$17 -> 0.013099947 | I11: ='Data Sheet'!H19/'Data Sheet'!H$17 -> 0.011311818 | J11: ='Data Sheet'!I19/'Data Sheet'!I$17 -> 0.0050563297 | ... L11: ='Data Sheet'!K19/'Data Sheet'!K$17 -> 0.0096338001
B12: ='Data Sheet'!A20 -> Power and Fuel | C12: ='Data Sheet'!B20/'Data Sheet'!B$17 -> 0.014591716 | D12: ='Data Sheet'!C20/'Data Sheet'!C$17 -> 0.013662913 | E12: ='Data Sheet'!D20/'Data Sheet'!D$17 -> 0.015040643 | F12: ='Data Sheet'!E20/'Data Sheet'!E$17 -> 0.01544759 | G12: ='Data Sheet'!F20/'Data Sheet'!F$17 -> 0.015810617 | H12: ='Data Sheet'!G20/'Data Sheet'!G$17 -> 0.014202116 | I12: ='Data Sheet'!H20/'Data Sheet'!H$17 -> 0.01467189 | J12: ='Data Sheet'!I20/'Data Sheet'!I$17 -> 0.017376718 | ... L12: ='Data Sheet'!K20/'Data Sheet'!K$17 -> 0.012948842
B13: ='Data Sheet'!A21 -> Other Mfr. Exp | C13: ='Data Sheet'!B21/'Data Sheet'!B$17 -> 0.040354816 | D13: ='Data Sheet'!C21/'Data Sheet'!C$17 -> 0.039373264 | E13: ='Data Sheet'!D21/'Data Sheet'!D$17 -> 0.039071609 | F13: ='Data Sheet'!E21/'Data Sheet'!E$17 -> 0.038705549 | G13: ='Data Sheet'!F21/'Data Sheet'!F$17 -> 0.038638973 | H13: ='Data Sheet'!G21/'Data Sheet'!G$17 -> 0.032222131 | I13: ='Data Sheet'!H21/'Data Sheet'!H$17 -> 0.031126792 | J13: ='Data Sheet'!I21/'Data Sheet'!I$17 -> 0.032823348 | ... L13: ='Data Sheet'!K21/'Data Sheet'!K$17 -> 0.031137228
B14: ='Data Sheet'!A22 -> Employee Cost | C14: ='Data Sheet'!B22/'Data Sheet'!B$17 -> 0.087797541 | D14: ='Data Sheet'!C22/'Data Sheet'!C$17 -> 0.084917788 | E14: ='Data Sheet'!D22/'Data Sheet'!D$17 -> 0.086559074 | F14: ='Data Sheet'!E22/'Data Sheet'!E$17 -> 0.086427727 | G14: ='Data Sheet'!F22/'Data Sheet'!F$17 -> 0.086980969 | H14: ='Data Sheet'!G22/'Data Sheet'!G$17 -> 0.090612283 | I14: ='Data Sheet'!H22/'Data Sheet'!H$17 -> 0.080642874 | J14: ='Data Sheet'!I22/'Data Sheet'!I$17 -> 0.080884073 | ... L14: ='Data Sheet'!K22/'Data Sheet'!K$17 -> 0.0819106
B15: ='Data Sheet'!A23 -> Selling and admin | C15: ='Data Sheet'!B23/'Data Sheet'!B$17 -> 0.10874079 | D15: ='Data Sheet'!C23/'Data Sheet'!C$17 -> 0.09773146 | E15: ='Data Sheet'!D23/'Data Sheet'!D$17 -> 0.091023394 | F15: ='Data Sheet'!E23/'Data Sheet'!E$17 -> 0.094051086 | G15: ='Data Sheet'!F23/'Data Sheet'!F$17 -> 0.090885585 | H15: ='Data Sheet'!G23/'Data Sheet'!G$17 -> 0.086012776 | I15: ='Data Sheet'!H23/'Data Sheet'!H$17 -> 0.080112406 | J15: ='Data Sheet'!I23/'Data Sheet'!I$17 -> 0.079020821 | ... L15: ='Data Sheet'!K23/'Data Sheet'!K$17 -> 0.076912282
B16: ='Data Sheet'!A24 -> Other Expenses | C16: ='Data Sheet'!B24/'Data Sheet'!B$17 -> 0.031534161 | D16: ='Data Sheet'!C24/'Data Sheet'!C$17 -> 0.027339154 | E16: ='Data Sheet'!D24/'Data Sheet'!D$17 -> 0.023153154 | F16: ='Data Sheet'!E24/'Data Sheet'!E$17 -> 0.021511358 | G16: ='Data Sheet'!F24/'Data Sheet'!F$17 -> 0.024806379 | H16: ='Data Sheet'!G24/'Data Sheet'!G$17 -> 0.021811726 | I16: ='Data Sheet'!H24/'Data Sheet'!H$17 -> 0.018302555 | J16: ='Data Sheet'!I24/'Data Sheet'!I$17 -> 0.018451465 | ... L16: ='Data Sheet'!K24/'Data Sheet'!K$17 -> 0.02949139
B17: ='Data Sheet'!A25 -> Other Income | C17: ='Data Sheet'!B25/'Data Sheet'!B$17 -> 0.037842065 | D17: ='Data Sheet'!C25/'Data Sheet'!C$17 -> 0.041120615 | E17: ='Data Sheet'!D25/'Data Sheet'!D$17 -> 0.051550395 | F17: ='Data Sheet'!E25/'Data Sheet'!E$17 -> 0.043038024 | G17: ='Data Sheet'!F25/'Data Sheet'!F$17 -> 0.04894579 | H17: ='Data Sheet'!G25/'Data Sheet'!G$17 -> 0.052315944 | I17: ='Data Sheet'!H25/'Data Sheet'!H$17 -> 0.031490386 | J17: ='Data Sheet'!I25/'Data Sheet'!I$17 -> 0.029577957 | ... L17: ='Data Sheet'!K25/'Data Sheet'!K$17 -> 0.23624656
B18: ='Data Sheet'!A26 -> Depreciation | C18: ='Data Sheet'!B26/'Data Sheet'!B$17 -> 0.027490234 | D18: ='Data Sheet'!C26/'Data Sheet'!C$17 -> 0.026954751 | E18: ='Data Sheet'!D26/'Data Sheet'!D$17 -> 0.028453629 | F18: ='Data Sheet'!E26/'Data Sheet'!E$17 -> 0.028891645 | G18: ='Data Sheet'!F26/'Data Sheet'!F$17 -> 0.033306066 | H18: ='Data Sheet'!G26/'Data Sheet'!G$17 -> 0.033407941 | I18: ='Data Sheet'!H26/'Data Sheet'!H$17 -> 0.028566628 | J18: ='Data Sheet'!I26/'Data Sheet'!I$17 -> 0.025508104 | ... L18: ='Data Sheet'!K26/'Data Sheet'!K$17 -> 0.021856705
B19: ='Data Sheet'!A27 -> Interest | C19: ='Data Sheet'!B27/'Data Sheet'!B$17 -> 0.001993514 | D19: ='Data Sheet'!C27/'Data Sheet'!C$17 -> 0.0011464286 | E19: ='Data Sheet'!D27/'Data Sheet'!D$17 -> 0.0026470151 | F19: ='Data Sheet'!E27/'Data Sheet'!E$17 -> 0.0014770505 | G19: ='Data Sheet'!F27/'Data Sheet'!F$17 -> 0.0016477787 | H19: ='Data Sheet'!G27/'Data Sheet'!G$17 -> 0.0011768778 | I19: ='Data Sheet'!H27/'Data Sheet'!H$17 -> 0.00098920694 | J19: ='Data Sheet'!I27/'Data Sheet'!I$17 -> 0.0010966027 | ... L19: ='Data Sheet'!K27/'Data Sheet'!K$17 -> 0.00059822095
B20: ='Data Sheet'!A28 -> Profit before tax | C20: ='Data Sheet'!B28/'Data Sheet'!B$17 -> 0.37913432 | D20: ='Data Sheet'!C28/'Data Sheet'!C$17 -> 0.3747304 | E20: ='Data Sheet'!D28/'Data Sheet'!D$17 -> 0.40067974 | F20: ='Data Sheet'!E28/'Data Sheet'!E$17 -> 0.39615197 | G20: ='Data Sheet'!F28/'Data Sheet'!F$17 -> 0.4056591 | H20: ='Data Sheet'!G28/'Data Sheet'!G$17 -> 0.36417171 | I20: ='Data Sheet'!H28/'Data Sheet'!H$17 -> 0.34200062 | J20: ='Data Sheet'!I28/'Data Sheet'!I$17 -> 0.36541842 | ... L20: ='Data Sheet'!K28/'Data Sheet'!K$17 -> 0.55683869
... B23: ='Data Sheet'!A31 -> Dividend Amount | C23: ='Data Sheet'!B31/'Data Sheet'!B$17 -> 0.17452803 | D23: ='Data Sheet'!C31/'Data Sheet'!C$17 -> 0.13491568 | E23: ='Data Sheet'!D31/'Data Sheet'!D$17 -> 0.14465738 | F23: ='Data Sheet'!E31/'Data Sheet'!E$17 -> 0.14581633 | G23: ='Data Sheet'!F31/'Data Sheet'!F$17 -> 0.25262525 | H23: ='Data Sheet'!G31/'Data Sheet'!G$17 -> 0.2686286 | I23: ='Data Sheet'!H31/'Data Sheet'!H$17 -> 0.23368633 | J23: ='Data Sheet'!I31/'Data Sheet'!I$17 -> 0.27162526 | ... L23: ='Data Sheet'!K31/'Data Sheet'!K$17 -> 0.23840857
B25: ='Data Sheet'!A34 -> EBITDA | C25: ='Data Sheet'!B34/'Data Sheet'!B$17 -> 0.40861806 | D25: ='Data Sheet'!C34/'Data Sheet'!C$17 -> 0.40283158 | E25: ='Data Sheet'!D34/'Data Sheet'!D$17 -> 0.43178038 | F25: ='Data Sheet'!E34/'Data Sheet'!E$17 -> 0.42652067 | G25: ='Data Sheet'!F34/'Data Sheet'!F$17 -> 0.44061295 | H25: ='Data Sheet'!G34/'Data Sheet'!G$17 -> 0.39875653 | I25: ='Data Sheet'!H34/'Data Sheet'!H$17 -> 0.37155645 | J25: ='Data Sheet'!I34/'Data Sheet'!I$17 -> 0.39202313 | ... L25: ='Data Sheet'!K34/'Data Sheet'!K$17 -> 0.57929362
A27: # | B27: ="Common Size Balance Sheet"&" "&"- "&'Data Sheet'!$B$1 -> Common Size Balance Sheet - ITC LTD
B29: Particulars | C29: ='Data Sheet'!B56 -> 42460 | D29: ='Data Sheet'!C56 -> 42825 | E29: ='Data Sheet'!D56 -> 43190 | F29: ='Data Sheet'!E56 -> 43555 | G29: ='Data Sheet'!F56 -> 43921 | H29: ='Data Sheet'!G56 -> 44286 | I29: ='Data Sheet'!H56 -> 44651 | J29: ='Data Sheet'!I56 -> 45016 | ... L29: ='Data Sheet'!K56 -> 45747
B31: Total Liabilities | C31: ='Data Sheet'!B61/'Data Sheet'!B$61 -> 1 | D31: ='Data Sheet'!C61/'Data Sheet'!C$61 -> 1 | E31: ='Data Sheet'!D61/'Data Sheet'!D$61 -> 1 | F31: ='Data Sheet'!E61/'Data Sheet'!E$61 -> 1 | G31: ='Data Sheet'!F61/'Data Sheet'!F$61 -> 1 | H31: ='Data Sheet'!G61/'Data Sheet'!G$61 -> 1 | I31: ='Data Sheet'!H61/'Data Sheet'!H$61 -> 1 | J31: ='Data Sheet'!I61/'Data Sheet'!I$61 -> 1 | ... L31: ='Data Sheet'!K61/'Data Sheet'!K$61 -> 1
B32: ='Data Sheet'!A57 -> Equity Share Capital | C32: ='Data Sheet'!B57/'Data Sheet'!B$61 -> 0.015579847 | D32: ='Data Sheet'!C57/'Data Sheet'!C$61 -> 0.021731243 | E32: ='Data Sheet'!D57/'Data Sheet'!D$61 -> 0.018997716 | F32: ='Data Sheet'!E57/'Data Sheet'!E$61 -> 0.017087767 | G32: ='Data Sheet'!F57/'Data Sheet'!F$61 -> 0.015899729 | H32: ='Data Sheet'!G57/'Data Sheet'!G$61 -> 0.016687464 | I32: ='Data Sheet'!H57/'Data Sheet'!H$61 -> 0.015963647 | J32: ='Data Sheet'!I57/'Data Sheet'!I$61 -> 0.014479624 | ... L32: ='Data Sheet'!K57/'Data Sheet'!K$61 -> 0.014220132
B33: ='Data Sheet'!A58 -> Reserves | C33: ='Data Sheet'!B58/'Data Sheet'!B$61 -> 0.8107205 | D33: ='Data Sheet'!C58/'Data Sheet'!C$61 -> 0.80857868 | E33: ='Data Sheet'!D58/'Data Sheet'!D$61 -> 0.79839629 | F33: ='Data Sheet'!E58/'Data Sheet'!E$61 -> 0.80730116 | G33: ='Data Sheet'!F58/'Data Sheet'!F$61 -> 0.8283976 | H33: ='Data Sheet'!G58/'Data Sheet'!G$61 -> 0.80146219 | I33: ='Data Sheet'!H58/'Data Sheet'!H$61 -> 0.79308804 | J33: ='Data Sheet'!I58/'Data Sheet'!I$61 -> 0.791235 | ... L33: ='Data Sheet'!K58/'Data Sheet'!K$61 -> 0.78155148
B34: ='Data Sheet'!A59 -> Borrowings | C34: ='Data Sheet'!B59/'Data Sheet'!B$61 -> 0.0016220296 | D34: ='Data Sheet'!C59/'Data Sheet'!C$61 -> 0.00081791367 | E34: ='Data Sheet'!D59/'Data Sheet'!D$61 -> 0.00055914552 | F34: ='Data Sheet'!E59/'Data Sheet'!E$61 -> 0.00018734569 | G34: ='Data Sheet'!F59/'Data Sheet'!F$61 -> 0.0035887635 | H34: ='Data Sheet'!G59/'Data Sheet'!G$61 -> 0.0036717355 | I34: ='Data Sheet'!H59/'Data Sheet'!H$61 -> 0.0032312547 | J34: ='Data Sheet'!I59/'Data Sheet'!I$61 -> 0.0035656132 | ... L34: ='Data Sheet'!K59/'Data Sheet'!K$61 -> 0.0032333099
B35: ='Data Sheet'!A60 -> Other Liabilities | C35: ='Data Sheet'!B60/'Data Sheet'!B$61 -> 0.17207763 | D35: ='Data Sheet'!C60/'Data Sheet'!C$61 -> 0.16887216 | E35: ='Data Sheet'!D60/'Data Sheet'!D$61 -> 0.18204685 | F35: ='Data Sheet'!E60/'Data Sheet'!E$61 -> 0.17542373 | G35: ='Data Sheet'!F60/'Data Sheet'!F$61 -> 0.1521139 | H35: ='Data Sheet'!G60/'Data Sheet'!G$61 -> 0.17817861 | I35: ='Data Sheet'!H60/'Data Sheet'!H$61 -> 0.18771706 | J35: ='Data Sheet'!I60/'Data Sheet'!I$61 -> 0.19071976 | ... L35: ='Data Sheet'!K60/'Data Sheet'!K$61 -> 0.20099508
B37: Total Assets | C37: ='Data Sheet'!B76/'Data Sheet'!B$76 -> 1 | D37: ='Data Sheet'!C76/'Data Sheet'!C$76 -> 1 | E37: ='Data Sheet'!D76/'Data Sheet'!D$76 -> 1 | F37: ='Data Sheet'!E76/'Data Sheet'!E$76 -> 1 | G37: ='Data Sheet'!F76/'Data Sheet'!F$76 -> 1 | H37: ='Data Sheet'!G76/'Data Sheet'!G$76 -> 1 | I37: ='Data Sheet'!H76/'Data Sheet'!H$76 -> 1 | J37: ='Data Sheet'!I76/'Data Sheet'!I$76 -> 1 | ... L37: ='Data Sheet'!K76/'Data Sheet'!K$76 -> 1
B38: ='Data Sheet'!A62 -> Net Block | C38: ='Data Sheet'!B62/'Data Sheet'!B$76 -> 0.29247315 | D38: ='Data Sheet'!C62/'Data Sheet'!C$76 -> 0.2843284 | E38: ='Data Sheet'!D62/'Data Sheet'!D$76 -> 0.25721877 | F38: ='Data Sheet'!E62/'Data Sheet'!E$76 -> 0.27006481 | G38: ='Data Sheet'!F62/'Data Sheet'!F$76 -> 0.28085797 | H38: ='Data Sheet'!G62/'Data Sheet'!G$76 -> 0.31586551 | I38: ='Data Sheet'!H62/'Data Sheet'!H$76 -> 0.31389688 | J38: ='Data Sheet'!I62/'Data Sheet'!I$76 -> 0.30118817 | ... L38: ='Data Sheet'!K62/'Data Sheet'!K$76 -> 0.24947928
B39: ='Data Sheet'!A63 -> Capital Work in Progress | C39: ='Data Sheet'!B63/'Data Sheet'!B$76 -> 0.049557669 | D39: ='Data Sheet'!C63/'Data Sheet'!C$76 -> 0.066726335 | E39: ='Data Sheet'!D63/'Data Sheet'!D$76 -> 0.085744934 | F39: ='Data Sheet'!E63/'Data Sheet'!E$76 -> 0.057659261 | G39: ='Data Sheet'!F63/'Data Sheet'!F$76 -> 0.042121697 | H39: ='Data Sheet'!G63/'Data Sheet'!G$76 -> 0.054382439 | I39: ='Data Sheet'!H63/'Data Sheet'!H$76 -> 0.04178376 | J39: ='Data Sheet'!I63/'Data Sheet'!I$76 -> 0.03499087 | ... L39: ='Data Sheet'!K63/'Data Sheet'!K$76 -> 0.012396324
B40: ='Data Sheet'!A64 -> Investments | C40: ='Data Sheet'!B64/'Data Sheet'!B$76 -> 0.22744018 | D40: ='Data Sheet'!C64/'Data Sheet'!C$76 -> 0.3145243 | E40: ='Data Sheet'!D64/'Data Sheet'!D$76 -> 0.3432839 | F40: ='Data Sheet'!E64/'Data Sheet'!E$76 -> 0.34909151 | G40: ='Data Sheet'!F64/'Data Sheet'!F$76 -> 0.37075504 | H40: ='Data Sheet'!G64/'Data Sheet'!G$76 -> 0.33718294 | I40: ='Data Sheet'!H64/'Data Sheet'!H$76 -> 0.32179133 | J40: ='Data Sheet'!I64/'Data Sheet'!I$76 -> 0.34270874 | ... L40: ='Data Sheet'!K64/'Data Sheet'!K$76 -> 0.3945313
B41: ='Data Sheet'!A65 -> Other Assets | C41: ='Data Sheet'!B74/'Data Sheet'!B$76 -> 0.10057474 | D41: ='Data Sheet'!C74/'Data Sheet'!C$76 -> 0.09187718 | E41: ='Data Sheet'!D74/'Data Sheet'!D$76 -> 0.11019074 | F41: ='Data Sheet'!E74/'Data Sheet'!E$76 -> 0.099500495 | G41: ='Data Sheet'!F74/'Data Sheet'!F$76 -> 0.064136617 | H41: ='Data Sheet'!G74/'Data Sheet'!G$76 -> 0.054530891 | I41: ='Data Sheet'!H74/'Data Sheet'!H$76 -> 0.089608376 | J41: ='Data Sheet'!I74/'Data Sheet'!I$76 -> 0.092668776 | ... L41: ='Data Sheet'!K74/'Data Sheet'!K$76 -> 0.066674432
B42: ='Data Sheet'!A67 -> Receivables | C42: ='Data Sheet'!B67/'Data Sheet'!B$76 -> 0.03711772 | D42: ='Data Sheet'!C67/'Data Sheet'!C$76 -> 0.044264121 | E42: ='Data Sheet'!D67/'Data Sheet'!D$76 -> 0.041753631 | F42: ='Data Sheet'!E67/'Data Sheet'!E$76 -> 0.056249428 | G42: ='Data Sheet'!F67/'Data Sheet'!F$76 -> 0.033145196 | H42: ='Data Sheet'!G67/'Data Sheet'!G$76 -> 0.033916408 | I42: ='Data Sheet'!H67/'Data Sheet'!H$76 -> 0.031891541 | J42: ='Data Sheet'!I67/'Data Sheet'!I$76 -> 0.034441768 | ... L42: ='Data Sheet'!K67/'Data Sheet'!K$76 -> 0.053630968
B43: ='Data Sheet'!A68 -> Inventory | C43: ='Data Sheet'!B68/'Data Sheet'!B$76 -> 0.17544753 | D43: ='Data Sheet'!C68/'Data Sheet'!C$76 -> 0.14519399 | E43: ='Data Sheet'!D68/'Data Sheet'!D$76 -> 0.11667166 | F43: ='Data Sheet'!E68/'Data Sheet'!E$76 -> 0.10955764 | G43: ='Data Sheet'!F68/'Data Sheet'!F$76 -> 0.11485246 | H43: ='Data Sheet'!G68/'Data Sheet'!G$76 -> 0.14095788 | I43: ='Data Sheet'!H68/'Data Sheet'!H$76 -> 0.14073459 | J43: ='Data Sheet'!I68/'Data Sheet'!I$76 -> 0.13714352 | ... L43: ='Data Sheet'!K68/'Data Sheet'!K$76 -> 0.17769409
B44: ='Data Sheet'!A69 -> Cash & Bank | C44: ='Data Sheet'!B69/'Data Sheet'!B$76 -> 0.11738902 | D44: ='Data Sheet'!C69/'Data Sheet'!C$76 -> 0.053085674 | E44: ='Data Sheet'!D69/'Data Sheet'!D$76 -> 0.045136368 | F44: ='Data Sheet'!E69/'Data Sheet'!E$76 -> 0.057876855 | G44: ='Data Sheet'!F69/'Data Sheet'!F$76 -> 0.094131023 | H44: ='Data Sheet'!G69/'Data Sheet'!G$76 -> 0.063163937 | I44: ='Data Sheet'!H69/'Data Sheet'!H$76 -> 0.060293523 | J44: ='Data Sheet'!I69/'Data Sheet'!I$76 -> 0.056858155 | ... L44: ='Data Sheet'!K69/'Data Sheet'!K$76 -> 0.045593601

Sheet Ratios
B2: Ratio Analysis
B3: ='Data Sheet'!B1 -> ITC LTD
D5: Post Covid-19 Years
B6: Particulars | C6: ='Data Sheet'!G16 -> 44286 | D6: ='Data Sheet'!H16 -> 44651 | E6: ='Data Sheet'!I16 -> 45016 | F6: ='Data Sheet'!J16 -> 45382 | G6: ='Data Sheet'!K16 -> 45747 | I6: Trend | K6: Mean | L6: Industry Avg
A8: # | B8: Growth Ratios
B9: SalesGrowth | C9: =IFERROR('Historical FS'!H9,0) -> -0.0026372963 | D9: =IFERROR('Historical FS'!I9,0) -> 0.23117498 | E9: =IFERROR('Historical FS'!J9,0) -> 0.16942152 | F9: =IFERROR('Historical FS'!K9,0) -> -0.042119724 | G9: =IFERROR('Historical FS'!L9,0) -> 0.10880596 | K9: =AVERAGE(C9:G9) -> 0.092929087 | L9: 0.1
B10: GrossMarginGrowth | C10: =IFERROR(('Historical FS'!H14/'Historical FS'!G14)-1,0) -> -0.10700914 | D10: =IFERROR(('Historical FS'!I14/'Historical FS'!H14)-1,0) -> 0.18839611 | E10: =IFERROR(('Historical FS'!J14/'Historical FS'!I14)-1,0) -> 0.22659213 | F10: =IFERROR(('Historical FS'!K14/'Historical FS'!J14)-1,0) -> -0.01075976 | G10: =IFERROR(('Historical FS'!L14/'Historical FS'!K14)-1,0) -> 0.049221548 | K10: =AVERAGE(C10:G10) -> 0.069288177 | L10: -
B11: EBITDA Growth | C11: =IFERROR(('Historical FS'!H23/'Historical FS'!G23)-1,0) -> -0.09738264 | D11: =IFERROR(('Historical FS'!I23/'Historical FS'!H23)-1,0) -> 0.14719376 | E11: =IFERROR(('Historical FS'!J23/'Historical FS'!I23)-1,0) -> 0.2338375 | F11: =IFERROR(('Historical FS'!K23/'Historical FS'!J23)-1,0) -> 0.025756513 | G11: =IFERROR(('Historical FS'!L23/'Historical FS'!K23)-1,0) -> 0.53006384 | K11: =AVERAGE(C11:G11) -> 0.16789379 | L11: -
B12: EBT Growth | C12: =IFERROR(('Historical FS'!H32/'Historical FS'!G32)-1,0) -> -0.10463913 | D12: =IFERROR(('Historical FS'!I32/'Historical FS'!H32)-1,0) -> 0.15621995 | E12: =IFERROR(('Historical FS'!J32/'Historical FS'!I32)-1,0) -> 0.24949531 | F12: =IFERROR(('Historical FS'!K32/'Historical FS'!J32)-1,0) -> 0.040350961 | G12: =IFERROR(('Historical FS'!L32/'Historical FS'!K32)-1,0) -> 0.55570009 | K12: =AVERAGE(C12:G12) -> 0.17942544 | L12: 0.034
B13: Net Profit Growth | C13: =IFERROR(('Historical FS'!H38/'Historical FS'!G38)-1,0) -> -0.14172585 | D13: =IFERROR(('Historical FS'!I38/'Historical FS'!H38)-1,0) -> 0.15843002 | E13: =IFERROR(('Historical FS'!J38/'Historical FS'!I38)-1,0) -> 0.25630889 | F13: =IFERROR(('Historical FS'!K38/'Historical FS'!J38)-1,0) -> 0.065444284 | G13: =IFERROR(('Historical FS'!L38/'Historical FS'!K38)-1,0) -> 0.68916543 | K13: =AVERAGE(C13:G13) -> 0.20552456 | L13: 0.041
B14: Self Sustained Growth Rate | C14: =C27*C28 -> 0.0025008559 | D14: =D27*D28 -> 0.021316433 | E14: =E27*E28 -> 0.0030846533 | F14: =F27*F28 -> 0.048114942 | G14: =G27*G28 -> 0.24410592 | K14: =AVERAGE(C14:G14) -> 0.063824562 | L14: -
B15: Dividend Growth | C15: =IFERROR(('Data Sheet'!G34/'Data Sheet'!F34)-1,0) -> -0.09738264 | D15: =IFERROR(('Data Sheet'!H34/'Data Sheet'!G34)-1,0) -> 0.14719376 | E15: =IFERROR(('Data Sheet'!I34/'Data Sheet'!H34)-1,0) -> 0.2338375 | F15: =IFERROR(('Data Sheet'!J34/'Data Sheet'!I34)-1,0) -> 0.025756513 | G15: =IFERROR(('Data Sheet'!K34/'Data Sheet'!J34)-1,0) -> 0.53006384 | K15: =AVERAGE(C15:G15) -> 0.16789379 | L15: 0.124
A17: # | B17: Profitability Ratios
B18: Gross Margin | C18: =IFERROR('Historical FS'!H15,0) -> 0.45426509 | D18: =IFERROR('Historical FS'!I15,0) -> 0.43848102 | E18: =IFERROR('Historical FS'!J15,0) -> 0.45991746 | F18: =IFERROR('Historical FS'!K15,0) -> 0.47497466 | G18: =IFERROR('Historical FS'!L15,0) -> 0.44945073 | K18: =AVERAGE(C18:G18) -> 0.45541779 | L18: -
B19: EBITDA Margin | C19: =IFERROR('Historical FS'!H24,0) -> 0.39875653 | D19: =IFERROR('Historical FS'!I24,0) -> 0.37155645 | E19: =IFERROR('Historical FS'!J24,0) -> 0.39202313 | F19: =IFERROR('Historical FS'!K24,0) -> 0.41980223 | G19: =IFERROR('Historical FS'!L24,0) -> 0.57929362 | K19: =AVERAGE(C19:G19) -> 0.43228639 | L19: -
B20: EBIT Margin | C20: =IFERROR('Data Sheet'!G33/'Data Sheet'!G17,0) -> 0.36534859 | D20: =IFERROR('Data Sheet'!H33/'Data Sheet'!H17,0) -> 0.34298982 | E20: =IFERROR('Data Sheet'!I33/'Data Sheet'!I17,0) -> 0.36651502 | F20: =IFERROR('Data Sheet'!J33/'Data Sheet'!J17,0) -> 0.3974556 | G20: =IFERROR('Data Sheet'!K33/'Data Sheet'!K17,0) -> 0.55743691 | K20: =AVERAGE(C20:G20) -> 0.40594919 | L20: -
B21: EBT Margin | C21: =IFERROR('Historical FS'!H33,0) -> 0.36417171 | D21: =IFERROR('Historical FS'!I33,0) -> 0.34200062 | E21: =IFERROR('Historical FS'!J33,0) -> 0.36541842 | F21: =IFERROR('Historical FS'!K33,0) -> 0.39687988 | G21: =IFERROR('Historical FS'!L33,0) -> 0.55683869 | K21: =AVERAGE(C21:G21) -> 0.40506186 | L21: -
B22: Net Profit Margin | C22: =IFERROR('Historical FS'!H39,0) -> 0.27169251 | D22: =IFERROR('Historical FS'!I39,0) -> 0.25563934 | E22: =IFERROR('Historical FS'!J39,0) -> 0.2746332 | F22: =IFERROR('Historical FS'!K39,0) -> 0.3054728 | G22: =IFERROR('Historical FS'!L39,0) -> 0.46536014 | K22: =AVERAGE(C22:G22) -> 0.3145596 | L22: 0.12
B23: SalesExpenses%Sales | C23: =IFERROR('Historical FS'!H18,0) -> 0.1975767 | D23: =IFERROR('Historical FS'!I18,0) -> 0.1752656 | E23: =IFERROR('Historical FS'!J18,0) -> 0.18047665 | F23: =IFERROR('Historical FS'!K18,0) -> 0.19846414 | G23: =IFERROR('Historical FS'!L18,0) -> 0.19326821 | K23: =AVERAGE(C23:G23) -> 0.18901026 | L23: -
B24: Depreciation%Sales | C24: =IFERROR('Historical FS'!H30,0) -> 0.033407941 | D24: =IFERROR('Historical FS'!I30,0) -> 0.028566628 | E24: =IFERROR('Historical FS'!J30,0) -> 0.025508104 | F24: =IFERROR('Historical FS'!K30,0) -> 0.022346631 | G24: =IFERROR('Historical FS'!L30,0) -> 0.021856705 | K24: =AVERAGE(C24:G24) -> 0.026337202 | L24: -
B25: OperatingIncome%Sales | C25: =C20 -> 0.36534859 | D25: =D20 -> 0.34298982 | E25: =E20 -> 0.36651502 | F25: =F20 -> 0.3974556 | G25: =G20 -> 0.55743691 | K25: =AVERAGE(C25:G25) -> 0.40594919 | L25: -
B26: Return on Capital Employed | C26: =IFERROR(('Historical FS'!H23-'Historical FS'!H29)/SUM('Data Sheet'!G57:G59),0) -> 0.29687699 | D26: =IFERROR(('Historical FS'!I23-'Historical FS'!I29)/SUM('Data Sheet'!H57:H59),0) -> 0.33171927 | E26: =IFERROR(('Historical FS'!J23-'Historical FS'!J29)/SUM('Data Sheet'!I57:I59),0) -> 0.37420679 | F26: =IFERROR(('Historical FS'!K23-'Historical FS'!K29)/SUM('Data Sheet'!J57:J59),0) -> 0.36091131 | G26: =IFERROR(('Historical FS'!L23-'Historical FS'!L29)/SUM('Data Sheet'!K57:K59),0) -> 0.59714506 | K26: =AVERAGE(C26:G26) -> 0.39217188 | L26: -
B27: Retained Earnings% | C27: =IFERROR('Historical FS'!H49,0) -> 0.011277094 | D27: =IFERROR('Historical FS'!I49,0) -> 0.085874917 | E27: =IFERROR('Historical FS'!J49,0) -> 0.010952563 | F27: =IFERROR('Historical FS'!K49,0) -> 0.17275494 | G27: =IFERROR('Historical FS'!L49,0) -> 0.48769017 | K27: =AVERAGE(C27:G27) -> 0.15370994 | L27: -
B28: Return on Equity% | C28: =IFERROR('Historical FS'!H38/SUM('Data Sheet'!G57:G58),0) -> 0.22176421 | D28: =IFERROR('Historical FS'!I38/SUM('Data Sheet'!H57:H58),0) -> 0.24822654 | E28: =IFERROR('Historical FS'!J38/SUM('Data Sheet'!I57:I58),0) -> 0.28163758 | F28: =IFERROR('Historical FS'!K38/SUM('Data Sheet'!J57:J58),0) -> 0.27851558 | G28: =IFERROR('Historical FS'!L38/SUM('Data Sheet'!K57:K58),0) -> 0.50053484 | K28: =AVERAGE(C28:G28) -> 0.30613575 | L28: 0.35
A30: # | B30: Solvency Ratios
B31: Interest Coverage Ratio | C31: =IFERROR(('Historical FS'!H23-'Historical FS'!H29)/'Historical FS'!H26,0) -> 310.43885 | D31: =IFERROR(('Historical FS'!I23-'Historical FS'!I29)/'Historical FS'!I26,0) -> 346.73212 | E31: =IFERROR(('Historical FS'!J23-'Historical FS'!J29)/'Historical FS'!J26,0) -> 334.22772 | F31: =IFERROR(('Historical FS'!K23-'Historical FS'!K29)/'Historical FS'!K26,0) -> 690.35873 | G31: =IFERROR(('Historical FS'!L23-'Historical FS'!L29)/'Historical FS'!L26,0) -> 931.82446 | K31: =AVERAGE(C31:G31) -> 522.71638 | L31: 10
A33: # | B33: Efficiency Ratios
B34: Debtor Turnover Ratio | C34: =IFERROR('Historical FS'!H8/'Historical FS'!H64,0) -> 19.689591 | D34: =IFERROR('Historical FS'!I8/'Historical FS'!I64,0) -> 24.633226 | E34: =IFERROR('Historical FS'!J8/'Historical FS'!J64,0) -> 23.990173 | F34: =IFERROR('Historical FS'!K8/'Historical FS'!K64,0) -> 16.874063 | G34: =IFERROR('Historical FS'!L8/'Historical FS'!L64,0) -> 15.959451 | K34: =AVERAGE(C34:G34) -> 20.229301 | L34: 45.62
B35: Creditor Turnover Ratio | C35: =IFERROR('Historical FS'!H8/'Historical FS'!H55,0) -> 3.7479256 | D35: =IFERROR('Historical FS'!I8/'Historical FS'!I55,0) -> 4.1849768 | E35: =IFERROR('Historical FS'!J8/'Historical FS'!J55,0) -> 4.3323459 | F35: =IFERROR('Historical FS'!K8/'Historical FS'!K55,0) -> 4.0093121 | G35: =IFERROR('Historical FS'!L8/'Historical FS'!L55,0) -> 4.2584165 | K35: =AVERAGE(C35:G35) -> 4.1065954 | L35: 5.04
B36: Inventory Turnover | C36: =IFERROR('Historical FS'!H11/'Historical FS'!H65,0) -> 2.5854666 | D36: =IFERROR('Historical FS'!I11/'Historical FS'!I65,0) -> 3.1344431 | E36: =IFERROR('Historical FS'!J11/'Historical FS'!J65,0) -> 3.253896 | F36: =IFERROR('Historical FS'!K11/'Historical FS'!K65,0) -> 2.5200517 | G36: =IFERROR('Historical FS'!L11/'Historical FS'!L65,0) -> 2.6518977 | K36: =AVERAGE(C36:G36) -> 2.829151 | L36: 3
B37: Fixed Asset Turnover | C37: =IFERROR('Historical FS'!H8/'Historical FS'!H58,0) -> 2.1141916 | D37: =IFERROR('Historical FS'!I8/'Historical FS'!I58,0) -> 2.5027058 | E37: =IFERROR('Historical FS'!J8/'Historical FS'!J58,0) -> 2.743348 | F37: =IFERROR('Historical FS'!K8/'Historical FS'!K58,0) -> 2.4418189 | G37: =IFERROR('Historical FS'!L8/'Historical FS'!L58,0) -> 3.4308292 | K37: =AVERAGE(C37:G37) -> 2.6465787 | L37: -
B38: CFO/Sales | C38: =IFERROR('Historical FS'!H$75/'Historical FS'!H8,0) -> 0.25431625 | D38: =IFERROR('Historical FS'!I$75/'Historical FS'!I8,0) -> 0.26013076 | E38: =IFERROR('Historical FS'!J$75/'Historical FS'!J8,0) -> 0.26618455 | F38: =IFERROR('Historical FS'!K$75/'Historical FS'!K8,0) -> 0.2528834 | G38: =IFERROR('Historical FS'!L$75/'Historical FS'!L8,0) -> 0.2340183 | K38: =AVERAGE(C38:G38) -> 0.25350665 | L38: -
B39: Capital Turnover Ratio | C39: =IFERROR('Historical FS'!H8/SUM('Historical FS'!H52:H53),0) -> 0.81623233 | D39: =IFERROR('Historical FS'!I8/SUM('Historical FS'!I52:I53),0) -> 0.97100291 | E39: =IFERROR('Historical FS'!J8/SUM('Historical FS'!J52:J53),0) -> 1.0255045 | F39: =IFERROR('Historical FS'!K8/SUM('Historical FS'!K52:K53),0) -> 0.91175245 | G39: =IFERROR('Historical FS'!L8/SUM('Historical FS'!L52:L53),0) -> 1.075586 | K39: =AVERAGE(C39:G39) -> 0.96001563 | L39: -
A41: # | B41: Working Capital Efficiency Ratios
B42: Debtor Days | C42: =365/C34 -> 18.537714 | D42: =365/D34 -> 14.817385 | E42: =365/E34 -> 15.214563 | F42: =365/F34 -> 21.630831 | G42: =365/G34 -> 22.870462 | K42: =AVERAGE(C42:G42) -> 18.614191 | L42: =365/L34 -> 8.0008768
B43: Payable Days | C43: =365/C35 -> 97.387204 | D43: =365/D35 -> 87.216733 | E43: =365/E35 -> 84.249966 | F43: =365/F35 -> 91.038061 | G43: =365/G35 -> 85.712611 | K43: =AVERAGE(C43:G43) -> 89.120915 | L43: =365/L35 -> 72.420635
B44: Inventory Days | C44: =365/C36 -> 141.17374 | D44: =365/D36 -> 116.44812 | E44: =365/E36 -> 112.17322 | F44: =365/F36 -> 144.8383 | G44: =365/G36 -> 137.63728 | K44: =AVERAGE(C44:G44) -> 130.45413 | L44: =365/L36 -> 121.66667
B45: Cash Conversion Cycle | C45: =(C42+C44)-C43 -> 62.324253 | D45: =(D42+D44)-D43 -> 44.04877 | E45: =(E42+E44)-E43 -> 43.13782 | F45: =(F42+F44)-F43 -> 75.431065 | G45: =(G42+G44)-G43 -> 74.795134 | K45: =AVERAGE(C45:G45) -> 59.947408 | L45: =(L42+L44)-L43 -> 57.246909
A47: # | B47: Liquidity Ratios
B48: CFO/Total Assets | C48: =IFERROR('Historical FS'!H$75/'Historical FS'!H69,0) -> 0.16983244 | D48: =IFERROR('Historical FS'!I$75/'Historical FS'!I69,0) -> 0.20435652 | E48: =IFERROR('Historical FS'!J$75/'Historical FS'!J69,0) -> 0.2199387 | F48: =IFERROR('Historical FS'!K$75/'Historical FS'!K69,0) -> 0.18722743 | G48: =IFERROR('Historical FS'!L$75/'Historical FS'!L69,0) -> 0.20030113 | K48: =AVERAGE(C48:G48) -> 0.19633124 | L48: -
B49: CFO/Total Debt | C49: =IFERROR('Historical FS'!H$75/'Historical FS'!H54,0) -> 46.253997 | D49: =IFERROR('Historical FS'!I$75/'Historical FS'!I54,0) -> 63.243706 | E49: =IFERROR('Historical FS'!J$75/'Historical FS'!J54,0) -> 61.683277 | F49: =IFERROR('Historical FS'!K$75/'Historical FS'!K54,0) -> 56.615562 | G49: =IFERROR('Historical FS'!L$75/'Historical FS'!L54,0) -> 61.949251 | K49: =AVERAGE(C49:G49) -> 57.949159 | L49: -

Sheet WACC
B2: Calculation of WACC
B3: ='Data Sheet'!B1 -> ITC LTD
B5: All figures are in INR unless stated otherwise.
B7: 1. Peer Comps
G8: Debt/ | H8: Debt/ | I8: Levered | J8: Unlevered
B9: Name | C9: Country | D9: Total Debt | E9: Total Equity | F9: Tax Rate 1 | G9: Equity | H9: Capital | I9: Beta 2 | J9: Beta 3
B11: ='WACC Data'!C4 -> ITC | C11: India | D11: ='WACC Data'!D4 -> 285 | E11: ='WACC Data'!E4 -> 519668 | F11: 0.3 | G11: =D11/E11 -> 0.00054842707 | H11: =D11/SUM(D11:E11) -> 0.00054812647 | I11: ='Beta - Regression'!J7 -> 0.49821386 | J11: =I11/1+(1-F11)*G11 -> 0.49859776
B12: ='WACC Data'!C5 -> Godfrey Phillips | C12: India | D12: ='WACC Data'!D5 -> 179 | E12: ='WACC Data'!E5 -> 45635 | F12: 0.3 | G12: =D12/E12 -> 0.003922428 | H12: =D12/SUM(D12:E12) -> 0.0039071026 | I12: 1.22 | J12: =I12/1+(1-F12)*G12 -> 1.2227457
B13: ='WACC Data'!C6 -> VST Industries | C13: India | D13: ='WACC Data'!D6 -> 0 | E13: ='WACC Data'!E6 -> 4791 | F13: 0.3 | G13: =D13/E13 -> 0 | H13: =D13/SUM(D13:E13) -> 0 | I13: 0.88 | J13: =I13/1+(1-F13)*G13 -> 0.88
B14: ='WACC Data'!C7 -> NTC Industries | C14: India | D14: ='WACC Data'!D7 -> 77.1 | E14: ='WACC Data'!E7 -> 249 | F14: 0.3 | G14: =D14/E14 -> 0.30963855 | H14: =D14/SUM(D14:E14) -> 0.23643054 | I14: 0.88 | J14: =I14/(1+(1-F14)*G14) -> 0.72323992
B15: ='WACC Data'!C8 -> Indian Wood Prod | C15: India | D15: ='WACC Data'!D8 -> 79.9 | E15: ='WACC Data'!E8 -> 253 | F15: 0.3 | G15: =D15/E15 -> 0.31581028 | H15: =D15/SUM(D15:E15) -> 0.24001202 | I15: 0.53 | J15: =I15/(1+(1-F15)*G15) -> 0.43404655
B16: ='WACC Data'!C9 -> Elitecon Inter. | C16: India | D16: ='WACC Data'!D9 -> 2.51 | E16: ='WACC Data'!E9 -> 32537 | F16: 0.3 | G16: =D16/E16 -> 7.7142945e-05 | H16: =D16/SUM(D16:E16) -> 7.7136994e-05 | I16: 0.2 | J16: =I16/(1+(1-F16)*G16) -> 0.1999892
E18: Average | F18: =AVERAGE(F11:F16) -> 0.3 | G18: =AVERAGE(G11:G16) -> 0.10499947 | H18: =AVERAGE(H11:H16) -> 0.080162487 | I18: =AVERAGE(I11:I16) -> 0.70136898 | J18: =AVERAGE(J11:J16) -> 0.65976986
E19: Median | F19: =MEDIAN(F11:F16) -> 0.3 | G19: =MEDIAN(G11:G16) -> 0.0022354275 | H19: =MEDIAN(H11:H16) -> 0.0022276145 | I19: =MEDIAN(I11:I16) -> 0.705 | J19: =MEDIAN(J11:J16) -> 0.61091884
B21: 2. Cost of Debt | G21: 4. Levered Beta
B23: Pre-tax Cost of Debt | E23: ='Data Sheet'!K27/'Data Sheet'!K59 -> 0.15836086 | G23: Comps Median Unlevered Beta | J23: =J19 -> 0.61091884
B24: Tax Rate | E24: 0.3 | G24: Target Debt/ Equity | J24: =E35 -> 0.08714853
B25: After Tax Cost of Debt | E25: =E23*(1-E24) -> 0.1108526 | G25: Tax Rate | J25: =F11 -> 0.3
G26: Levered Beta 4 | J26: =J23*(1+(1-J25)*J24) -> 0.64818732
B28: 3. Capital Structure | G28: 5. Cost of Equity
C30: Current | D30: Current % | E30: Target % | G30: Risk Free Rate | J30: 0.0649
B31: Total Debt | C31: =D11 -> 285 | D31: =C31/C33 -> 0.00054812647 | E31: =H18 -> 0.080162487 | G31: Equity Risk Premium | J31: =Rm!F5-WACC!J30 -> 0.101448
B32: Market Capitalization | C32: =E11 -> 519668 | D32: =C32/C33 -> 0.99945187 | E32: =1-E31 -> 0.91983751 | G32: Levered Beta | J32: =J26 -> 0.64818732
B33: Total Capitalization | C33: =SUM(C31:C32) -> 519953 | D33: =SUM(D31:D32) -> 1 | E33: =SUM(E31:E32) -> 1 | G33: Cost of Equity | J33: =J30+(J31*J32) -> 0.13065731
B35: Debt / Equity | D35: =D31/D32 -> 0.00054842707 | E35: =E31/E32 -> 0.08714853 | G35: 6. Weighted Average Cost of Capital
B37: 1. Tax Rate considered as Marginal Tax Rate for the country | I37: Total Cost | J37: Total Weight
B38: 2. Levered Beta is based on 5 year monthly data | G38: Debt Capital | I38: =E25 -> 0.1108526 | J38: =E31 -> 0.080162487
B39: 3. Unlevered Beta = Levered Beta/(1+(1-Tax Rate) x Debt/Equity) | G39: Equity Capital | I39: =J33 -> 0.13065731 | J39: =E32 -> 0.91983751
B40: 4. Levered Beta = Unlevered Beta*(1+(1-Tax Rate) x Debt/Equity) | G40: Weighted Average Cost of Capital | J40: =SUMPRODUCT(I38:I39,J38:J39) -> 0.12906971

Sheet Intrinsic Growth
B2: Calculation of Intrinsic Growth
B3: ='[2]Data Sheet'!B1 -> ITC LTD
A5: # | B5: Calculation of ROIC | G5: ='RAW FSn'!J4 -> 44256 | H5: ='RAW FSn'!K4 -> 44621 | I5: ='RAW FSn'!L4 -> 44986 | J5: ='RAW FSn'!M4 -> 45352 | K5: ='RAW FSn'!N4 -> 45717
B7: Current Assets
B8: ='RAW FSn'!B36 -> Other Assets | G8: ='RAW FSn'!J37 -> 10397 | H8: ='RAW FSn'!K37 -> 10864 | I8: ='RAW FSn'!L37 -> 11771 | J8: ='RAW FSn'!M37 -> 14153 | K8: ='RAW FSn'!N37 -> 15638
B9: ='RAW FSn'!B37 -> Inventories | G9: ='RAW FSn'!J38 -> 2502 | H9: ='RAW FSn'!K38 -> 2462 | I9: ='RAW FSn'!L38 -> 2956 | J9: ='RAW FSn'!M38 -> 4026 | K9: ='RAW FSn'!N38 -> 4720
B10: ='RAW FSn'!B40 -> Loans n Advances | G10: ='RAW FSn'!J41 -> 4015 | H10: ='RAW FSn'!K41 -> 6906 | I10: ='RAW FSn'!L41 -> 7941 | J10: ='RAW FSn'!M41 -> 4531 | K10: ='RAW FSn'!N41 -> 5858
B11: Total Current Assets | G11: =SUM(G8:G10) -> 16914 | H11: =SUM(H8:H10) -> 20232 | I11: =SUM(I8:I10) -> 22668 | J11: =SUM(J8:J10) -> 22710 | K11: =SUM(K8:K10) -> 26216
B13: Current Liabilities
B14: ='RAW FSn'!B14 -> Trade Payables | G14: ='RAW FSn'!J14 -> 4319 | H14: ='RAW FSn'!K14 -> 4417 | I14: ='RAW FSn'!L14 -> 4659 | J14: ='RAW FSn'!M14 -> 4798 | K14: ='RAW FSn'!N14 -> 4807
B15: ='RAW FSn'!B15 -> Advance from Customers | G15: ='RAW FSn'!J15 -> 811 | H15: ='RAW FSn'!K15 -> 1278 | I15: ='RAW FSn'!L15 -> 1295 | J15: ='RAW FSn'!M15 -> 886 | K15: ='RAW FSn'!N15 -> 1264
B16: ='RAW FSn'!B16 -> Other liability items | G16: ='RAW FSn'!J16 -> 7666 | H16: ='RAW FSn'!K16 -> 8429 | I16: ='RAW FSn'!L16 -> 10032 | J16: ='RAW FSn'!M16 -> 10877 | K16: ='RAW FSn'!N16 -> 11249
B17: Total Current Liabilities | G17: =SUM(G14:G16) -> 12796 | H17: =SUM(H14:H16) -> 14124 | I17: =SUM(I14:I16) -> 15986 | J17: =SUM(J14:J16) -> 16561 | K17: =SUM(K14:K16) -> 17320
A19: # | B19: Net Working Capital | G19: =G11-G17 -> 4118 | H19: =H11-H17 -> 6108 | I19: =I11-I17 -> 6682 | J19: =J11-J17 -> 6149 | K19: =K11-K17 -> 8896
B21: Non Current Assets
B22: ='RAW FSn'!B20 -> Land | G22: ='RAW FSn'!J20 -> 2889 | H22: ='RAW FSn'!K20 -> 2829 | I22: ='RAW FSn'!L20 -> 2830 | J22: ='RAW FSn'!M20 -> 2865 | K22: ='RAW FSn'!N20 -> 1588
B23: ='RAW FSn'!B21 -> Building | G23: ='RAW FSn'!J21 -> 8387 | H23: ='RAW FSn'!K21 -> 9100 | I23: ='RAW FSn'!L21 -> 9789 | J23: ='RAW FSn'!M21 -> 10944 | K23: ='RAW FSn'!N21 -> 7550
B24: ='RAW FSn'!B22 -> Plant Machinery | G24: ='RAW FSn'!J22 -> 15307 | H24: ='RAW FSn'!K22 -> 16912 | I24: ='RAW FSn'!L22 -> 18480 | J24: ='RAW FSn'!M22 -> 20718 | K24: ='RAW FSn'!N22 -> 19423
B25: ='RAW FSn'!B23 -> Equipments | G25: ='RAW FSn'!J23 -> 41 | H25: ='RAW FSn'!K23 -> 44 | I25: ='RAW FSn'!L23 -> 44 | J25: ='RAW FSn'!M23 -> 53 | K25: ='RAW FSn'!N23 -> 63
B26: ='RAW FSn'!B24 -> Furniture n fittings | G26: ='RAW FSn'!J24 -> 833 | H26: ='RAW FSn'!K24 -> 907 | I26: ='RAW FSn'!L24 -> 1000 | J26: ='RAW FSn'!M24 -> 1068 | K26: ='RAW FSn'!N24 -> 282
B27: ='RAW FSn'!B25 -> Railway sidings | G27: ='RAW FSn'!J25 -> 2 | H27: ='RAW FSn'!K25 -> 2 | I27: ='RAW FSn'!L25 -> 2 | J27: ='RAW FSn'!M25 -> 2 | K27: ='RAW FSn'!N25 -> 2
B28: ='RAW FSn'!B26 -> Vehicles | G28: ='RAW FSn'!J26 -> 180 | H28: ='RAW FSn'!K26 -> 179 | I28: ='RAW FSn'!L26 -> 189 | J28: ='RAW FSn'!M26 -> 192 | K28: ='RAW FSn'!N26 -> 141
B29: ='RAW FSn'!B27 -> Intangible Assets | G29: ='RAW FSn'!J27 -> 2734 | H29: ='RAW FSn'!K27 -> 2744 | I29: ='RAW FSn'!L27 -> 3490 | J29: ='RAW FSn'!M27 -> 3505 | K29: ='RAW FSn'!N27 -> 3622
B30: ='RAW FSn'!B28 -> Other fixed assets | G30: ='RAW FSn'!J28 -> 716 | H30: ='RAW FSn'!K28 -> 719 | I30: ='RAW FSn'!L28 -> 786 | J30: ='RAW FSn'!M28 -> 841 | K30: ='RAW FSn'!N28 -> 967
B32: Gross Block | G32: =SUM(G22:G30) -> 31089 | H32: =SUM(H22:H30) -> 33436 | I32: =SUM(I22:I30) -> 36610 | J32: =SUM(J22:J30) -> 40188 | K32: =SUM(K22:K30) -> 33638
B33: Accumulated Depreciation | G33: =-'RAW FSn'!J30 -> -7790 | H33: =-'RAW FSn'!K30 -> -9204 | I33: =-'RAW FSn'!L30 -> -10757 | J33: =-'RAW FSn'!M30 -> -12368 | K33: =-'RAW FSn'!N30 -> -11683
A34: # | B34: Net Non Current Assets | G34: =SUM(G32:G33) -> 23299 | H34: =SUM(H32:H33) -> 24232 | I34: =SUM(I32:I33) -> 25853 | J34: =SUM(J32:J33) -> 27820 | K34: =SUM(K32:K33) -> 21955
A36: # | B36: Invested Capital | G36: =G34+G19 -> 27417 | H36: =H34+H19 -> 30340 | I36: =I34+I19 -> 32535 | J36: =J34+J19 -> 33969 | K36: =K34+K19 -> 30851
B37: EBIT | G37: ='Data Sheet'!G33 -> 17996.14 | H37: ='Data Sheet'!H33 -> 20800.46 | I37: ='Data Sheet'!I33 -> 25992.89 | J37: ='Data Sheet'!J33 -> 26999.93 | K37: ='Data Sheet'!K33 -> 41988.01
B38: Tax Rate | G38: 0.3 | H38: 0.3 | I38: 0.3 | J38: 0.3 | K38: 0.3
A40: # | B40: ROIC | G40: =(G37*(1-G38))/G36 -> 0.45947033 | H40: =(H37*(1-H38))/H36 -> 0.47990514 | I40: =(I37*(1-I38))/I36 -> 0.5592446 | J40: =(J37*(1-J38))/J36 -> 0.55638821 | K40: =(K37*(1-K38))/K36 -> 0.95269544
A42: # | B42: Calculation of Reinvestment Rate | G42: =G5 -> 44256 | H42: =H5 -> 44621 | I42: =I5 -> 44986 | J42: =J5 -> 45352 | K42: =K5 -> 45717
B44: CAPEX | G44: =-SUM('RAW FSn'!J53:J54) -> 1834 | H44: =-SUM('RAW FSn'!K53:K54) -> 2009 | I44: =-SUM('RAW FSn'!L53:L54) -> 2694 | J44: =-SUM('RAW FSn'!M53:M54) -> 3456 | K44: =-SUM('RAW FSn'!N53:N54) -> 2104
B45: Change in Working Capital | H45: =H19-G19 -> 1990 | I45: =I19-H19 -> 574 | J45: =J19-I19 -> -533 | K45: =K19-J19 -> 2747
B46: Depriciation | H46: ='Data Sheet'!H26 -> 1732.41 | I46: ='Data Sheet'!I26 -> 1809.01 | J46: ='Data Sheet'!J26 -> 1518.05 | K46: ='Data Sheet'!K26 -> 1646.32
B48: EBIT | G48: =G37 -> 17996.14 | H48: =H37 -> 20800.46 | I48: =I37 -> 25992.89 | J48: =J37 -> 26999.93 | K48: =K37 -> 41988.01
B49: Tax Rate | G49: 0.3 | H49: 0.3 | I49: 0.3 | J49: 0.3 | K49: 0.3
B50: EBIT(1-T) | G50: =G48*(1-G49) -> 12597.298 | H50: =H48*(1-H49) -> 14560.322 | I50: =I48*(1-I49) -> 18195.023 | J50: =J48*(1-J49) -> 18899.951 | K50: =K48*(1-K49) -> 29391.607
B52: Net CAPEX/Reinvestment | H52: =SUM(H44:H45)-H46 -> 2266.59 | I52: =SUM(I44:I45)-I46 -> 1458.99 | J52: =SUM(J44:J45)-J46 -> 1404.95 | K52: =SUM(K44:K45)-K46 -> 3204.68
B54: Reinvestment Rate | H54: =H52/H50 -> 0.15566895 | I54: =I52/I50 -> 0.080186214 | J54: =J52/J50 -> 0.074336172 | K54: =K52/K50 -> 0.10903385
B56: 4 Year Average | C56: =AVERAGE(H54:K54) -> 0.1048063
B57: 4 Year Median | C57: =MEDIAN(H54:K54) -> 0.094610031
A59: # | B59: Calculation of Growth Rate | G59: =G42 -> 44256 | H59: =H42 -> 44621 | I59: =I42 -> 44986 | J59: =J42 -> 45352 | K59: =K42 -> 45717
B61: Reinvestment Rate | H61: =H54 -> 0.15566895 | I61: =I54 -> 0.080186214 | J61: =J54 -> 0.074336172 | K61: =K54 -> 0.10903385
B62: ROIC | H62: =H40 -> 0.47990514 | I62: =I40 -> 0.5592446 | J62: =J40 -> 0.55638821 | K62: =K40 -> 0.95269544
B64: Intrinsic Growth | H64: =H61*H62 -> 0.074706328 | I64: =I61*I62 -> 0.044843707 | J64: =J61*J62 -> 0.041359769 | K64: =K61*K62 -> 0.10387605
B66: 4 Year Average | C66: =AVERAGE(H64:K64) -> 0.066196463
B67: 4 Year Median | C67: =MEDIAN(H64:K64) -> 0.059775018

Sheet DCF
B2: Discounted Cash Flow Model
B3: ='[2]Data Sheet'!B1 -> ITC LTD
A5: # | B5: Calculation of PV of FCFF | F5: ='Intrinsic Growth'!K5 -> 45717 | G5: =F5+365 -> 46082 | H5: =G5+366 -> 46448 | I5: =H5+365 -> 46813 | J5: =I5+365 -> 47178 | K5: =J5+365 -> 47543
B7: Growth Rate | F7: =D19 -> 0.066196463 | G7: =F7-(($F$7-$K$7)/4) -> 0.059647348 | H7: =G7-(($F$7-$K$7)/4) -> 0.053098232 | I7: =H7-(($F$7-$K$7)/4) -> 0.046549116 | J7: =I7-(($F$7-$K$7)/4) -> 0.04 | K7: =D18 -> 0.04
B8: EBIT | F8: ='Data Sheet'!K33 -> 41988.01 | G8: =F8*(1+G7) -> 44492.483 | H8: =G8*(1+H7) -> 46854.956 | I8: =H8*(1+I7) -> 49036.012 | J8: =I8*(1+J7) -> 50997.453 | K8: =J8*(1+K7) -> 53037.351
B9: Tax Rate | F9: 0.3 | G9: =F9 -> 0.3 | H9: =G9 -> 0.3 | I9: =H9 -> 0.3 | J9: =I9 -> 0.3 | K9: =J9 -> 0.3
B10: EBIT(1-T) | F10: =F8*(1-F9) -> 29391.607 | G10: =G8*(1-G9) -> 31144.738 | H10: =H8*(1-H9) -> 32798.469 | I10: =I8*(1-I9) -> 34325.209 | J10: =J8*(1-J9) -> 35698.217 | K10: =K8*(1-K9) -> 37126.146
B11: Less: Reinvestment Rate | F11: ='Intrinsic Growth'!C57 -> 0.094610031 | G11: =F11+(($K$11-$F$11)/4) -> 0.15095752 | H11: =G11+(($K$11-$F$11)/4) -> 0.20730502 | I11: =H11+(($K$11-$F$11)/4) -> 0.26365251 | J11: =I11+(($K$11-$F$11)/4) -> 0.32 | K11: 0.32
B12: Free Cash Flow to Firm (FCFF) | F12: =F10*(1-F11) -> 26610.866 | G12: =G10*(1-G11) -> 26443.206 | H12: =H10*(1-H11) -> 25999.182 | I12: =I10*(1-I11) -> 25275.281 | J12: =J10*(1-J11) -> 24274.788 | K12: =K10*(1-K11) -> 25245.779
B13: Mid Year Convention | G13: 0.5 | H13: =+G13+1 -> 1.5 | I13: =+H13+1 -> 2.5 | J13: =+I13+1 -> 3.5 | K13: =+J13+1 -> 4.5
B14: Discounting Factor | G14: =1/(1+$D$21)^G13 -> 0.94110834 | H14: =1/(1+$D$21)^H13 -> 0.83352545 | I14: =1/(1+$D$21)^I13 -> 0.73824091 | J14: =1/(1+$D$21)^J13 -> 0.65384883 | K14: =1/(1+$D$21)^K13 -> 0.57910403
B16: PV of FCFF | G16: =G12*G14 -> 24885.921 | H16: =H12*H14 -> 21670.98 | I16: =I12*I14 -> 18659.247 | J16: =J12*J14 -> 15872.041 | K16: =K12*K14 -> 14619.933
B18: Expected Sector EBIT Growth | D18: 0.04
B19: Intrinsic Growth | D19: ='Intrinsic Growth'!C66 -> 0.066196463 | G19: Sanity Check for Terminal Growth Rate > Sector Growth Rate
B20: Terminal Growth Rate (GDP) | D20: 0.065 | G20: =IF(D19>D20,"Pass","Recheck") -> Pass
B21: WACC | D21: =WACC!J40 -> 0.12906971
A23: # | B23: Calculation of Terminal Value of FCFF | G23: Sensitivity Analysis - Share Price
G24: =D43 -> 268.92545 | H24: 0.1 | I24: =D21 -> 0.12906971 | J24: 0.14 | K24: 0.16 | L24: WACC
B25: FCFF (n+1) | D25: =K12*(1+D18) -> 26255.61 | G25: 0.04 | H25: 281.7801 | I25: 215.73205 | J25: 200.8315 | K25: 180.59436
B26: WACC | D26: =D21 -> 0.12906971 | G26: 0.065 | H26: 426.33116 | I26: 268.92545 | J26: 241.3058 | K26: 207.22218
B27: Terminal Growth Rate | D27: =D20 -> 0.065 | G27: 0.07 | H27: 484.15158 | I27: 284.96724 | J27: 252.86989 | K27: 214.32294
G28: 0.075 | H28: 565.10018 | I28: 303.97591 | J28: 266.21306 | K28: 222.25907
B29: Terminal Value | D29: =D25/(D26-D27) -> 409797.53 | G29: 0.08 | H29: 686.52307 | I29: 326.85838 | J29: 281.7801 | K29: 231.18723
G30: Growth Rate
A32: # | B32: Calculation of Equity Value per Share
B34: PV of FCFF | D34: =SUM(G16:K16) -> 95708.122
B35: PV of Terminal Value | D35: =D29*K14 -> 237315.4
B36: Value of Operating Assets | D36: =SUM(D34:D35) -> 333023.53
B37: (Also the Enterprise Value)
B38: Add: Cash | D38: ='Data Sheet'!K69 -> 4012.36
B39: Less: Debt | D39: =SUM('RAW FSn'!N8:N10) -> 284
B40: Value of Equity | D40: =D36+D38-D39 -> 336751.89
B41: No of Shares | D41: ='Data Sheet'!B6 -> 1252.2128
B43: Equity Value per Share | D43: =D40/D41 -> 268.92545
B45: Share price | D45: 407
B46: Discount/Premium | D46: =D45/D43 -> 1.5134306
B47: Valuation | D47: =IF(D46>1,"Overvalued","Undervalued") -> Overvalued

Sheet Football Field
B2: Football Field Analysis
B3: ='Data Sheet'!B1 -> ITC LTD
B4: Data is from Comparables Valuation of ITC and BBB Scenario Analysis Tab
J6: Football Field Analysis - Data
L7: OpenLow | M7: Low | N7: OpenHigh | O7: High
J8: Comps | L8: 365.6 | M8: =L8 -> 365.6 | N8: 534.3 | O8: =N8 -> 534.3
J9: DCF Bear | L9: =DCF!K25 -> 180.59436 | M9: =L9 -> 180.59436 | N9: =DCF!H25 -> 281.7801 | O9: =N9 -> 281.7801
J10: DCF Base | L10: =DCF!K26 -> 207.22218 | M10: =L10 -> 207.22218 | N10: =DCF!H26 -> 426.33116 | O10: =N10 -> 426.33116
J11: DCF Bull | L11: =DCF!K29 -> 231.18723 | M11: =L11 -> 231.18723 | N11: =DCF!H29 -> 686.52307 | O11: =N11 -> 686.52307
J12: 52W H/L | L12: 390 | M12: =L12 -> 390 | N12: 495 | O12: =N12 -> 495
C21: Current Market Price

Sheet Data

Sheet Data Sheet
A1: COMPANY NAME | B1: ITC LTD | E1: =IF(B2<>B3, "A NEW VERSION OF THE WORKSHEET IS AVAILABLE", "")
A2: LATEST VERSION | B2: 2.1 | E2: PLEASE DO NOT MAKE ANY CHANGES TO THIS SHEET
A3: CURRENT VERSION | B3: 2.1
A5: META
A6: Number of shares | B6: =IF(B9>0, B9/B8, 0) -> 1252.2128
A7: Face Value | B7: 1
A8: Current Price | B8: 415
A9: Market Capitalization | B9: 519668.31
A15: PROFIT & LOSS
A16: Report Date | B16: 42460 | C16: 42825 | D16: 43190 | E16: 43555 | F16: 43921 | G16: 44286 | H16: 44651 | I16: 45016 | J16: 45382 | K16: 45747
A17: Sales | B17: 39192.1 | C17: 42767.6 | D17: 43448.94 | E17: 48339.58 | F17: 49387.7 | G17: 49257.45 | H17: 60644.54 | I17: 70919.03 | J17: 67931.94 | K17: 75323.34
A18: Raw Material Cost | B18: 13763.88 | C18: 15456.59 | D18: 14827.72 | E18: 17623.52 | F18: 18048.6 | G18: 20776.71 | H18: 27071.07 | I18: 29364.36 | J18: 27348.57 | K18: 32704.37
A19: Change in Inventory | B19: 195.38 | C19: -592.57 | D19: -1027.76 | E19: 203.19 | F19: 703.13 | G19: 645.27 | H19: 686 | I19: 358.59 | J19: 367.77 | K19: 725.65
A20: Power and Fuel | B20: 571.88 | C20: 584.33 | D20: 653.5 | E20: 746.73 | F20: 780.85 | G20: 699.56 | H20: 889.77 | I20: 1232.34 | J20: 952.9 | K20: 975.35
A21: Other Mfr. Exp | B21: 1581.59 | C21: 1683.9 | D21: 1697.62 | E21: 1871.01 | F21: 1908.29 | G21: 1587.18 | H21: 1887.67 | I21: 2327.8 | J21: 2183.76 | K21: 2345.36
A22: Employee Cost | B22: 3440.97 | C22: 3631.73 | D22: 3760.9 | E22: 4177.88 | F22: 4295.79 | G22: 4463.33 | H22: 4890.55 | I22: 5736.22 | J22: 5548.53 | K22: 6169.78
A23: Selling and admin | B23: 4261.78 | C23: 4179.74 | D23: 3954.87 | E23: 4546.39 | F23: 4488.63 | G23: 4236.77 | H23: 4858.38 | I23: 5604.08 | J23: 5312.45 | K23: 5793.29
A24: Other Expenses | B24: 1235.89 | C24: 1169.23 | D24: 1005.98 | E24: 1039.85 | F24: 1225.13 | G24: 1074.39 | H24: 1109.95 | I24: 1308.56 | J24: 1765.97 | K24: 2221.39
A25: Other Income | B25: 1483.11 | C25: 1758.63 | D25: 2239.81 | E25: 2080.44 | F25: 2417.32 | G25: 2576.95 | H25: 1909.72 | I25: 2097.64 | J25: 3330.45 | K25: 17794.88
A26: Depreciation | B26: 1077.4 | C26: 1152.79 | D26: 1236.28 | E26: 1396.61 | F26: 1644.91 | G26: 1645.59 | H26: 1732.41 | I26: 1809.01 | J26: 1518.05 | K26: 1646.32
A27: Interest | B27: 78.13 | C27: 49.03 | D27: 115.01 | E27: 71.4 | F27: 81.38 | G27: 57.97 | H27: 59.99 | I27: 77.77 | J27: 39.11 | K27: 45.06
... A31: Dividend Amount | B31: 6840.12 | C31: 5770.02 | D31: 6285.21 | E31: 7048.7 | F31: 12476.58 | G31: 13231.96 | H31: 14171.8 | I31: 19263.4 | J31: 17166.46 | K31: 17957.73
A33: EBIT | B33: =B28+B27 -> 14937.2 | C33: =C28+C27 -> 16075.35 | D33: =D28+D27 -> 17524.12 | E33: =E28+E27 -> 19221.22 | F33: =F28+F27 -> 20115.95 | G33: =G28+G27 -> 17996.14 | H33: =H28+H27 -> 20800.46 | I33: =I28+I27 -> 25992.89 | ... K33: =K28+K27 -> 41988.01
A34: EBITDA | B34: =B33+B26 -> 16014.6 | C34: =C33+C26 -> 17228.14 | D34: =D33+D26 -> 18760.4 | E34: =E33+E26 -> 20617.83 | F34: =F33+F26 -> 21760.86 | G34: =G33+G26 -> 19641.73 | H34: =H33+H26 -> 22532.87 | I34: =I33+I26 -> 27801.9 | ... K34: =K33+K26 -> 43634.33
A40: Quarters
A41: Report Date | B41: 45016 | C41: 45107 | D41: 45199 | E41: 45291 | F41: 45382 | G41: 45473 | H41: 45565 | I41: 45657 | J41: 45747 | K41: 45838
A42: Sales | B42: 17634.89 | C42: 17164.46 | D42: 17774.47 | E42: 17195.24 | F42: 17037.8 | G42: 17777.81 | H42: 19990.36 | I42: 18790.17 | J42: 18765 | K42: 21494.79
A43: Expenses | B43: 11010.89 | C43: 10494.39 | D43: 11320.23 | E43: 10985.01 | F43: 10735.73 | G43: 11232.97 | H43: 13438.28 | I43: 12428.27 | J43: 12245.61 | K43: 14678.32
A44: Other Income | B44: 682.52 | C44: 722.3 | D44: 673.5 | E44: 820.26 | F44: 868 | G44: 771.13 | H44: 690.31 | I44: 803.4 | J44: 15391.28 | K44: 750.97
A45: Depreciation | B45: 461.4 | C45: 442.46 | D45: 453.04 | E45: 384.04 | F45: 385.09 | G45: 403.13 | H45: 416.18 | I45: 415.98 | J45: 411.03 | K45: 422.96
A46: Interest | B46: 12.15 | C46: 9.9 | D46: 9.87 | E46: 11.94 | F46: 10.72 | G46: 9.6 | H46: 14.73 | I46: 9.82 | J46: 10.91 | K46: 16.47
A47: Profit before tax | B47: 6832.97 | C47: 6940.01 | D47: 6664.83 | E47: 6634.51 | F47: 6774.26 | G47: 6903.24 | H47: 6811.48 | I47: 6739.5 | J47: 21488.73 | K47: 7128.01
A48: Tax | B48: 1607.95 | C48: 1759.89 | D48: 1700.31 | E48: 1227.99 | F48: 1583.55 | G48: 1726.25 | H48: 1757.05 | I48: 1726.32 | J48: 1680.85 | K48: 1784.6
A49: Net profit | B49: 5175.48 | C49: 5104.93 | D49: 4898.07 | E49: 5335.23 | F49: 5120.55 | G49: 5091.59 | H49: 4992.87 | I49: 4934.8 | J49: 19727.37 | K49: 5244.2
A50: Operating Profit | B50: 6624 | C50: 6670.07 | D50: 6454.24 | E50: 6210.23 | F50: 6302.07 | G50: 6544.84 | H50: 6552.08 | I50: 6361.9 | J50: 6519.39 | K50: 6816.47
A51: EBITDA | B51: =B49+B48+B46+B45 -> 7256.98 | C51: =C49+C48+C46+C45 -> 7317.18 | D51: =D49+D48+D46+D45 -> 7061.29 | E51: =E49+E48+E46+E45 -> 6959.2 | F51: =F49+F48+F46+F45 -> 7099.91 | G51: =G49+G48+G46+G45 -> 7230.57 | H51: =H49+H48+H46+H45 -> 7180.83 | I51: =I49+I48+I46+I45 -> 7086.92 | ... K51: =K49+K48+K46+K45 -> 7468.23
A55: BALANCE SHEET
A56: Report Date | B56: 42460 | C56: 42825 | D56: 43190 | E56: 43555 | F56: 43921 | G56: 44286 | H56: 44651 | I56: 45016 | J56: 45382 | K56: 45747
A57: Equity Share Capital | B57: 804.72 | C57: 1214.74 | D57: 1220.43 | E57: 1225.86 | F57: 1229.22 | G57: 1230.88 | H57: 1232.33 | I57: 1242.8 | J57: 1248.47 | K57: 1251.41
A58: Reserves | B58: 41874.8 | C58: 45198.19 | D58: 51289.68 | E58: 57915.01 | F58: 64044.04 | G58: 59116.46 | H58: 61223.24 | I58: 67912.46 | J58: 73258.53 | K58: 68778.64
A59: Borrowings | B59: 83.78 | C59: 45.72 | D59: 35.92 | E59: 13.44 | F59: 277.45 | G59: 270.83 | H59: 249.44 | I59: 306.04 | J59: 303.43 | K59: 284.54
A60: Other Liabilities | B60: 8888.04 | C60: 9439.67 | D60: 11694.85 | E60: 12584.73 | F60: 11760.04 | G60: 13142.59 | H60: 14491.01 | I60: 16369.66 | J60: 16943.54 | K60: 17688.11
A61: Total | B61: 51651.34 | C61: 55898.32 | D61: 64240.88 | E61: 71739.04 | F61: 77310.75 | G61: 73760.76 | H61: 77196.02 | I61: 85830.96 | J61: 91753.97 | K61: 88002.7
A62: Net Block | B62: 15106.63 | C62: 15893.48 | D62: 16523.96 | E62: 19374.19 | F62: 21713.34 | G62: 23298.48 | H62: 24231.59 | I62: 25851.27 | J62: 27820.22 | K62: 21954.85
A63: Capital Work in Progress | B63: 2559.72 | C63: 3729.89 | D63: 5508.33 | E63: 4136.42 | F63: 3256.46 | G63: 4011.29 | H63: 3225.54 | I63: 3003.3 | J63: 2860.78 | K63: 1090.91
A64: Investments | B64: 11747.59 | C64: 17581.38 | D64: 22052.86 | E64: 25043.49 | F64: 28663.35 | G64: 24870.87 | H64: 24841.01 | I64: 29415.02 | J64: 31114.02 | K64: 34719.82
A65: Other Assets | B65: 22237.4 | C65: 18693.57 | D65: 20155.73 | E65: 23184.94 | F65: 23677.6 | G65: 21580.12 | H65: 24897.88 | I65: 27561.37 | J65: 29958.95 | K65: 30237.12
A66: Total | B66: 51651.34 | C66: 55898.32 | D66: 64240.88 | E66: 71739.04 | F66: 77310.75 | G66: 73760.76 | H66: 77196.02 | I66: 85830.96 | J66: 91753.97 | K66: 88002.7
A67: Receivables | B67: 1917.18 | C67: 2474.29 | D67: 2682.29 | E67: 4035.28 | F67: 2562.48 | G67: 2501.7 | H67: 2461.9 | I67: 2956.17 | J67: 4025.82 | K67: 4719.67
... A70: No. of Equity Shares | B70: 8047206991 | C70: 12147383071 | D70: 12204294911 | E70: 12258631601 | F70: 12292231241 | G70: 12308844231 | H70: 12323255931 | I70: 12428017741 | J70: 12484700000 | K70: 12514119781
A71: New Bonus Shares | C71: 4026657100
A72: Face value | B72: 1 | C72: 1 | D72: 1 | E72: 1 | F72: 1 | G72: 1 | H72: 1 | I72: 1 | J72: 1 | K72: 1
A74: Other Assets | B74: =B65-SUM(B67:B69) -> 5194.82 | C74: =C65-SUM(C67:C69) -> 5135.78 | D74: =D65-SUM(D67:D69) -> 7078.75 | E74: =E65-SUM(E67:E69) -> 7138.07 | F74: =F65-SUM(F67:F69) -> 4958.45 | G74: =G65-SUM(G67:G69) -> 4022.24 | H74: =H65-SUM(H67:H69) -> 6917.41 | I74: =I65-SUM(I67:I69) -> 7953.85 | ... K74: =K65-SUM(K67:K69) -> 5867.53
A76: Total Assets | B76: =B61 -> 51651.34 | C76: =C61 -> 55898.32 | D76: =D61 -> 64240.88 | E76: =E61 -> 71739.04 | F76: =F61 -> 77310.75 | G76: =G61 -> 73760.76 | H76: =H61 -> 77196.02 | I76: =I61 -> 85830.96 | ... K76: =K61 -> 88002.7
A80: CASH FLOW:
A81: Report Date | B81: 42460 | C81: 42825 | D81: 43190 | E81: 43555 | F81: 43921 | G81: 44286 | H81: 44651 | I81: 45016 | J81: 45382 | K81: 45747
A82: Cash from Operating Activity | B82: 9799.04 | C82: 10627.31 | D82: 13169.4 | E82: 12583.41 | F82: 14689.66 | G82: 12526.97 | H82: 15775.51 | I82: 18877.55 | J82: 17178.86 | K82: 17627.04
A83: Cash from Investing Activity | B83: -3920.73 | C83: -3250.93 | D83: -7113.89 | E83: -5545.68 | F83: -6174.02 | G83: 5739.98 | H83: -2238.49 | I83: -5732.29 | J83: 1562.77 | K83: -563.84
A84: Cash from Financing Activity | B84: -5612.52 | C84: -7301.03 | D84: -6221.13 | E84: -6868.64 | F84: -8181.48 | G84: -18633.83 | H84: -13580.5 | I84: -13006.03 | J84: -18550.96 | K84: -17037.4
A85: Net Cash Flow | B85: 265.79 | C85: 75.35 | D85: -165.62 | E85: 169.09 | F85: 334.16 | G85: -366.88 | H85: -43.48 | I85: 139.23 | J85: 190.67 | K85: 25.8
A90: PRICE: | B90: 205.13 | C90: 262.75 | D90: 239.5 | E90: 278.64 | F90: 160.95 | G90: 204.82 | H90: 234.96 | I90: 359.49 | J90: 401.53 | K90: 409.75
A92: DERIVED:
A93: Adjusted Equity Shares in Cr | B93: 1207.08 | C93: 1214.74 | D93: 1220.43 | E93: 1225.86 | F93: 1229.22 | G93: 1230.88 | H93: 1232.33 | I93: 1242.8 | J93: 1248.47 | K93: 1251.41

Sheet WACC Data
B3: S.No. | C3: Name | D3: Debt Rs.Cr. | E3: Mar Cap Rs.Cr.
B4: 1 | C4: ITC | D4: 285 | E4: 519668
B5: 2 | C5: Godfrey Phillips | D5: 179 | E5: 45635
B6: 3 | C6: VST Industries | D6: 0 | E6: 4791
B7: 4 | C7: NTC Industries | D7: 77.1 | E7: 249
B8: 5 | C8: Indian Wood Prod | D8: 79.9 | E8: 253
B9: 6 | C9: Elitecon Inter. | D9: 2.51 | E9: 32537
B10: 7 | C10: Sinnar Bidi Udy. | D10: 0 | E10: 39.9

Sheet RAW FS
B2: Balance Sheet
B4: ='RAW FS ITC'!Q4 -> 0 | C4: ='RAW FS ITC'!R4 -> 41699 | D4: ='RAW FS ITC'!S4 -> 42064 | E4: ='RAW FS ITC'!T4 -> 42430 | F4: ='RAW FS ITC'!U4 -> 42795 | G4: ='RAW FS ITC'!V4 -> 43160 | H4: ='RAW FS ITC'!W4 -> 43525 | I4: ='RAW FS ITC'!X4 -> 43891 | ... N4: ='RAW FS ITC'!AC4 -> 45717
B5: ='RAW FS ITC'!Q5 -> Equity Capital | C5: ='RAW FS ITC'!R5 -> 795 | D5: ='RAW FS ITC'!S5 -> 802 | E5: ='RAW FS ITC'!T5 -> 805 | F5: ='RAW FS ITC'!U5 -> 1215 | G5: ='RAW FS ITC'!V5 -> 1220 | H5: ='RAW FS ITC'!W5 -> 1226 | I5: ='RAW FS ITC'!X5 -> 1229 | ... N5: ='RAW FS ITC'!AC5 -> 1251
B6: ='RAW FS ITC'!Q6 -> Reserves | C6: ='RAW FS ITC'!R6 -> 26442 | D6: ='RAW FS ITC'!S6 -> 30934 | E6: ='RAW FS ITC'!T6 -> 41875 | F6: ='RAW FS ITC'!U6 -> 45198 | G6: ='RAW FS ITC'!V6 -> 51290 | H6: ='RAW FS ITC'!W6 -> 57915 | I6: ='RAW FS ITC'!X6 -> 64044 | ... N6: ='RAW FS ITC'!AC6 -> 68779
B7: ='RAW FS ITC'!Q7 -> Borrowings
B8: ='RAW FS ITC'!Q8 -> Long term Borrowings | C8: ='RAW FS ITC'!R8 -> 76 | D8: ='RAW FS ITC'!S8 -> 61 | E8: ='RAW FS ITC'!T8 -> 27 | F8: ='RAW FS ITC'!U8 -> 18 | G8: ='RAW FS ITC'!V8 -> 12 | H8: ='RAW FS ITC'!W8 -> 8 | I8: ='RAW FS ITC'!X8 -> 6 | ... N8: ='RAW FS ITC'!AC8 -> 0
B9: ='RAW FS ITC'!Q9 -> Short term Borrowings | C9: ='RAW FS ITC'!R9 -> 150 | D9: ='RAW FS ITC'!S9 -> 195 | E9: ='RAW FS ITC'!T9 -> 44 | F9: ='RAW FS ITC'!U9 -> 19 | G9: ='RAW FS ITC'!V9 -> 17 | H9: ='RAW FS ITC'!W9 -> 2 | I9: ='RAW FS ITC'!X9 -> 1 | ... N9: ='RAW FS ITC'!AC9 -> 91
B10: ='RAW FS ITC'!Q10 -> Lease Liabilities | C10: ='RAW FS ITC'!R10 -> 0 | D10: ='RAW FS ITC'!S10 -> 0 | E10: ='RAW FS ITC'!T10 -> 0 | F10: ='RAW FS ITC'!U10 -> 0 | G10: ='RAW FS ITC'!V10 -> 0 | H10: ='RAW FS ITC'!W10 -> 0 | I10: ='RAW FS ITC'!X10 -> 268 | ... N10: ='RAW FS ITC'!AC10 -> 193
B11: ='RAW FS ITC'!Q11 -> Other Borrowings | C11: ='RAW FS ITC'!R11 -> 16 | D11: ='RAW FS ITC'!S11 -> 13 | E11: ='RAW FS ITC'!T11 -> 13 | F11: ='RAW FS ITC'!U11 -> 8 | G11: ='RAW FS ITC'!V11 -> 7 | H11: ='RAW FS ITC'!W11 -> 3 | I11: ='RAW FS ITC'!X11 -> 2 | ... N11: ='RAW FS ITC'!AC11 -> 0
B12: ='RAW FS ITC'!Q12 -> Other Liabilities | C12: ='RAW FS ITC'!R12 -> 0 | D12: ='RAW FS ITC'!S12 -> 0 | E12: ='RAW FS ITC'!T12 -> 0 | F12: ='RAW FS ITC'!U12 -> 0 | G12: ='RAW FS ITC'!V12 -> 0 | H12: ='RAW FS ITC'!W12 -> 0 | I12: ='RAW FS ITC'!X12 -> 0 | ... N12: ='RAW FS ITC'!AC12 -> 0
B13: ='RAW FS ITC'!Q13 -> Non controlling int | C13: ='RAW FS ITC'!R13 -> 203 | D13: ='RAW FS ITC'!S13 -> 225 | E13: ='RAW FS ITC'!T13 -> 261 | F13: ='RAW FS ITC'!U13 -> 295 | G13: ='RAW FS ITC'!V13 -> 334 | H13: ='RAW FS ITC'!W13 -> 343 | I13: ='RAW FS ITC'!X13 -> 377 | ... N13: ='RAW FS ITC'!AC13 -> 368
B14: ='RAW FS ITC'!Q14 -> Trade Payables | C14: ='RAW FS ITC'!R14 -> 2106 | D14: ='RAW FS ITC'!S14 -> 2020 | E14: ='RAW FS ITC'!T14 -> 2339 | F14: ='RAW FS ITC'!U14 -> 2659 | G14: ='RAW FS ITC'!V14 -> 3496 | H14: ='RAW FS ITC'!W14 -> 3510 | I14: ='RAW FS ITC'!X14 -> 3630 | ... N14: ='RAW FS ITC'!AC14 -> 4807
B15: ='RAW FS ITC'!Q15 -> Advance from Customers | C15: ='RAW FS ITC'!R15 -> 0 | D15: ='RAW FS ITC'!S15 -> 0 | E15: ='RAW FS ITC'!T15 -> 805 | F15: ='RAW FS ITC'!U15 -> 495 | G15: ='RAW FS ITC'!V15 -> 461 | H15: ='RAW FS ITC'!W15 -> 430 | I15: ='RAW FS ITC'!X15 -> 703 | ... N15: ='RAW FS ITC'!AC15 -> 1264
B16: ='RAW FS ITC'!Q16 -> Other liability items | C16: ='RAW FS ITC'!R16 -> 11060 | D16: ='RAW FS ITC'!S16 -> 11702 | E16: ='RAW FS ITC'!T16 -> 5483 | F16: ='RAW FS ITC'!U16 -> 5991 | G16: ='RAW FS ITC'!V16 -> 7404 | H16: ='RAW FS ITC'!W16 -> 8301 | I16: ='RAW FS ITC'!X16 -> 7050 | ... N16: ='RAW FS ITC'!AC16 -> 11249
B17: ='RAW FS ITC'!Q17 -> Total Liabilities | C17: ='RAW FS ITC'!R17 -> 40848 | D17: ='RAW FS ITC'!S17 -> 45952 | E17: ='RAW FS ITC'!T17 -> 51651 | F17: ='RAW FS ITC'!U17 -> 55898 | G17: ='RAW FS ITC'!V17 -> 64241 | H17: ='RAW FS ITC'!W17 -> 71739 | I17: ='RAW FS ITC'!X17 -> 77311 | ... N17: ='RAW FS ITC'!AC17 -> 88003
B19: ='RAW FS ITC'!Q19 -> Fixed Assets | C19: ='RAW FS ITC'!R19 -> 12921 | D19: ='RAW FS ITC'!S19 -> 15303 | E19: ='RAW FS ITC'!T19 -> 15107 | F19: ='RAW FS ITC'!U19 -> 15893 | G19: ='RAW FS ITC'!V19 -> 16524 | H19: ='RAW FS ITC'!W19 -> 19374 | I19: ='RAW FS ITC'!X19 -> 21713 | ... N19: ='RAW FS ITC'!AC19 -> 21955
B20: ='RAW FS ITC'!Q20 -> Land | C20: ='RAW FS ITC'!R20 -> 1564 | D20: ='RAW FS ITC'!S20 -> 1717 | E20: ='RAW FS ITC'!T20 -> 1615 | F20: ='RAW FS ITC'!U20 -> 1673 | G20: ='RAW FS ITC'!V20 -> 1685 | H20: ='RAW FS ITC'!W20 -> 2021 | I20: ='RAW FS ITC'!X20 -> 2797 | ... N20: ='RAW FS ITC'!AC20 -> 1588
... B41: ='RAW FS ITC'!Q41 -> Total Assets | C41: ='RAW FS ITC'!R41 -> 40848 | D41: ='RAW FS ITC'!S41 -> 45952 | E41: ='RAW FS ITC'!T41 -> 51651 | F41: ='RAW FS ITC'!U41 -> 55898 | G41: ='RAW FS ITC'!V41 -> 64241 | H41: ='RAW FS ITC'!W41 -> 71739 | I41: ='RAW FS ITC'!X41 -> 77311 | ... N41: ='RAW FS ITC'!AC41 -> 88003
B43: Cash Flow Statement
B45: ='RAW FS ITC'!Q45 -> Cash from Operating Activity | C45: ='RAW FS ITC'!R45 -> 7344 | D45: ='RAW FS ITC'!S45 -> 9843 | E45: ='RAW FS ITC'!T45 -> 9799 | F45: ='RAW FS ITC'!U45 -> 10627 | G45: ='RAW FS ITC'!V45 -> 13169 | H45: ='RAW FS ITC'!W45 -> 12583 | I45: ='RAW FS ITC'!X45 -> 14690 | ... N45: ='RAW FS ITC'!AC45 -> 17627
B46: ='RAW FS ITC'!Q46 -> Profit from operations | C46: ='RAW FS ITC'!R46 -> 13172 | D46: ='RAW FS ITC'!S46 -> 14261 | E46: ='RAW FS ITC'!T46 -> 15154 | F46: ='RAW FS ITC'!U46 -> 16075 | G46: ='RAW FS ITC'!V46 -> 17433 | H46: ='RAW FS ITC'!W46 -> 18862 | I46: ='RAW FS ITC'!X46 -> 19416 | ... N46: ='RAW FS ITC'!AC46 -> 26719
B47: ='RAW FS ITC'!Q47 -> Receivables | C47: ='RAW FS ITC'!R47 -> -1546 | D47: ='RAW FS ITC'!S47 -> 558 | E47: ='RAW FS ITC'!T47 -> -207 | F47: ='RAW FS ITC'!U47 -> -870 | G47: ='RAW FS ITC'!V47 -> -964 | H47: ='RAW FS ITC'!W47 -> -755 | I47: ='RAW FS ITC'!X47 -> 1411 | ... N47: ='RAW FS ITC'!AC47 -> -1023
B48: ='RAW FS ITC'!Q48 -> Inventory | C48: ='RAW FS ITC'!R48 -> -755 | D48: ='RAW FS ITC'!S48 -> -505 | E48: ='RAW FS ITC'!T48 -> -693 | F48: ='RAW FS ITC'!U48 -> 593 | G48: ='RAW FS ITC'!V48 -> 602 | H48: ='RAW FS ITC'!W48 -> -359 | I48: ='RAW FS ITC'!X48 -> -508 | ... N48: ='RAW FS ITC'!AC48 -> -2975
B49: ='RAW FS ITC'!Q49 -> Payables | C49: ='RAW FS ITC'!R49 -> 456 | D49: ='RAW FS ITC'!S49 -> -23 | E49: ='RAW FS ITC'!T49 -> 622 | F49: ='RAW FS ITC'!U49 -> 321 | G49: ='RAW FS ITC'!V49 -> 2098 | H49: ='RAW FS ITC'!W49 -> 639 | I49: ='RAW FS ITC'!X49 -> -607 | ... N49: ='RAW FS ITC'!AC49 -> 1256
B50: ='RAW FS ITC'!Q50 -> Loans Advances | C50: ='RAW FS ITC'!R50 -> 0 | D50: ='RAW FS ITC'!S50 -> 0 | E50: ='RAW FS ITC'!T50 -> 0 | F50: ='RAW FS ITC'!U50 -> 0 | G50: ='RAW FS ITC'!V50 -> 0 | H50: ='RAW FS ITC'!W50 -> 0 | I50: ='RAW FS ITC'!X50 -> 0 | ... N50: ='RAW FS ITC'!AC50 -> 0
B51: ='RAW FS ITC'!Q51 -> Other WC items | C51: ='RAW FS ITC'!R51 -> 0 | D51: ='RAW FS ITC'!S51 -> 0 | E51: ='RAW FS ITC'!T51 -> 0 | F51: ='RAW FS ITC'!U51 -> 0 | G51: ='RAW FS ITC'!V51 -> 0 | H51: ='RAW FS ITC'!W51 -> 0 | I51: ='RAW FS ITC'!X51 -> 0 | ... N51: ='RAW FS ITC'!AC51 -> 0
B52: ='RAW FS ITC'!Q52 -> Working capital changes | C52: ='RAW FS ITC'!R52 -> -1844 | D52: ='RAW FS ITC'!S52 -> 31 | E52: ='RAW FS ITC'!T52 -> -277 | F52: ='RAW FS ITC'!U52 -> 44 | G52: ='RAW FS ITC'!V52 -> 1736 | H52: ='RAW FS ITC'!W52 -> -476 | I52: ='RAW FS ITC'!X52 -> 296 | ... N52: ='RAW FS ITC'!AC52 -> -2742
B53: ='RAW FS ITC'!Q53 -> Direct taxes | C53: ='RAW FS ITC'!R53 -> -3984 | D53: ='RAW FS ITC'!S53 -> -4449 | E53: ='RAW FS ITC'!T53 -> -5078 | F53: ='RAW FS ITC'!U53 -> -5492 | G53: ='RAW FS ITC'!V53 -> -6000 | H53: ='RAW FS ITC'!W53 -> -5803 | I53: ='RAW FS ITC'!X53 -> -5023 | ... N53: ='RAW FS ITC'!AC53 -> -6350
B54: ='RAW FS ITC'!Q54 -> Exceptional CF items | C54: ='RAW FS ITC'!R54 -> 0 | D54: ='RAW FS ITC'!S54 -> 0 | E54: ='RAW FS ITC'!T54 -> 0 | F54: ='RAW FS ITC'!U54 -> 0 | G54: ='RAW FS ITC'!V54 -> 0 | H54: ='RAW FS ITC'!W54 -> 0 | I54: ='RAW FS ITC'!X54 -> 0 | ... N54: ='RAW FS ITC'!AC54 -> 0
B56: ='RAW FS ITC'!Q56 -> Cash from Investing Activity | C56: ='RAW FS ITC'!R56 -> -3254 | D56: ='RAW FS ITC'!S56 -> -5275 | E56: ='RAW FS ITC'!T56 -> -3921 | F56: ='RAW FS ITC'!U56 -> -3251 | G56: ='RAW FS ITC'!V56 -> -7114 | H56: ='RAW FS ITC'!W56 -> -5546 | I56: ='RAW FS ITC'!X56 -> -6174 | ... N56: ='RAW FS ITC'!AC56 -> -564
B57: ='RAW FS ITC'!Q57 -> Fixed assets purchased | C57: ='RAW FS ITC'!R57 -> -2887 | D57: ='RAW FS ITC'!S57 -> -3300 | E57: ='RAW FS ITC'!T57 -> -2348 | F57: ='RAW FS ITC'!U57 -> -3122 | G57: ='RAW FS ITC'!V57 -> -2878 | H57: ='RAW FS ITC'!W57 -> -3169 | I57: ='RAW FS ITC'!X57 -> -2441 | ... N57: ='RAW FS ITC'!AC57 -> -2279
... B79: ='RAW FS ITC'!Q79 -> Net Cash Flow | C79: ='RAW FS ITC'!R79 -> -32 | D79: ='RAW FS ITC'!S79 -> -93 | E79: ='RAW FS ITC'!T79 -> 266 | F79: ='RAW FS ITC'!U79 -> 75 | G79: ='RAW FS ITC'!V79 -> -166 | H79: ='RAW FS ITC'!W79 -> 169 | I79: ='RAW FS ITC'!X79 -> 334 | ... N79: ='RAW FS ITC'!AC79 -> 26

Sheet Rm
B2: Year | C2: Annual
B3: 2000 | C3: -0.1465 | E3: Average Return | F3: =AVERAGE(C3:C27) -> 0.153348
B4: 2001 | C4: -0.1618 | E4: Dividend Yield | F4: 0.013
B5: 2002 | C5: 0.0325 | E5: Total Market Returns | F5: =SUM(F3:F4) -> 0.166348
B6: 2003 | C6: 0.719
B7: 2004 | C7: 0.1068
B8: 2005 | C8: 0.3634
B9: 2006 | C9: 0.3983
B10: 2007 | C10: 0.5477
B11: 2008 | C11: -0.5179
B12: 2009 | C12: 0.7576
B13: 2010 | C13: 0.1795
B14: 2011 | C14: -0.2462
B15: 2012 | C15: 0.277
B16: 2013 | C16: 0.0676
B17: 2014 | C17: 0.3139
... B27: 2024 | C27: 0.0875

Sheet Sector Data
B3: India - Sector Data
B4: Figures in $mn
B5: Industry Name | C5: Number of Firms | D5: Capital Expenditures | E5: Depreciation & Amort | F5: CapEx/Deprecn | G5: Acquisitions | H5: Net R&D | I5: Net Cap Ex/Sales | J5: Net Cap Ex/ EBIT (1-t) | K5: Sales/ Invested Capital | L5: Reinvestment Rate | M5: Expected EBIT Growth
B6: Advertising | C6: 13 | D6: 12.255 | E6: 6.172 | F6: 1.98558 | G6: 15.7 | H6: 1.95 | I6: 0.11509867 | J6: 0.92871968 | K6: 4.3520758 | L6: =1/K6 -> 0.22977541 | M6: =VLOOKUP(B6,'[3]Industry Averages'!$A$9:$E$104,5,0) -> 0.58596196
B7: Aerospace/Defense | C7: 13 | D7: 179.856 | E7: 230.043 | F7: 0.78183644 | G7: 0 | H7: 130.9138 | I7: 0.011286263 | J7: 0.085900571 | K7: 2.3987362 | L7: =1/K7 -> 0.4168862 | M7: =VLOOKUP(B7,'[3]Industry Averages'!$A$9:$E$104,5,0) -> 0.03398414
B8: Air Transport | C8: 6 | D8: 522.139 | E8: 907.273 | F8: 0.57550373 | G8: 0 | H8: 0 | I8: -0.052425789 | J8: -30.163963 | K8: 0.99250582 | L8: =1/K8 -> 1.0075508 | M8: =VLOOKUP(B8,'[3]Industry Averages'!$A$9:$E$104,5,0) -> -0.5981078
B9: Apparel | C9: 323 | D9: 1319.155 | E9: 1037.401 | F9: 1.271596 | G9: 18.023 | H9: 19.954 | I9: 0.0044862222 | J9: 0.13248117 | K9: 2.8247624 | L9: =1/K9 -> 0.35401208 | M9: =VLOOKUP(B9,'[3]Industry Averages'!$A$9:$E$104,5,0) -> 0.0951539
B10: Auto & Truck | C10: 12 | D10: 2055.735 | E10: 4078.638 | F10: 0.50402487 | G10: 103.4 | H10: 106.7262 | I10: -0.023678848 | J10: -0.48880652 | K10: 1.1695525 | L10: =1/K10 -> 0.85502786 | M10: =VLOOKUP(B10,'[3]Industry Averages'!$A$9:$E$104,5,0) -> -0.035019143
B11: Auto Parts | C11: 107 | D11: 1610.951 | E11: 1354.436 | F11: 1.1893888 | G11: 188.833 | H11: 14.6402 | I11: 0.012636963 | J11: 0.25411286 | K11: 1.9351197 | L11: =1/K11 -> 0.51676391 | M11: =VLOOKUP(B11,'[3]Industry Averages'!$A$9:$E$104,5,0) -> 0.05925667
B12: Bank (Money Center) | C12: 32 | D12: 2515.32 | E12: 9.25 | F12: NA | G12: 283.761 | H12: 0 | I12: 0.028561625 | J12: 95.335947 | K12: 0.43746869 | L12: =1/K12 -> 2.2858779 | M12: =VLOOKUP(B12,'[3]Industry Averages'!$A$9:$E$104,5,0) -> 0.011761751
B13: Banks (Regional) | C13: 5 | D13: 90.31 | E13: 0 | F13: NA | G13: 0 | H13: 0 | I13: 0.04048142 | J13: 14.611621 | K13: 0.52508707 | L13: =1/K13 -> 1.904446 | M13: =VLOOKUP(B13,'[3]Industry Averages'!$A$9:$E$104,5,0) -> 0.021963454
B14: Beverage (Alcoholic) | C14: 19 | D14: 132.855 | E14: 94.074 | F14: 1.4122393 | G14: 31.03 | H14: 1.323 | I14: 0.01977449 | J14: 0.23780071 | K14: 1.8773559 | L14: =1/K14 -> 0.53266405 | M14: =VLOOKUP(B14,'[3]Industry Averages'!$A$9:$E$104,5,0) -> 0.043070541
B15: Beverage (Soft) | C15: 5 | D15: 1.59 | E15: 70.091 | F15: 0.022684795 | G15: 0 | H15: 0 | I15: -0.043484802 | J15: -0.34007574 | K15: 2.003551 | L15: =1/K15 -> 0.49911381 | M15: =VLOOKUP(B15,'[3]Industry Averages'!$A$9:$E$104,5,0) -> -0.10415247
B16: Broadcasting | C16: 17 | D16: 182.505 | E16: 165.614 | F16: 1.1019902 | G16: 4.95 | H16: 0.0408 | I16: 0.0064843801 | J16: 0.04850055 | K16: 1.0879531 | L16: =1/K16 -> 0.91915728 | M16: =VLOOKUP(B16,'[3]Industry Averages'!$A$9:$E$104,5,0) -> 0.17417748
B17: Brokerage & Investment Banking | C17: 174 | D17: 98.346 | E17: 60.774 | F17: 1.6182249 | G17: 1.609 | H17: 0.9788 | I17: 0.0057186927 | J17: 2.605898 | K17: 0.79574458 | L17: =1/K17 -> 1.2566847 | M17: =VLOOKUP(B17,'[3]Industry Averages'!$A$9:$E$104,5,0) -> 0.01122989
B18: Building Materials | C18: 48 | D18: 294.063 | E18: 132.09 | F18: 2.2262321 | G18: -0.027 | H18: 0.4822 | I18: 0.030565549 | J18: 0.55016619 | K18: 2.0105272 | L18: =1/K18 -> 0.49738198 | M18: =VLOOKUP(B18,'[3]Industry Averages'!$A$9:$E$104,5,0) -> 0.17157185
B19: Business & Consumer Services | C19: 58 | D19: 141.797 | E19: 125.523 | F19: 1.1296495 | G19: -26.311 | H19: 0.0796 | I19: -0.0015559104 | J19: -0.022128622 | K19: 4.0759056 | L19: =1/K19 -> 0.24534425 | M19: =VLOOKUP(B19,'[3]Industry Averages'!$A$9:$E$104,5,0) -> 0.13481715
B20: Cable TV | C20: 8 | D20: 207.31 | E20: 272.431 | F20: 0.76096333 | G20: -0.428 | H20: 0 | I20: -0.050339982 | J20: -0.91369891 | K20: 0.98018147 | L20: =1/K20 -> 1.0202192 | M20: =VLOOKUP(B20,'[3]Industry Averages'!$A$9:$E$104,5,0) -> -0.0035265426
B21: Chemical (Basic) | C21: 128 | D21: 1638.433 | E21: 741.087 | F21: 2.2108511 | G21: 29.028 | H21: 4.4914 | I21: 0.036515056 | J21: 0.36157794 | K21: 1.4829761 | L21: =1/K21 -> 0.67431971 | M21: =VLOOKUP(B21,'[3]Industry Averages'!$A$9:$E$104,5,0) -> 0.11908759
B22: Chemical (Diversified) | C22: 10 | D22: 678.43 | E22: 188.1 | F22: 3.6067517 | G22: 33.42 | H22: 1.6744 | I22: 0.068788133 | J22: 0.69803449 | K22: 1.9394418 | L22: =1/K22 -> 0.51561227 | M22: =VLOOKUP(B22,'[3]Industry Averages'!$A$9:$E$104,5,0) -> 0.22137522
B23: Chemical (Specialty) | C23: 167 | D23: 2136.228 | E23: 1159.721 | F23: 1.8420189 | G23: 149.754 | H23: -8.0284 | I23: 0.022489218 | J23: 0.23451832 | K23: 2.0349819 | L23: =1/K23 -> 0.49140486 | M23: =VLOOKUP(B23,'[3]Industry Averages'!$A$9:$E$104,5,0) -> 0.20753919
B24: Coal & Related Energy | C24: 2 | D24: 1808.8 | E24: 550.3 | F24: 3.2869344 | G24: 0 | H24: 0.786 | I24: 0.082890845 | J24: 0.43299618 | K24: 4.0386197 | L24: =1/K24 -> 0.24760935 | M24: =VLOOKUP(B24,'[3]Industry Averages'!$A$9:$E$104,5,0) -> 0.29707528
B25: Computer Services | C25: 132 | D25: 1553.518 | E25: 2311.906 | F25: 0.67196417 | G25: 1856.958 | H25: -15.5838 | I25: 0.011830691 | J25: 0.089775144 | K25: 2.3636029 | L25: =1/K25 -> 0.42308292 | M25: =VLOOKUP(B25,'[3]Industry Averages'!$A$9:$E$104,5,0) -> 0.13864804
... B30: Drugs (Pharmaceutical) | C30: 156 | D30: 2186.779 | E30: 1565.338 | F30: 1.3970012 | G30: 407.009 | H30: 93.1694 | I30: 0.031780616 | J30: 0.29197519 | K30: 0.9289109 | L30: =1/K30 -> 1.0765295 | M30: =VLOOKUP(B30,'[3]Industry Averages'!$A$9:$E$104,5,0) -> 0.0549422
B31: Education | C31: 26 | D31: 9.189 | E31: 17.787 | F31: 0.51661326 | G31: 4.209 | H31: 0.3008 | I31: -0.025667073 | J31: NA | K31: 0.46552026 | L31: =1/K31 -> 2.1481342 | M31: =VLOOKUP(B31,'[3]Industry Averages'!$A$9:$E$104,5,0) -> NA
B32: Electrical Equipment | C32: 102 | D32: 563.663 | E32: 356.551 | F32: 1.5808762 | G32: 1.613 | H32: 32.2512 | I32: 0.013219963 | J32: 0.28987967 | K32: 1.5318774 | L32: =1/K32 -> 0.65279376 | M32: =VLOOKUP(B32,'[3]Industry Averages'!$A$9:$E$104,5,0) -> 0.054779301
B33: Electronics (Consumer & Office) | C33: 8 | D33: 57.396 | E33: 14.183 | F33: 4.0468166 | G33: 0 | H33: 0.4182 | I33: 0.02488621 | J33: 1.2335302 | K33: 8.0284903 | L33: =1/K33 -> 0.12455642 | M33: =VLOOKUP(B33,'[3]Industry Averages'!$A$9:$E$104,5,0) -> 0.3261852
B34: Electronics (General) | C34: 27 | D34: 56.801 | E34: 29.397 | F34: 1.932204 | G34: 38.2 | H34: 1.4602 | I34: 0.04877407 | J34: 0.76100466 | K34: 2.4268056 | L34: =1/K34 -> 0.41206432 | M34: =VLOOKUP(B34,'[3]Industry Averages'!$A$9:$E$104,5,0) -> 0.27119359
B35: Engineering/Construction | C35: 144 | D35: 1658.835 | E35: 1125.749 | F35: 1.473539 | G35: 31.045 | H35: 41.3822 | I35: 0.01222911 | J35: 0.18999347 | K35: 0.97947461 | L35: =1/K35 -> 1.0209555 | M35: =VLOOKUP(B35,'[3]Industry Averages'!$A$9:$E$104,5,0) -> 0.048665675
B36: Entertainment | C36: 60 | D36: 108.201 | E36: 238.994 | F36: 0.45273522 | G36: 14.456 | H36: 0.227 | I36: -0.063295763 | J36: -0.90136254 | K36: 0.67995091 | L36: =1/K36 -> 1.4706944 | M36: =VLOOKUP(B36,'[3]Industry Averages'!$A$9:$E$104,5,0) -> 0.0066039227
B37: Environmental & Waste Services | C37: 10 | D37: 37.591 | E37: 8.302 | F37: 4.5279451 | G37: 0 | H37: 0.1204 | I37: 0.047153118 | J37: 0.31870481 | K37: 5.2712447 | L37: =1/K37 -> 0.18970851 | M37: =VLOOKUP(B37,'[3]Industry Averages'!$A$9:$E$104,5,0) -> 0.84345977
B38: Farming/Agriculture | C38: 57 | D38: 161.962 | E38: 119.337 | F38: 1.3571818 | G38: -3.786 | H38: 2.4352 | I38: 0.0077462768 | J38: 0.13946671 | K38: 1.4992995 | L38: =1/K38 -> 0.66697815 | M38: =VLOOKUP(B38,'[3]Industry Averages'!$A$9:$E$104,5,0) -> 0.041177374
B39: Financial Svcs. (Non-bank & Insurance) | C39: 254 | D39: 906.479 | E39: 620.979 | F39: 1.4597579 | G39: 287.916 | H39: 0.3624 | I39: 0.011353578 | J39: 0.1942699 | K39: 0.10361554 | L39: =1/K39 -> 9.6510623 | M39: =VLOOKUP(B39,'[3]Industry Averages'!$A$9:$E$104,5,0) -> 0.0016319973
B40: Food Processing | C40: 185 | D40: 1139.239 | E40: 609.472 | F40: 1.8692229 | G40: 99.593 | H40: 3.0956 | I40: 0.016544828 | J40: 0.34667722 | K40: 2.3987394 | L40: =1/K40 -> 0.41688564 | M40: =VLOOKUP(B40,'[3]Industry Averages'!$A$9:$E$104,5,0) -> 0.054777163
B41: Food Wholesalers | C41: 32 | D41: 6.987 | E41: 5.029 | F41: 1.3893418 | G41: 0 | H41: 0.0144 | I41: 0.0019393916 | J41: 0.27852798 | K41: 6.2547509 | L41: =1/K41 -> 0.15987847 | M41: =VLOOKUP(B41,'[3]Industry Averages'!$A$9:$E$104,5,0) -> -0.12880592
B42: Furn/Home Furnishings | C42: 38 | D42: 205.164 | E42: 125.409 | F42: 1.6359591 | G42: 258.564 | H42: 0.717 | I42: 0.056785498 | J42: 1.2293977 | K42: 2.8429462 | L42: =1/K42 -> 0.35174777 | M42: =VLOOKUP(B42,'[3]Industry Averages'!$A$9:$E$104,5,0) -> 0.16055102
B43: Green & Renewable Energy | C43: 18 | D43: 2209.946 | E43: 407.417 | F43: 5.4242852 | G43: 155.484 | H43: 0.0186 | I43: 0.62222232 | J43: 1.7375867 | K43: 0.17791576 | L43: =1/K43 -> 5.6206375 | M43: =VLOOKUP(B43,'[3]Industry Averages'!$A$9:$E$104,5,0) -> 0.1203388
... B46: Heathcare Information and Technology | C46: 14 | D46: 245.562 | E46: 130.381 | F46: 1.8834186 | G46: 0 | H46: -5.9586 | I46: 0.052776096 | J46: 0.27452649 | K46: 0.84191312 | L46: =1/K46 -> 1.187771 | M46: =VLOOKUP(B46,'[3]Industry Averages'!$A$9:$E$104,5,0) -> 0.068925326
B47: Homebuilding | C47: 1 | D47: 0 | E47: 0 | F47: NA | G47: 0 | H47: 0 | I47: 0 | J47: 0 | K47: 0.39187228 | L47: =1/K47 -> 2.5518519 | M47: =VLOOKUP(B47,'[3]Industry Averages'!$A$9:$E$104,5,0) -> -0.087953556
B48: Hospitals/Healthcare Facilities | C48: 24 | D48: 359.256 | E48: 253.77 | F48: 1.4156756 | G48: 37.39 | H48: -0.2278 | I48: 0.028952691 | J48: 0.27604457 | K48: 1.5637777 | L48: =1/K48 -> 0.63947707 | M48: =VLOOKUP(B48,'[3]Industry Averages'!$A$9:$E$104,5,0) -> 0.061834622
B49: Hotel/Gaming | C49: 57 | D49: 148.636 | E49: 218.179 | F49: 0.68125713 | G49: 2.832 | H49: -0.2888 | I49: -0.024199395 | J49: -0.28817139 | K49: 0.54590969 | L49: =1/K49 -> 1.8318048 | M49: =VLOOKUP(B49,'[3]Industry Averages'!$A$9:$E$104,5,0) -> -0.01690855
B50: Household Products | C50: 36 | D50: 349.272 | E50: 289.444 | F50: 1.2066997 | G50: 7.234 | H50: 0.2278 | I50: 0.0053128495 | J50: 0.034634032 | K50: 1.8467134 | L50: =1/K50 -> 0.54150255 | M50: =VLOOKUP(B50,'[3]Industry Averages'!$A$9:$E$104,5,0) -> 0.049129456
B51: Information Services | C51: 24 | D51: 242.605 | E51: 190.988 | F51: 1.2702631 | G51: 152.813 | H51: 0.8042 | I51: 0.054409208 | J51: NA | K51: 2.0161587 | L51: =1/K51 -> 0.49599271 | M51: =VLOOKUP(B51,'[3]Industry Averages'!$A$9:$E$104,5,0) -> NA
B52: Insurance (General) | C52: 2 | D52: 22.01 | E52: 20.84 | F52: 1.056142 | G52: 0 | H52: 0 | I52: 0.00059022348 | J52: NA | K52: 2.0227551 | L52: =1/K52 -> 0.49437522 | M52: =VLOOKUP(B52,'[3]Industry Averages'!$A$9:$E$104,5,0) -> NA
B53: Insurance (Life) | C53: 7 | D53: 159.36 | E53: -1789.213 | F53: NA | G53: 0 | H53: 0 | I53: 0.015894366 | J53: 1.0830439 | K53: 27.659866 | L53: =1/K53 -> 0.036153465 | M53: =VLOOKUP(B53,'[3]Industry Averages'!$A$9:$E$104,5,0) -> 0.52271366
B54: Insurance (Prop/Cas.) | C54: 2 | D54: 20.02 | E54: 7.8 | F54: 2.5666667 | G54: 0 | H54: 0 | I54: 0.0017839156 | J54: 0.023687101 | K54: 1.1971136 | L54: =1/K54 -> 0.83534263 | M54: =VLOOKUP(B54,'[3]Industry Averages'!$A$9:$E$104,5,0) -> 0.0021071216
B55: Investments & Asset Management | C55: 96 | D55: 123.974 | E55: 152.524 | F55: 0.81281634 | G55: 0.014 | H55: 0.798 | I55: -0.0062420506 | J55: -0.032318518 | K55: 0.23998448 | L55: =1/K55 -> 4.1669362 | M55: =VLOOKUP(B55,'[3]Industry Averages'!$A$9:$E$104,5,0) -> -0.0091890334
B56: Machinery | C56: 149 | D56: 364.846 | E56: 282.71 | F56: 1.2905309 | G56: 47.929 | H56: -203.9688 | I56: -0.0065319395 | J56: -0.081072682 | K56: 1.7491018 | L56: =1/K56 -> 0.57172203 | M56: =VLOOKUP(B56,'[3]Industry Averages'!$A$9:$E$104,5,0) -> 0.057117455
B57: Metals & Mining | C57: 39 | D57: 3290.709 | E57: 2544.546 | F57: 1.2932401 | G57: 50.6 | H57: 2.4316 | I57: 0.015023865 | J57: 0.12188783 | K57: 1.5089391 | L57: =1/K57 -> 0.66271725 | M57: =VLOOKUP(B57,'[3]Industry Averages'!$A$9:$E$104,5,0) -> 0.047486807
B58: Office Equipment & Services | C58: 13 | D58: 11.138 | E58: 8.616 | F58: 1.2927112 | G58: 0 | H58: 0.0434 | I58: 0.010388843 | J58: 0.16317856 | K58: 1.983694 | L58: =1/K58 -> 0.50411001 | M58: =VLOOKUP(B58,'[3]Industry Averages'!$A$9:$E$104,5,0) -> 0.094608582
B59: Oil/Gas (Integrated) | C59: 1 | D59: 5441.3 | E59: 3108.8 | F59: 1.7502895 | G59: 0 | H59: 6.76 | I59: 0.031070945 | J59: 0.44887613 | K59: 1.5854294 | L59: =1/K59 -> 0.63074393 | M59: =VLOOKUP(B59,'[3]Industry Averages'!$A$9:$E$104,5,0) -> 0.039412352
B60: Oil/Gas (Production and Exploration) | C60: 6 | D60: 984.041 | E60: 356.791 | F60: 2.758032 | G60: 0 | H60: 3.4 | I60: 0.12979088 | J60: 0.55508675 | K60: 0.76607136 | L60: =1/K60 -> 1.3053614 | M60: =VLOOKUP(B60,'[3]Industry Averages'!$A$9:$E$104,5,0) -> 0.13604872
B61: Oil/Gas Distribution | C61: 11 | D61: 175.249 | E61: 307.997 | F61: 0.5689958 | G61: 24.6 | H61: 0 | I61: -0.012710918 | J61: -0.13728574 | K61: 2.4712319 | L61: =1/K61 -> 0.40465648 | M61: =VLOOKUP(B61,'[3]Industry Averages'!$A$9:$E$104,5,0) -> 0.051078271
B62: Oilfield Svcs/Equip. | C62: 22 | D62: 20972.774 | E62: 7314.322 | F62: 2.8673572 | G62: 303.3 | H62: 20.5486 | I62: 0.043075722 | J62: 1.2697498 | K62: 1.7169471 | L62: =1/K62 -> 0.58242912 | M62: =VLOOKUP(B62,'[3]Industry Averages'!$A$9:$E$104,5,0) -> 0.14364011
B63: Packaging & Container | C63: 79 | D63: 496.734 | E63: 241.195 | F63: 2.0594706 | G63: -0.021 | H63: 0.7066 | I63: 0.039511584 | J63: 0.69052922 | K63: 1.4785431 | L63: =1/K63 -> 0.67634148 | M63: =VLOOKUP(B63,'[3]Industry Averages'!$A$9:$E$104,5,0) -> 0.12924755
B64: Paper/Forest Products | C64: 50 | D64: 383.407 | E64: 200.152 | F64: 1.9155792 | G64: 6.629 | H64: 0.8082 | I64: 0.035064033 | J64: 0.36737281 | K64: 1.2129511 | L64: =1/K64 -> 0.82443556 | M64: =VLOOKUP(B64,'[3]Industry Averages'!$A$9:$E$104,5,0) -> 0.057808054
B65: Power | C65: 30 | D65: 9577.575 | E65: 6046.038 | F65: 1.5841076 | G65: 136.3 | H65: 11.2516 | I65: 0.049610994 | J65: 0.33518377 | K65: 0.54234524 | L65: =1/K65 -> 1.843844 | M65: =VLOOKUP(B65,'[3]Industry Averages'!$A$9:$E$104,5,0) -> 0.052286629
B66: Precious Metals | C66: 1 | D66: 0.038 | E66: 0.003 | F66: 12.666667 | G66: 0 | H66: 0 | I66: 8.75 | J66: NA | K66: 0.00068622405 | L66: =1/K66 -> 1457.25 | M66: =VLOOKUP(B66,'[3]Industry Averages'!$A$9:$E$104,5,0) -> NA
B67: Publishing & Newspapers | C67: 25 | D67: 22.612 | E67: 66.912 | F67: 0.33793639 | G67: 4.995 | H67: 0.1012 | I67: -0.03145557 | J67: -0.47283571 | K67: 0.79541061 | L67: =1/K67 -> 1.2572123 | M67: =VLOOKUP(B67,'[3]Industry Averages'!$A$9:$E$104,5,0) -> -0.0020872203
B68: R.E.I.T. | C68: 4 | D68: 0.479 | E68: 221.1 | F68: 0.0021664405 | G68: 167.4 | H68: 0 | I68: -0.055450094 | J68: -0.11960151 | K68: 0.10401743 | L68: =1/K68 -> 9.6137737 | M68: =VLOOKUP(B68,'[3]Industry Averages'!$A$9:$E$104,5,0) -> -0.0052557108
B69: Real Estate (Development) | C69: 137 | D69: 458.396 | E69: 132.474 | F69: 3.4602714 | G69: -1.069 | H69: 0.2194 | I69: 0.065727372 | J69: 0.46036074 | K69: 0.35545556 | L69: =1/K69 -> 2.8132912 | M69: =VLOOKUP(B69,'[3]Industry Averages'!$A$9:$E$104,5,0) -> 0.04609447
B70: Real Estate (General/Diversified) | C70: 15 | D70: 43.756 | E70: 91.657 | F70: 0.47738852 | G70: 114.001 | H70: 0.0678 | I70: 0.037157453 | J70: 0.19097827 | K70: 0.18337935 | L70: =1/K70 -> 5.4531766 | M70: =VLOOKUP(B70,'[3]Industry Averages'!$A$9:$E$104,5,0) -> -0.0055160551
B71: Real Estate (Operations & Services) | C71: 30 | D71: 2.449 | E71: 24.22 | F71: 0.10111478 | G71: 0 | H71: 0.0206 | I71: -0.12135807 | J71: -0.35085283 | K71: 0.22237473 | L71: =1/K71 -> 4.4969138 | M71: =VLOOKUP(B71,'[3]Industry Averages'!$A$9:$E$104,5,0) -> -0.032764429
B72: Recreation | C72: 11 | D72: 3.551 | E72: 18.69 | F72: 0.18999465 | G72: 0 | H72: -0.0036 | I72: -0.13896246 | J72: -0.87944318 | K72: 0.39546291 | L72: =1/K72 -> 2.5286821 | M72: =VLOOKUP(B72,'[3]Industry Averages'!$A$9:$E$104,5,0) -> -0.04829848
B73: Reinsurance | C73: 1 | D73: 2.48 | E73: 0.8 | F73: 3.1 | G73: 0 | H73: 0 | I73: 0.00028865483 | J73: 0.0034129116 | K73: 1.0845426 | L73: =1/K73 -> 0.92204773 | M73: =VLOOKUP(B73,'[3]Industry Averages'!$A$9:$E$104,5,0) -> 0.00031305845
B74: Restaurant/Dining | C74: 13 | D74: 238.219 | E74: 197.712 | F74: 1.2048788 | G74: 96.355 | H74: 0 | I74: 0.069807001 | J74: 0.883824 | K74: 1.116234 | L74: =1/K74 -> 0.89586949 | M74: =VLOOKUP(B74,'[3]Industry Averages'!$A$9:$E$104,5,0) -> 0.089699132
B75: Retail (Automotive) | C75: 4 | D75: 2.09 | E75: 2.961 | F75: 0.70584262 | G75: 0 | H75: 0 | I75: -0.0040863817 | J75: -0.29761597 | K75: 3.9132518 | L75: =1/K75 -> 0.25554195 | M75: =VLOOKUP(B75,'[3]Industry Averages'!$A$9:$E$104,5,0) -> 0.11542089
B76: Retail (Building Supply) | C76: 2 | D76: 5.16 | E76: 6.35 | F76: 0.81259843 | G76: 0 | H76: 0 | I76: -0.0027262314 | J76: -0.47387853 | K76: 3.931724 | L76: =1/K76 -> 0.25434135 | M76: =VLOOKUP(B76,'[3]Industry Averages'!$A$9:$E$104,5,0) -> -0.070849813
B77: Retail (Distributors) | C77: 239 | D77: 1877.353 | E77: 270.195 | F77: 6.9481412 | G77: 66.355 | H77: 0.03 | I77: 0.086444958 | J77: 3.0138248 | K77: 1.8495472 | L77: =1/K77 -> 0.54067287 | M77: =VLOOKUP(B77,'[3]Industry Averages'!$A$9:$E$104,5,0) -> 0.13155021
B78: Retail (General) | C78: 5 | D78: 37.17 | E78: 304.18 | F78: 0.12219738 | G78: 0 | H78: 0 | I78: -0.11824019 | J78: NA | K78: 0.78189759 | L78: =1/K78 -> 1.2789399 | M78: =VLOOKUP(B78,'[3]Industry Averages'!$A$9:$E$104,5,0) -> NA
B79: Retail (Grocery and Food) | C79: 5 | D79: 290.518 | E79: 72.546 | F79: 4.004604 | G79: 0 | H79: 0 | I79: 0.044944867 | J79: 0.77377882 | K79: 2.8303328 | L79: =1/K79 -> 0.35331534 | M79: =VLOOKUP(B79,'[3]Industry Averages'!$A$9:$E$104,5,0) -> 0.21158284
B80: Retail (Online) | C80: 13 | D80: 35.311 | E80: 47.831 | F80: 0.73824507 | G80: 26.27 | H80: 0.4292 | I80: 0.0083257489 | J80: NA | K80: 0.90286408 | L80: =1/K80 -> 1.1075864 | M80: =VLOOKUP(B80,'[3]Industry Averages'!$A$9:$E$104,5,0) -> NA
B81: Retail (Special Lines) | C81: 28 | D81: 130.68 | E81: 208.642 | F81: 0.62633602 | G81: -0.12 | H81: 0.1358 | I81: -0.016713977 | J81: -0.73826199 | K81: 1.5681995 | L81: =1/K81 -> 0.63767397 | M81: =VLOOKUP(B81,'[3]Industry Averages'!$A$9:$E$104,5,0) -> 0.069002525
B82: Rubber& Tires | C82: 16 | D82: 867.078 | E82: 510.808 | F82: 1.6974636 | G82: 0 | H82: 2.4634 | I82: 0.034196273 | J82: 0.85892675 | K82: 1.3204629 | L82: =1/K82 -> 0.75731021 | M82: =VLOOKUP(B82,'[3]Industry Averages'!$A$9:$E$104,5,0) -> 0.10110434
B83: Semiconductor | C83: 8 | D83: 11.166 | E83: 3.6 | F83: 3.1016667 | G83: 0 | H83: 0.0512 | I83: 0.098898987 | J83: 6.4894376 | K83: 0.90745 | L83: =1/K83 -> 1.1019891 | M83: =VLOOKUP(B83,'[3]Industry Averages'!$A$9:$E$104,5,0) -> 0.15848688
B84: Semiconductor Equip | C84: 1 | D84: 59.9 | E84: 5.22 | F84: 11.475096 | G84: 0 | H84: 0 | I84: 0.64481132 | J84: 3.190752 | K84: 0.8445374 | L84: =1/K84 -> 1.1840802 | M84: =VLOOKUP(B84,'[3]Industry Averages'!$A$9:$E$104,5,0) -> 0.63668957
B85: Shipbuilding & Marine | C85: 20 | D85: 931.372 | E85: 501.197 | F85: 1.8582952 | G85: 186.8 | H85: 0 | I85: 0.16691159 | J85: 0.53795638 | K85: 0.33701842 | L85: =1/K85 -> 2.9671969 | M85: =VLOOKUP(B85,'[3]Industry Averages'!$A$9:$E$104,5,0) -> 0.053748695
B86: Shoe | C86: 12 | D86: 59.264 | E86: 69.007 | F86: 0.85881142 | G86: -0.001 | H86: 0.3938 | I86: -0.0071880934 | J86: -0.08546306 | K86: 1.6084227 | L86: =1/K86 -> 0.6217271 | M86: =VLOOKUP(B86,'[3]Industry Averages'!$A$9:$E$104,5,0) -> 0.11401249
B87: Software (Entertainment) | C87: 7 | D87: 10.95 | E87: 48.874 | F87: 0.2240455 | G87: 12.31 | H87: 1.2372 | I87: -0.019746166 | J87: -0.1266317 | K87: 0.34598691 | L87: =1/K87 -> 2.8902828 | M87: =VLOOKUP(B87,'[3]Industry Averages'!$A$9:$E$104,5,0) -> 0.02411778
B88: Software (Internet) | C88: 7 | D88: 2.84 | E88: 2.612 | F88: 1.0872894 | G88: 0 | H88: 0 | I88: 0.0070634158 | J88: 0.044442976 | K88: 2.8522577 | L88: =1/K88 -> 0.35059946 | M88: =VLOOKUP(B88,'[3]Industry Averages'!$A$9:$E$104,5,0) -> -0.036861834
B89: Software (System & Application) | C89: 74 | D89: 144.428 | E89: 159.714 | F89: 0.90429142 | G89: 196.192 | H89: 32.9152 | I89: 0.044408639 | J89: 0.35783811 | K89: 1.7224831 | L89: =1/K89 -> 0.58055721 | M89: =VLOOKUP(B89,'[3]Industry Averages'!$A$9:$E$104,5,0) -> 0.16585904
B90: Steel | C90: 157 | D90: 6002.259 | E90: 3615.021 | F90: 1.6603663 | G90: 1294.383 | H90: 53.6032 | I90: 0.035892632 | J90: 0.38824088 | K90: 1.4225481 | L90: =1/K90 -> 0.70296391 | M90: =VLOOKUP(B90,'[3]Industry Averages'!$A$9:$E$104,5,0) -> 0.10464826
B91: Telecom (Wireless) | C91: 3 | D91: 3793.33 | E91: 7141.8 | F91: 0.53114481 | G91: 0 | H91: 0 | I91: -0.15952388 | J91: -1.8400342 | K91: 0.40842598 | L91: =1/K91 -> 2.448424 | M91: =VLOOKUP(B91,'[3]Industry Averages'!$A$9:$E$104,5,0) -> -0.12187765
B92: Telecom. Equipment | C92: 20 | D92: 99.475 | E92: 74.325 | F92: 1.3383787 | G92: 29.494 | H92: 12.5394 | I92: 0.042849453 | J92: 8.5530831 | K92: 0.7211393 | L92: =1/K92 -> 1.3866946 | M92: =VLOOKUP(B92,'[3]Industry Averages'!$A$9:$E$104,5,0) -> 0.41266933
... B97: Trucking | C97: 12 | D97: 39.139 | E97: 24.735 | F97: 1.5823327 | G97: 0 | H97: 0 | I97: 0.023913404 | J97: 0.39030082 | K97: 2.4414306 | L97: =1/K97 -> 0.40959591 | M97: =VLOOKUP(B97,'[3]Industry Averages'!$A$9:$E$104,5,0) -> 0.099366887
B98: Utility (General) | C98: 0 | D98: 0 | E98: 0 | F98: NA | G98: 0 | H98: 0 | I98: NA | J98: NA | K98: NA | L98: =1/K98 -> #VALUE! | M98: =VLOOKUP(B98,'[3]Industry Averages'!$A$9:$E$104,5,0) -> NA
B99: Utility (Water) | C99: 1 | D99: 0.331 | E99: 1.15 | F99: 0.28782609 | G99: 0 | H99: 1.262 | I99: 0.0011937483 | J99: 0.021168747 | K99: 1.5152258 | L99: =1/K99 -> 0.65996766 | M99: =VLOOKUP(B99,'[3]Industry Averages'!$A$9:$E$104,5,0) -> 0.15376352
B100: Total Market | C100: 4149 | D100: 91128.196 | E100: 56787.85 | F100: 1.6047129 | G100: 7200.638 | H100: 290.6888 | I100: 0.024042223 | J100: 0.35915811 | K100: 0.92986384 | L100: =1/K100 -> 1.0754263 | M100: =VLOOKUP(B100,'[3]Industry Averages'!$A$9:$E$104,5,0) -> 0.045696556
B101: Total Market (without financials) | C101: 3577 | D101: 87192.377 | E101: 57704.896 | F101: 1.5110048 | G101: 6627.338 | H101: 288.5496 | I101: 0.025165027 | J101: 0.32789454 | K101: 1.2945772 | L101: =1/K101 -> 0.77245299 | M101: =VLOOKUP(B101,'[3]Industry Averages'!$A$9:$E$104,5,0) -> 0.070760858

Sheet RAW FSn
B2: Balance Sheet
C4: 41699 | D4: 42064 | E4: 42430 | F4: 42795 | G4: 43160 | H4: 43525 | I4: 43891 | J4: 44256 | K4: 44621 | L4: 44986 | M4: 45352 | N4: 45717
B5: Equity Capital | C5: 795 | D5: 802 | E5: 805 | F5: 1215 | G5: 1220 | H5: 1226 | I5: 1229 | J5: 1231 | K5: 1232 | L5: 1243 | M5: 1248 | N5: 1251
B6: Reserves | C6: 26442 | D6: 30934 | E6: 41875 | F6: 45198 | G6: 51290 | H6: 57915 | I6: 64044 | J6: 59116 | K6: 61223 | L6: 67912 | M6: 73259 | N6: 68779
B7: Borrowings
B8: Long term Borrowings | C8: 76 | D8: 61 | E8: 27 | F8: 18 | G8: 12 | H8: 8 | I8: 6 | J8: 6 | K8: 5 | L8: 3 | M8: 2 | N8: 0
B9: Short term Borrowings | C9: 150 | D9: 195 | E9: 44 | F9: 19 | G9: 17 | H9: 2 | I9: 1 | J9: 4 | K9: 1 | L9: 35 | M9: 10 | N9: 91
B10: Lease Liabilities | C10: 0 | D10: 0 | E10: 0 | F10: 0 | G10: 0 | H10: 0 | I10: 268 | J10: 261 | K10: 244 | L10: 267 | M10: 292 | N10: 193
B11: Other Borrowings | C11: 16 | D11: 13 | E11: 13 | F11: 8 | G11: 7 | H11: 3 | I11: 2 | J11: 0 | K11: 0 | L11: 0 | M11: 0 | N11: 0
B12: Other Liabilities
B13: Non controlling int | C13: 203 | D13: 225 | E13: 261 | F13: 295 | G13: 334 | H13: 343 | I13: 377 | J13: 347 | K13: 366 | L13: 384 | M13: 383 | N13: 368
B14: Trade Payables | C14: 2106 | D14: 2020 | E14: 2339 | F14: 2659 | G14: 3496 | H14: 3510 | I14: 3630 | J14: 4319 | K14: 4417 | L14: 4659 | M14: 4798 | N14: 4807
B15: Advance from Customers | C15: 0 | D15: 0 | E15: 805 | F15: 495 | G15: 461 | H15: 430 | I15: 703 | J15: 811 | K15: 1278 | L15: 1295 | M15: 886 | N15: 1264
B16: Other liability items | C16: 11060 | D16: 11702 | E16: 5483 | F16: 5991 | G16: 7404 | H16: 8301 | I16: 7050 | J16: 7666 | K16: 8429 | L16: 10032 | M16: 10877 | N16: 11249
B17: Total Liabilities | C17: 40848 | D17: 45952 | E17: 51651 | F17: 55898 | G17: 64241 | H17: 71739 | I17: 77311 | J17: 73761 | K17: 77196 | L17: 85831 | M17: 91754 | N17: 88003
B19: Fixed Assets
B20: Land | C20: 1564 | D20: 1717 | E20: 1615 | F20: 1673 | G20: 1685 | H20: 2021 | I20: 2797 | J20: 2889 | K20: 2829 | L20: 2830 | M20: 2865 | N20: 1588
B21: Building | C21: 4110 | D21: 4860 | E21: 4219 | F21: 4716 | G21: 5331 | H21: 6996 | I21: 8161 | J21: 8387 | K21: 9100 | L21: 9789 | M21: 10944 | N21: 7550
B22: Plant Machinery | C22: 12633 | D22: 14667 | E22: 9112 | F22: 10384 | G22: 11453 | H22: 13316 | I22: 14625 | J22: 15307 | K22: 16912 | L22: 18480 | M22: 20718 | N22: 19423
B23: Equipments | C23: 34 | D23: 46 | E23: 27 | F23: 32 | G23: 32 | H23: 34 | I23: 40 | J23: 41 | K23: 44 | L23: 44 | M23: 53 | N23: 63
B24: Furniture n fittings | C24: 729 | D24: 805 | E24: 413 | F24: 459 | G24: 497 | H24: 644 | I24: 810 | J24: 833 | K24: 907 | L24: 1000 | M24: 1068 | N24: 282
B25: Railway sidings | C25: 2 | D25: 2 | E25: 2 | F25: 2 | G25: 2 | H25: 2 | I25: 2 | J25: 2 | K25: 2 | L25: 2 | M25: 2 | N25: 2
B26: Vehicles | C26: 120 | D26: 128 | E26: 107 | F26: 128 | G26: 140 | H26: 161 | I26: 184 | J26: 180 | K26: 179 | L26: 189 | M26: 192 | N26: 141
B27: Intangible Assets | C27: 398 | D27: 678 | E27: 563 | F27: 563 | G27: 570 | H27: 684 | I27: 684 | J27: 2734 | K27: 2744 | L27: 3490 | M27: 3505 | N27: 3622
B28: Other fixed assets | C28: 411 | D28: 458 | E28: 117 | F28: 138 | G28: 212 | H28: 234 | I28: 663 | J28: 716 | K28: 719 | L28: 786 | M28: 841 | N28: 967
B29: Gross Block | C29: 20000 | D29: 23361 | E29: 16176 | F29: 18094 | G29: 19920 | H29: 24090 | I29: 27965 | J29: 31088 | K29: 33435 | L29: 36608 | M29: 40189 | N29: 33638
B30: Accumulated Depreciation | C30: 7073 | D30: 8057 | E30: 1069 | F30: 2201 | G30: 3396 | H30: 4716 | I30: 6252 | J30: 7790 | K30: 9204 | L30: 10757 | M30: 12368 | N30: 11683
B31: Net Block | C31: =C29-C30 -> 12927 | D31: =D29-D30 -> 15304 | E31: =E29-E30 -> 15107 | F31: =F29-F30 -> 15893 | G31: =G29-G30 -> 16524 | H31: =H29-H30 -> 19374 | I31: =I29-I30 -> 21713 | J31: =J29-J30 -> 23298 | ... N31: =N29-N30 -> 21955
B33: CWIP | C33: 3117 | D33: 2700 | E33: 2560 | F33: 3730 | G33: 5508 | H33: 4136 | I33: 3256 | J33: 4011 | K33: 3226 | L33: 3003 | M33: 2861 | N33: 1091
B34: Investments | C34: 7284 | D34: 6943 | E34: 11748 | F34: 17581 | G34: 22053 | H34: 25043 | I34: 28663 | J34: 24871 | K34: 24841 | L34: 29415 | M34: 31114 | N34: 34720
B36: Other Assets
B37: Inventories | C37: 8255 | D37: 8587 | E37: 9062 | F37: 8116 | G37: 7495 | H37: 7860 | I37: 8879 | J37: 10397 | K37: 10864 | L37: 11771 | M37: 14153 | N37: 15638
B38: Trade receivables | C38: 2439 | D38: 1982 | E38: 1917 | F38: 2474 | G38: 2682 | H38: 4035 | I38: 2562 | J38: 2502 | K38: 2462 | L38: 2956 | M38: 4026 | N38: 4720
B39: Cash Equivalents | C39: 3490 | D39: 7896 | E39: 6063 | F39: 2967 | G39: 2900 | H39: 4152 | I39: 7277 | J39: 4659 | K39: 4654 | L39: 4880 | M39: 7218 | N39: 4012
B40: Loans n Advances | C40: 107 | D40: 150 | E40: 14 | F40: 7 | G40: 74 | H40: 67 | I40: 6 | J40: 7 | K40: 11 | L40: 13 | M40: 31 | N40: 10
B41: Other asset items | C41: 3234 | D41: 2391 | E41: 5180 | F41: 5129 | G41: 7004 | H41: 7071 | I41: 4952 | J41: 4015 | K41: 6906 | L41: 7941 | M41: 4531 | N41: 5858
B42: Total Assets | C42: 40848 | D42: 45952 | E42: 51651 | F42: 55898 | G42: 64241 | H42: 71739 | I42: 77311 | J42: 73761 | K42: 77196 | L42: 85831 | M42: 91754 | N42: 88003
B44: Cash Flow Statement
B45: Cash from Operating Activity
B46: Profit from operations | C46: 13172 | D46: 14261 | E46: 15154 | F46: 16075 | G46: 17433 | H46: 18862 | I46: 19416 | J46: 17326 | K46: 20857 | L46: 26052 | M46: 26635 | N46: 26719
B47: Receivables | C47: -1546 | D47: 558 | E47: -207 | F47: -870 | G47: -964 | H47: -755 | I47: 1411 | J47: -66 | K47: -732 | L47: -884 | M47: -934 | N47: -1023
B48: Inventory | C48: -755 | D48: -505 | E48: -693 | F48: 593 | G48: 602 | H48: -359 | I48: -508 | J48: -1460 | K48: -466 | L48: -1098 | M48: -2545 | N48: -2975
B49: Payables | C49: 456 | D49: -23 | E49: 622 | F49: 321 | G49: 2098 | H49: 639 | I49: -607 | J49: 1112 | K49: 1099 | L49: 1058 | M49: 141 | N49: 1256
B50: Working capital changes | C50: -1844 | D50: 31 | E50: -277 | F50: 44 | G50: 1736 | H50: -476 | I50: 296 | J50: -413 | K50: -100 | L50: -924 | M50: -3337 | N50: -2742
B51: Direct taxes | C51: -3984 | D51: -4449 | E51: -5078 | F51: -5492 | G51: -6000 | H51: -5803 | I51: -5023 | J51: -4387 | K51: -4982 | L51: -6250 | M51: -6120 | N51: -6350
B52: Cash from Investing Activity
B53: Fixed assets purchased | C53: -2887 | D53: -3300 | E53: -2348 | F53: -3122 | G53: -2878 | H53: -3169 | I53: -2441 | J53: -1837 | K53: -2142 | L53: -2743 | M53: -3563 | N53: -2279
B54: Fixed assets sold | C54: 38 | D54: 9 | E54: 8 | F54: 50 | G54: 80 | H54: 28 | I54: 27 | J54: 3 | K54: 133 | L54: 49 | M54: 107 | N54: 175
B55: Investments purchased | C55: -94242 | D55: -98742 | E55: -154081 | F55: -85683 | G55: -98330 | H55: -94187 | I55: -79835 | J55: -57553 | K55: -69776 | L55: -80932 | M55: -75107 | N55: -66373
B56: Investments sold | C56: 93293 | D56: 99658 | E56: 150651 | F56: 81034 | G56: 95017 | H56: 92454 | I56: 75835 | J56: 62797 | K56: 70992 | L56: 77230 | M56: 77830 | N56: 67311
B57: Interest received | C57: 374 | D57: 559 | E57: 741 | F57: 756 | G57: 736 | H57: 1184 | I57: 1513 | J57: 1275 | K57: 1035 | L57: 1324 | M57: 1138 | N57: 1072
B58: Dividends received | C58: 192 | D58: 268 | E58: 64 | F58: 4 | G58: 13 | H58: 13 | I58: 17 | J58: 7 | K58: 16 | L58: 19 | M58: 36 | N58: 38
B59: Invest in subsidiaries | C59: 0 | D59: 0 | E59: -8 | F59: 0 | G59: 0 | H59: 0 | I59: 0 | J59: 0 | K59: 0 | L59: 0 | M59: 0 | N59: 0
B60: Investment in group cos | C60: 0 | D60: 0 | E60: 0 | F60: 0 | G60: 0 | H60: 0 | I60: 0 | J60: -2 | K60: -2 | L60: -2 | M60: -65 | N60: -30
B61: Redemp n Canc of Shares | C61: 0 | D61: 0 | E61: 0 | F61: 129 | G61: 18 | H61: 18 | I61: 0 | J61: 0 | K61: 0 | L61: 56 | M61: 0 | N61: 0
B62: Other investing items | C62: -21 | D62: -3728 | E62: 1052 | F62: 3579 | G62: -1769 | H62: -1887 | I62: -1290 | J62: 1051 | K62: -2494 | L62: -733 | M62: 1187 | N62: -478
B63: Cash from Financing Activity
B64: Proceeds from shares | C64: 691 | D64: 979 | E64: 532 | F64: 1067 | G64: 913 | H64: 969 | I64: 625 | J64: 291 | K64: 292 | L64: 2477 | M64: 1443 | N64: 797
B65: Proceeds from borrowings | C65: 156 | D65: 7 | E65: 0 | F65: 0 | G65: 11 | H65: 0 | I65: 0 | J65: 0 | K65: 0 | L65: 0 | M65: 8 | N65: 90
B66: Repayment of borrowings | C66: -15 | D66: -20 | E66: -13 | F66: -13 | G66: -8 | H66: -18 | I66: -3 | J66: -2 | K66: -1 | L66: -1 | M66: -2 | N66: -54
B67: Interest paid fin | C67: -48 | D67: -16 | E67: -28 | F67: -25 | G67: -49 | H67: -98 | I67: -44 | J67: -41 | K67: -40 | L67: -41 | M67: -46 | N67: -50
B68: Dividends paid | C68: -4239 | D68: -4876 | E68: -5133 | F68: -6994 | G68: -5952 | H68: -6519 | I68: -7302 | J68: -18881 | K68: -13788 | L68: -15418 | M68: -19899 | N68: -17782
B69: Financial liabilities | C69: 0 | D69: 0 | E69: 0 | F69: 0 | G69: 0 | H69: 0 | I69: -49 | J69: -55 | K69: -59 | L69: -59 | M69: -67 | N69: -66
B70: Other financing items | C70: -667 | D70: -734 | E70: -971 | F70: -1335 | G70: -1136 | H70: -1203 | I70: -1409 | J70: 55 | K70: 15 | L70: 35 | M70: 12 | N70: 28
B71: Net Cash Flow | C71: -32 | D71: -93 | E71: 266 | F71: 75 | G71: -166 | H71: 169 | I71: 334 | J71: -367 | K71: -43 | L71: 139 | M71: 191 | N71: 26

Sheet RAW FS ITC
B2: Balance Sheet
C4: 41699 | D4: 42064 | E4: 42430 | F4: 42795 | G4: 43160 | H4: 43525 | I4: 43891 | J4: 44256 | K4: 44621 | L4: 44986 | M4: 45352 | N4: 45717 | R4: 41699 | S4: 42064 | T4: 42430 | U4: 42795 | V4: 43160 | W4: 43525 | X4: 43891 | Y4: 44256 | Z4: 44621 | AA4: 44986 | AB4: 45352 | AC4: 45717
B5: Equity Capital | C5: 64 | D5: 64 | E5: 129 | F5: 129 | G5: 129 | H5: 129 | I5: 129 | J5: 129 | K5: 129 | L5: 129 | M5: 129 | N5: 129 | Q5: Equity Capital | R5: 795 | S5: 802 | T5: 805 | U5: 1215 | V5: 1220 | W5: 1226 | X5: 1229 | Y5: 1231 | Z5: 1232 | AA5: 1243 | AB5: 1248 | AC5: 1251
B6: Reserves | C6: 1296 | D6: 1760 | E6: 1888 | F6: 2197 | G6: 2414 | H6: 2846 | I6: 2894 | J6: 3111 | K6: 3219 | L6: 3670 | M6: 3703 | N6: 3846 | Q6: Reserves | R6: 26442 | S6: 30934 | T6: 41875 | U6: 45198 | V6: 51290 | W6: 57915 | X6: 64044 | Y6: 59116 | Z6: 61223 | AA6: 67912 | AB6: 73259 | AC6: 68779
B7: Borrowings | Q7: Borrowings
B8: Long term Borrowings | C8: 252 | D8: 169 | E8: 0 | F8: 0 | G8: 20 | H8: 14 | I8: 10 | J8: 8 | K8: 0 | L8: 2 | M8: 0 | N8: 0 | Q8: Long term Borrowings | R8: 76 | S8: 61 | T8: 27 | U8: 18 | V8: 12 | W8: 8 | X8: 6 | Y8: 6 | Z8: 5 | AA8: 3 | AB8: 2 | AC8: 0
B9: Short term Borrowings | C9: 274 | D9: 165 | E9: 153 | F9: 239 | G9: 289 | H9: 335 | I9: 325 | J9: 340 | K9: 345 | L9: 473 | M9: 383 | N9: 379 | Q9: Short term Borrowings | R9: 150 | S9: 195 | T9: 44 | U9: 19 | V9: 17 | W9: 2 | X9: 1 | Y9: 4 | Z9: 1 | AA9: 35 | AB9: 10 | AC9: 91
B10: Lease Liabilities | C10: 0 | D10: 0 | E10: 0 | F10: 0 | G10: 0 | H10: 0 | I10: 0 | J10: 160 | K10: 134 | L10: 133 | M10: 145 | N10: 175 | Q10: Lease Liabilities | R10: 0 | S10: 0 | T10: 0 | U10: 0 | V10: 0 | W10: 0 | X10: 268 | Y10: 261 | Z10: 244 | AA10: 267 | AB10: 292 | AC10: 193
B11: Other Borrowings | C11: 154 | D11: 94 | E11: 179 | F11: 0 | G11: 3 | H11: 3 | I11: 3 | J11: 3 | K11: 0 | L11: 0 | M11: 0 | N11: 0 | Q11: Other Borrowings | R11: 16 | S11: 13 | T11: 13 | U11: 8 | V11: 7 | W11: 3 | X11: 2 | Y11: 0 | Z11: 0 | AA11: 0 | AB11: 0 | AC11: 0
B12: Other Liabilities | Q12: Other Liabilities
B13: Non controlling int | C13: 36 | D13: 14 | E13: 14 | F13: 13 | G13: 12 | H13: 12 | I13: 13 | J13: 18 | K13: 57 | L13: 157 | M13: 337 | N13: 291 | Q13: Non controlling int | R13: 203 | S13: 225 | T13: 261 | U13: 295 | V13: 334 | W13: 343 | X13: 377 | Y13: 347 | Z13: 366 | AA13: 384 | AB13: 383 | AC13: 368
B14: Trade Payables | C14: 503 | D14: 564 | E14: 669 | F14: 697 | G14: 822 | H14: 944 | I14: 950 | J14: 1134 | K14: 1344 | L14: 1452 | M14: 1581 | N14: 1363 | Q14: Trade Payables | R14: 2106 | S14: 2020 | T14: 2339 | U14: 2659 | V14: 3496 | W14: 3510 | X14: 3630 | Y14: 4319 | Z14: 4417 | AA14: 4659 | AB14: 4798 | AC14: 4807
B15: Advance from Customers | C15: 17 | D15: 30 | E15: 27 | F15: 23 | G15: 23 | H15: 30 | I15: 20 | J15: 41 | K15: 27 | L15: 46 | M15: 30 | N15: 59 | Q15: Advance from Customers | R15: 0 | S15: 0 | T15: 805 | U15: 495 | V15: 461 | W15: 430 | X15: 703 | Y15: 811 | Z15: 1278 | AA15: 1295 | AB15: 886 | AC15: 1264
B16: Other liability items | C16: 369 | D16: 264 | E16: 299 | F16: 326 | G16: 360 | H16: 583 | I16: 620 | J16: 482 | K16: 422 | L16: 738 | M16: 1045 | N16: 2039 | Q16: Other liability items | R16: 11060 | S16: 11702 | T16: 5483 | U16: 5991 | V16: 7404 | W16: 8301 | X16: 7050 | Y16: 7666 | Z16: 8429 | AA16: 10032 | AB16: 10877 | AC16: 11249
B17: Total Liabilities | C17: 2965 | D17: 3125 | E17: 3358 | F17: 3623 | G17: 4072 | H17: 4896 | I17: 4964 | J17: 5426 | K17: 5677 | L17: 6800 | M17: 7353 | N17: 8281 | Q17: Total Liabilities | R17: 40848 | S17: 45952 | T17: 51651 | U17: 55898 | V17: 64241 | W17: 71739 | X17: 77311 | Y17: 73761 | Z17: 77196 | AA17: 85831 | AB17: 91754 | AC17: 88003
B19: Fixed Assets - | C19: 888 | D19: 1076 | E19: 1050 | F19: 1085 | G19: 1110 | H19: 1300 | I19: 1396 | J19: 1612 | K19: 1760 | L19: 2246 | M19: 2724 | N19: 2758 | Q19: Fixed Assets | R19: 12921 | S19: 15303 | T19: 15107 | U19: 15893 | V19: 16524 | W19: 19374 | X19: 21713 | Y19: 23298 | Z19: 24232 | AA19: 25851 | AB19: 27820 | AC19: 21955
B20: Land | C20: 52 | D20: 52 | E20: 50 | F20: 49 | G20: 48 | H20: 71 | I20: 74 | J20: 73 | K20: 81 | L20: 71 | M20: 91 | N20: 83 | Q20: Land | R20: 1564 | S20: 1717 | T20: 1615 | U20: 1673 | V20: 1685 | W20: 2021 | X20: 2797 | Y20: 2889 | Z20: 2829 | AA20: 2830 | AB20: 2865 | AC20: 1588
B21: Building | C21: 316 | D21: 306 | E21: 266 | F21: 276 | G21: 291 | H21: 560 | I21: 617 | J21: 597 | K21: 620 | L21: 645 | M21: 706 | N21: 679 | Q21: Building | R21: 4110 | S21: 4860 | T21: 4219 | U21: 4716 | V21: 5331 | W21: 6996 | X21: 8161 | Y21: 8387 | Z21: 9100 | AA21: 9789 | AB21: 10944 | AC21: 7550
B22: Plant Machinery | C22: 449 | D22: 477 | E22: 272 | F22: 359 | G22: 401 | H22: 470 | I22: 583 | J22: 590 | K22: 671 | L22: 748 | M22: 837 | N22: 811 | Q22: Plant Machinery | R22: 12633 | S22: 14667 | T22: 9112 | U22: 10384 | V22: 11453 | W22: 13316 | X22: 14625 | Y22: 15307 | Z22: 16912 | AA22: 18480 | AB22: 20718 | AC22: 19423
B23: Equipments | C23: 14 | D23: 14 | E23: 10 | F23: 13 | G23: 17 | H23: 18 | I23: 20 | J23: 23 | K23: 26 | L23: 29 | M23: 33 | N23: 32 | Q23: Equipments | R23: 34 | S23: 46 | T23: 27 | U23: 32 | V23: 32 | W23: 34 | X23: 40 | Y23: 41 | Z23: 44 | AA23: 44 | AB23: 53 | AC23: 63
B24: Furniture n fittings | C24: 23 | D24: 24 | E24: 12 | F24: 14 | G24: 20 | H24: 21 | I24: 28 | J24: 32 | K24: 36 | L24: 39 | M24: 46 | N24: 47 | Q24: Furniture n fittings | R24: 729 | S24: 805 | T24: 413 | U24: 459 | V24: 497 | W24: 644 | X24: 810 | Y24: 833 | Z24: 907 | AA24: 1000 | AB24: 1068 | AC24: 282
B25: Vehicles | C25: 7 | D25: 7 | E25: 2 | F25: 3 | G25: 4 | H25: 4 | I25: 5 | J25: 6 | K25: 6 | L25: 6 | M25: 6 | N25: 6 | Q25: Vehicles | R25: 122 | S25: 130 | T25: 109 | U25: 130 | V25: 142 | W25: 163 | X25: 186 | Y25: 182 | Z25: 181 | AA25: 191 | AB25: 194 | AC25: 143
... B29: Accumulated Depreciation | C29: 308 | D29: 377 | E29: 85 | F29: 167 | G29: 249 | H29: 434 | I29: 540 | J29: 592 | K29: 763 | L29: 769 | M29: 860 | N29: 777 | Q29: Accumulated Depreciation | R29: 7073 | S29: 8057 | T29: 1069 | U29: 2201 | V29: 3396 | W29: 4716 | X29: 6252 | Y29: 7790 | Z29: 9204 | AA29: 10757 | AB29: 12368 | AC29: 11683
B30: Net Block | C30: =C28-C29 -> 910 | D30: =D28-D29 -> 1096 | E30: =E28-E29 -> 1057 | F30: =F28-F29 -> 1093 | G30: =G28-G29 -> 1120 | H30: =H28-H29 -> 1300 | I30: =I28-I29 -> 1400 | J30: =J28-J29 -> 1612 | ... N30: =N28-N29 -> 2758 | Q30: Net Block | R30: =R28-R29 -> 12927 | S30: =S28-S29 -> 15304 | T30: =T28-T29 -> 15107 | U30: =U28-U29 -> 15893 | V30: =V28-V29 -> 16524 | W30: =W28-W29 -> 19374 | X30: =X28-X29 -> 21713 | Y30: =Y28-Y29 -> 23298 | ... AC30: =AC28-AC29 -> 21955
B32: CWIP | C32: 4 | D32: 3 | E32: 37 | F32: 11 | G32: 27 | H32: 45 | I32: 58 | J32: 24 | K32: 39 | L32: 67 | M32: 44 | N32: 40 | Q32: CWIP | R32: 3117 | S32: 2700 | T32: 2560 | U32: 3730 | V32: 5508 | W32: 4136 | X32: 3256 | Y32: 4011 | Z32: 3226 | AA32: 3003 | AB32: 2861 | AC32: 1091
B33: Investments | C33: 311 | D33: 284 | E33: 544 | F33: 608 | G33: 543 | H33: 450 | I33: 733 | J33: 854 | K33: 828 | L33: 1096 | M33: 602 | N33: 1590 | Q33: Investments | R33: 7284 | S33: 6943 | T33: 11748 | U33: 17581 | V33: 22053 | W33: 25043 | X33: 28663 | Y33: 24871 | Z33: 24841 | AA33: 29415 | AB33: 31114 | AC33: 34720
B35: Other Assets | C35: 1762 | D35: 1763 | E35: 1727 | F35: 1919 | G35: 2392 | H35: 3101 | I35: 2777 | J35: 2936 | K35: 3050 | L35: 3391 | M35: 3983 | N35: 3893 | Q35: Other Assets | R35: 17526 | S35: 21006 | T35: 22237 | U35: 18694 | V35: 20156 | W35: 23185 | X35: 23678 | Y35: 21580 | Z35: 24898 | AA35: 27561 | AB35: 29959 | AC35: 30237
B36: Inventories | C36: 796 | D36: 995 | E36: 926 | F36: 1253 | G36: 1511 | H36: 1411 | I36: 1380 | J36: 1126 | K36: 1412 | L36: 1225 | M36: 1336 | N36: 1235 | Q36: Inventories | R36: 8255 | S36: 8587 | T36: 9062 | U36: 8116 | V36: 7495 | W36: 7860 | X36: 8879 | Y36: 10397 | Z36: 10864 | AA36: 11771 | AB36: 14153 | AC36: 15638
B37: Trade receivables | C37: 223 | D37: 177 | E37: 252 | F37: 247 | G37: 340 | H37: 517 | I37: 539 | J37: 388 | K37: 652 | L37: 1015 | M37: 1069 | N37: 1271 | Q37: Trade receivables | R37: 2439 | S37: 1982 | T37: 1917 | U37: 2474 | V37: 2682 | W37: 4035 | X37: 2562 | Y37: 2502 | Z37: 2462 | AA37: 2956 | AB37: 4026 | AC37: 4720
B38: Cash Equivalents | C38: 406 | D38: 205 | E38: 317 | F38: 236 | G38: 201 | H38: 552 | I38: 279 | J38: 944 | K38: 579 | L38: 756 | M38: 943 | N38: 777 | Q38: Cash Equivalents | R38: 3490 | S38: 7896 | T38: 6063 | U38: 2967 | V38: 2900 | W38: 4152 | X38: 7277 | Y38: 4659 | Z38: 4654 | AA38: 4880 | AB38: 7218 | AC38: 4012
B39: Loans n Advances | C39: 47 | D39: 89 | E39: 106 | F39: 83 | G39: 217 | H39: 110 | I39: 97 | J39: 102 | K39: 20 | L39: 110 | M39: 214 | N39: 214 | Q39: Loans n Advances | R39: 107 | S39: 150 | T39: 14 | U39: 7 | V39: 74 | W39: 67 | X39: 6 | Y39: 7 | Z39: 11 | AA39: 13 | AB39: 31 | AC39: 10
B40: Other asset items | C40: 290 | D40: 297 | E40: 126 | F40: 100 | G40: 123 | H40: 511 | I40: 482 | J40: 376 | K40: 387 | L40: 285 | M40: 421 | N40: 396 | Q40: Other asset items | R40: 3234 | S40: 2391 | T40: 5180 | U40: 5129 | V40: 7004 | W40: 7071 | X40: 4952 | Y40: 4015 | Z40: 6906 | AA40: 7941 | AB40: 4531 | AC40: 5858
B41: Total Assets | C41: 2965 | D41: 3125 | E41: 3358 | F41: 3623 | G41: 4072 | H41: 4896 | I41: 4964 | J41: 5426 | K41: 5677 | L41: 6800 | M41: 7353 | N41: 8281 | Q41: Total Assets | R41: 40848 | S41: 45952 | T41: 51651 | U41: 55898 | V41: 64241 | W41: 71739 | X41: 77311 | Y41: 73761 | Z41: 77196 | AA41: 85831 | AB41: 91754 | AC41: 88003
B43: Cash Flow Statement
B45: Cash from Operating Activity | C45: 660 | D45: 665 | E45: 818 | F45: 649 | G45: 516 | H45: 1062 | I45: 1214 | J45: 2007 | K45: 1016 | L45: 1419 | M45: 1387 | N45: 1363 | Q45: Cash from Operating Activity | R45: 7344 | S45: 9843 | T45: 9799 | U45: 10627 | V45: 13169 | W45: 12583 | X45: 14690 | Y45: 12527 | Z45: 15776 | AA45: 18878 | AB45: 17179 | AC45: 17627
B46: Profit from operations | C46: 754 | D46: 891 | E46: 1085 | F46: 1215 | G46: 1160 | H46: 1361 | I46: 1475 | J46: 1617 | K46: 1709 | L46: 1847 | M46: 2040 | N46: 2219 | Q46: Profit from operations | R46: 13172 | S46: 14261 | T46: 15154 | U46: 16075 | V46: 17433 | W46: 18862 | X46: 19416 | Y46: 17326 | Z46: 20857 | AA46: 26052 | AB46: 26635 | AC46: 26719
B47: Receivables | C47: -28 | D47: 46 | E47: -76 | F47: 5 | G47: -93 | H47: -177 | I47: -22 | J47: 147 | K47: -272 | L47: -360 | M47: -52 | N47: -205 | Q47: Receivables | R47: -1546 | S47: 558 | T47: -207 | U47: -870 | V47: -964 | W47: -755 | X47: 1411 | Y47: -66 | Z47: -732 | AA47: -884 | AB47: -934 | AC47: -1023
B48: Inventory | C48: 41 | D48: -198 | E48: 66 | F48: -328 | G48: -257 | H48: 100 | I48: 31 | J48: 251 | K48: -286 | L48: 191 | M48: -101 | N48: 101 | Q48: Inventory | R48: -755 | S48: -505 | T48: -693 | U48: 593 | V48: 602 | W48: -359 | X48: -508 | Y48: -1460 | Z48: -466 | AA48: -1098 | AB48: -2545 | AC48: -2975
B49: Payables | C49: 0 | D49: 0 | E49: 106 | F49: 28 | G49: 125 | H49: 121 | I49: 10 | J49: 184 | K49: 210 | L49: 99 | M49: 106 | N49: -218 | Q49: Payables | R49: 456 | S49: -23 | T49: 622 | U49: 321 | V49: 2098 | W49: 639 | X49: -607 | Y49: 1112 | Z49: 1099 | AA49: 1058 | AB49: 141 | AC49: 1256
B50: Loans Advances | C50: 0 | D50: 0 | E50: -99 | F50: 0 | G50: 2 | H50: -1 | I50: -1 | J50: -60 | K50: 1 | L50: 1 | M50: 9 | N50: -3 | Q50: Loans Advances | R50: 0 | S50: 0 | T50: 0 | U50: 0 | V50: 0 | W50: 0 | X50: 0 | Y50: 0 | Z50: 0 | AA50: 0 | AB50: 0 | AC50: 0
B51: Other WC items | C51: 74 | D51: 135 | E51: -17 | F51: 25 | G51: -126 | H51: -22 | I51: 11 | J51: 153 | K51: 5 | L51: 10 | M51: -188 | N51: 32 | Q51: Other WC items | R51: 0 | S51: 0 | T51: 0 | U51: 0 | V51: 0 | W51: 0 | X51: 0 | Y51: 0 | Z51: 0 | AA51: 0 | AB51: 0 | AC51: 0
B52: Working capital changes | C52: 88 | D52: -17 | E52: -20 | F52: -270 | G52: -349 | H52: 21 | I52: 29 | J52: 675 | K52: -342 | L52: -59 | M52: -226 | N52: -293 | Q52: Working capital changes | R52: -1844 | S52: 31 | T52: -277 | U52: 44 | V52: 1736 | W52: -476 | X52: 296 | Y52: -413 | Z52: -100 | AA52: -924 | AB52: -3337 | AC52: -2742
B53: Direct taxes | C53: -181 | D53: -210 | E53: -247 | F53: -296 | G53: -295 | H53: -320 | I53: -290 | J53: -285 | K53: -351 | L53: -369 | M53: -378 | N53: -484 | Q53: Direct taxes | R53: -3984 | S53: -4449 | T53: -5078 | U53: -5492 | V53: -6000 | W53: -5803 | X53: -5023 | Y53: -4387 | Z53: -4982 | AA53: -6250 | AB53: -6120 | AC53: -6350
B54: Exceptional CF items | C54: 0 | D54: 0 | E54: 0 | F54: 0 | G54: 0 | H54: 0 | I54: 0 | J54: 0 | K54: 0 | L54: 0 | M54: -49 | N54: -79 | Q54: Exceptional CF items | R54: 0 | S54: 0 | T54: 0 | U54: 0 | V54: 0 | W54: 0 | X54: 0 | Y54: 0 | Z54: 0 | AA54: 0 | AB54: 0 | AC54: 0
B56: Cash from Investing Activity | C56: -202 | D56: -186 | E56: -203 | F56: -125 | G56: 59 | H56: -367 | I56: -22 | J56: -933 | K56: 441 | L56: -928 | M56: 176 | N56: -621 | Q56: Cash from Investing Activity | R56: -3254 | S56: -5275 | T56: -3921 | U56: -3251 | V56: -7114 | W56: -5546 | X56: -6174 | Y56: 5740 | Z56: -2238 | AA56: -5732 | AB56: 1563 | AC56: -564
B57: Fixed assets purchased | C57: -77 | D57: -59 | E57: -101 | F57: -87 | G57: -133 | H57: -162 | I57: -188 | J57: -142 | K57: -132 | L57: -182 | M57: -153 | N57: -161 | Q57: Fixed assets purchased | R57: -2887 | S57: -3300 | T57: -2348 | U57: -3122 | V57: -2878 | W57: -3169 | X57: -2441 | Y57: -1837 | Z57: -2142 | AA57: -2743 | AB57: -3563 | AC57: -2279
... B79: Net Cash Flow | C79: 119 | D79: -147 | E79: 14 | F79: -51 | G79: 8 | H79: -3 | I79: 45 | J79: 16 | K79: 167 | L79: -69 | M79: 21 | N79: 93 | Q79: Net Cash Flow | R79: -32 | S79: -93 | T79: 266 | U79: 75 | V79: -166 | W79: 169 | X79: 334 | Y79: -367 | Z79: -43 | AA79: 139 | AB79: 191 | AC79: 26

Sheet List of Stocks
A2: COMPANY_NAME | B2: BSE | C2: NSE | D2: Industry
A3: 20 MICRONS LTD | B3: 533022 | C3: 20MICRONS | D3: Mining
A4: 21ST CENTURY MANAGEMENT SERVICES LTD | B4: 526921 | C4: 21STCENMGM | D4: Other Financial Services
A5: 3I INFOTECH LTD | B5: 532628 | C5: 3IINFOTECH | D5: IT Consulting & Software
A6: 3M (INDIA) LTD | B6: 523395 | C6: 3M(INDIA) | D6: Diversified
A7: 3M INDIA LTD | B7: 523395 | C7: 3MINDIA | D7: Diversified
A8: 3P LAND HOLDINGS LTD | B8: 516092 | C8: 3PLAND | D8: Paper & Paper Products
A9: 5PAISA CAPITAL LTD | B9: 540776 | C9: 5PAISA | D9: Other Financial Services
A10: 63 MOONS TECHNOLOGIES LTD | B10: 526881 | C10: 63MOONS | D10: IT Consulting & Software
A11: 7NR RETAIL LTD | B11: 540615 | C11: Not Listed | D11: Specialty Retail
A12: 7SEAS ENTERTAINMENT LTD | B12: 540874 | C12: Not Listed | D12: Movies & Entertainment
A13: 8K MILES SOFTWARE SERVICES LTD | B13: 512161 | C13: 8KMILES | D13: Internet Software & Services
A14: A & M FEBCON LTD | B14: 540697 | C14: Not Listed | D14: Industrial Machinery
A15: A AND M JUMBO BAGS LTD | B15: Not Listed | C15: AMJUMBO | D15: SME
A16: A INFRASTRUCTURE LTD | B16: 539620 | C16: Not Listed | D16: Cement & Cement Products
A17: A K SPINTEX LTD | B17: 539300 | C17: Not Listed | D17: Textiles
A18: A K CAPITAL SERVICES LTD | B18: 530499 | C18: Not Listed | D18: Finance (including NBFCs)
A19: A.F. Enterprises Ltd | B19: 538351 | C19: AFEL | D19: Investment Companies
A20: A-1 ACID LTD | B20: 542012 | C20: Not Listed | D20: Comm.Trading & Distribution
A21: A2Z INFRA ENGINEERING LTD | B21: 533292 | C21: A2ZINFRA | D21: Utilities:Non-Elec.
A22: AADHAAR VENTURES (INDIA) LTD | B22: 531611 | C22: Not Listed | D22: Finance (including NBFCs)
A23: AADHAAR VENTURES INDIA LTD | B23: 531611 | C23: Not Listed | D23: Finance (including NBFCs)
A24: AAKASH EXPLORATION SERVICES LTD | B24: Not Listed | C24: AAKASH | D24: SME
A25: AANANDA LAKSHMI SPINNING MILLS LTD | B25: 539096 | C25: Not Listed | D25: Textiles
A26: AANCHAL ISPAT LTD | B26: 538812 | C26: Not Listed | D26: Iron & Steel/Interm.Products
A27: AAR COMMERCIAL COMPANY LTD | B27: 539632 | C27: Not Listed | D27: Distributors
A28: Aar Shyam India Investment Company Ltd | B28: 542377 | C28: AARSHYAM | D28: Finance (including NBFCs)
A29: AAREY DRUGS & PHARMACEUTICALS LTD | B29: 524412 | C29: Not Listed | D29: Pharmaceuticals
A30: AARON INDUSTRIES LTD | B30: Not Listed | C30: AARON | D30: SME
A31: Aartech Solonics Ltd | B31: 542580 | C31: AARTECH | D31: Heavy Electrical Equipment
A32: AARTI DRUGS LTD | B32: 524348 | C32: AARTIDRUGS | D32: Pharmaceuticals
A33: AARTI INDUSTRIES LTD | B33: 524208 | C33: AARTIIND | D33: Commodity Chemicals
A34: AARV INFRATEL LTD | B34: 526488 | C34: Not Listed | D34: Textiles
A35: AARVEE DENIMS & EXPORTS LTD | B35: 514274 | C35: AARVEEDEN | D35: Textiles
A36: AARVI ENCON LTD | B36: Not Listed | C36: AARVI | D36: SME
A37: AASHEE INFOTECH LTD | B37: 519319 | C37: Not Listed | D37: Internet Software & Services
A38: AASWA TRADING & EXPORTS LTD | B38: 512038 | C38: Not Listed | D38: Comm.Trading & Distribution
A39: AAVAS FINANCIERS LTD | B39: 541988 | C39: AAVAS | D39: Housing Finance
A40: AAYUSH FOOD AND HERBS LTD | B40: 539528 | C40: Not Listed | D40: Packaged Foods
A41: ABAN OFFSHORE LTD | B41: 523204 | C41: ABAN | D41: Exploration & Production
A42: ABANS ENTERPRISES LTD | B42: 512165 | C42: Not Listed | D42: Comm.Trading & Distribution
A43: ABB INDIA LTD | B43: 500002 | C43: ABB | D43: Heavy Electrical Equipment
A44: ABBOTT (INDIA) LTD | B44: 500488 | C44: ABBOT(INDIA) | D44: Pharmaceuticals
A45: ABBOTT INDIA LTD | B45: 500488 | C45: ABBOTINDIA | D45: Pharmaceuticals
A46: ABC (INDIA) LTD | B46: 520123 | C46: Not Listed | D46: Surface Transportation
A47: ABC GAS INTERNATIONAL LTD | B47: 513119 | C47: Not Listed | D47: Copper
A48: ABC INDIA LTD | B48: 520123 | C48: Not Listed | D48: Surface Transportation
... A56: ABIRAMI FINANCIAL SERVICES INDIA LTD | B56: 511756 | C56: Not Listed | D56: Finance (including NBFCs)
A57: ABM INTERNATIONAL LTD | B57: Not Listed | C57: ABMINTLTD | D57: Others
A58: ABM KNOWLEDGEWARE LTD | B58: 531161 | C58: Not Listed | D58: IT Software Products
A59: ACC LTD | B59: 500410 | C59: ACC | D59: Cement & Cement Products
A60: ACCEL LTD | B60: 517494 | C60: Not Listed | D60: Storage Media & Peripherals
A61: ACCELYA KALE SOLUTIONS LTD | B61: 532268 | C61: ACCELYA | D61: IT Consulting & Software
A62: ACCORD SYNERGY LTD | B62: Not Listed | C62: ACCORD | D62: SME
A63: ACCURACY SHIPPING LTD | B63: Not Listed | C63: ACCURACY | D63: SME
A64: ACE EDUTREND LTD | B64: 530093 | C64: Not Listed | D64: Education
A65: ACE INTEGRATED SOLUTIONS LTD | B65: Not Listed | C65: ACEINTEG | D65: SME
A66: ACE MEN ENGG WORKS LTD | B66: 539661 | C66: Not Listed | D66: Distributors
A67: ACE SOFTWARE EXPORTS LTD | B67: 531525 | C67: Not Listed | D67: IT Software Products
A68: Achal Investments Ltd | B68: 538570 | C68: ACHAL | D68: Other Financial Services
A69: ACI INFOCOM LTD | B69: 517356 | C69: Not Listed | D69: Storage Media & Peripherals
A70: ACKNIT INDUSTRIES LTD | B70: 530043 | C70: Not Listed | D70: Other Apparels & Accessories
A71: ACME RESOURCES LTD | B71: 539391 | C71: Not Listed | D71: Finance (including NBFCs)
A72: ACROW INDIA LTD. | B72: 513149 | C72: ACROW | D72: Iron &amp; Steel Products
A73: ACRYSIL LTD | B73: 524091 | C73: Not Listed | D73: Plastic Products
A74: ACTION CONSTRUCTION EQUIPMENT LTD | B74: 532762 | C74: ACE | D74: Transport Related Services
A75: ACTION FINANCIAL SERVICES (INDIA) LTD | B75: 511706 | C75: Not Listed | D75: Other Financial Services
A76: ACTION FINANCIAL SERVICES INDIA LTD | B76: 511706 | C76: Not Listed | D76: Other Financial Services
A77: ACTIVE CLOTHING CO LTD | B77: 541144 | C77: Not Listed | D77: Other Apparels & Accessories
... A135: AGRI-TECH INDIA LTD | B135: 537292 | C135: AGRITECH | D135: Other Agricultural Products
A136: AGRO PHOS (INDIA) LTD | B136: Not Listed | C136: AGROPHOS | D136: SME
A137: AGRO PHOS INDIA LTD | B137: Not Listed | C137: AGROPHOS | D137: SME
A138: AGRO TECH FOODS LTD | B138: 500215 | C138: ATFL | D138: Other Agricultural Products
A139: AHIMSA INDUSTRIES LTD | B139: Not Listed | C139: AHIMSA | D139: SME
A140: AHLADA ENGINEERS LTD | B140: Not Listed | C140: AHLADA | D140: SME
A141: AHLUWALIA CONTRACTS (INDIA) LTD | B141: 532811 | C141: AHLUCONT | D141: Realty
A142: AHLUWALIA CONTRACTS INDIA LTD | B142: 532811 | C142: AHLUCONT | D142: Realty
A143: AHMEDABAD STEELCRAFT LTD | B143: 522273 | C143: Not Listed | D143: Iron & Steel/Interm.Products
A144: AI CHAMPDANY INDUSTRIES LTD | B144: 532806 | C144: Not Listed | D144: Jute & Jute Products
A145: AIA ENGINEERING LTD | B145: 532683 | C145: AIAENG | D145: Other Industrial Goods
A146: AIMCO PESTICIDES LTD | B146: 524288 | C146: Not Listed | D146: Agrochemicals
A147: AIRAN LTD | B147: Not Listed | C147: AIRAN | D147: SME
A148: AIRO LAM LTD | B148: Not Listed | C148: AIROLAM | D148: SME
A149: AISHWARYA TELECOM LTD | B149: 532975 | C149: Not Listed | D149: Telecom Equipment
A150: AJANTA PHARMA LTD | B150: 532331 | C150: AJANTPHARM | D150: Pharmaceuticals
A151: AJANTA SOYA LTD | B151: 519216 | C151: Not Listed | D151: Edible Oils
A152: AJCON GLOBAL SERVICES LTD | B152: 511692 | C152: Not Listed | D152: Other Financial Services
A153: AJEL LTD | B153: 530713 | C153: Not Listed | D153: IT Consulting & Software
A154: AJMERA REALTY & INFRA (INDIA) LTD | B154: 513349 | C154: AJMERA | D154: Realty
A155: AJMERA REALTY & INFRA INDIA LTD | B155: 513349 | C155: AJMERA | D155: Realty
A156: AJOONI BIOTECH LTD | B156: Not Listed | C156: AJOONI | D156: SME
A157: AJWA FUN WORLD & RESORT LTD | B157: 526628 | C157: Not Listed | D157: Other Leisure Facilities
A158: AKAR AUTO INDUSTRIES LTD | B158: 530621 | C158: Not Listed | D158: Industrial Machinery
A159: AKASH INFRA PROJECTS LTD | B159: Not Listed | C159: AKASH | D159: SME
A160: AKASHDEEP METAL INDUSTRIES LTD | B160: 538778 | C160: Not Listed | D160: Finance (including NBFCs)
A161: AKG EXIM LTD | B161: Not Listed | C161: AKG | D161: SME
A162: AKI (INDIA) LTD | B162: 542020 | C162: Not Listed | D162: Other Apparels & Accessories
A163: AKI INDIA LTD | B163: 542020 | C163: Not Listed | D163: Other Apparels & Accessories
A164: AKM LACE AND EMBROTEX LTD | B164: 540718 | C164: Not Listed | D164: Textiles
A165: AKME STAR HOUSING FINANCE LTD | B165: 539017 | C165: Not Listed | D165: Housing Finance
...

Sheet Forecasts

Sheet Forecasting
B2: Forecasts
B3: ='Data Sheet'!B1 -> ITC LTD
B4: Based on Statistical Forecasts using Linear Regression
B6: ='Data Sheet'!$B$1&" - "&'Data Sheet'!A17&" Forecasting" -> ITC LTD - Sales Forecasting | G6: ='Data Sheet'!$B$1&" - "&'Historical FS'!B23&" Forecasting" -> ITC LTD - EBITDA Forecasting | L6: ='Data Sheet'!$B$1&" - "&'Historical FS'!B40&" Forecasting" -> ITC LTD - Forecasting
B7: Year Weight | C7: Year | D7: ='Historical FS'!B8 -> Sales | E7: =D7&" Growth" -> Sales Growth | G7: Year Weight | H7: Year | I7: ='Historical FS'!B23 -> EBITDA | J7: ='Historical FS'!B23&" Growth" -> EBITDA Growth | L7: Year Weight | M7: Year | N7: ='Historical FS'!B43 -> Earnings per Share | O7: EPS Growth
B8: 1 | C8: ='Data Sheet'!B16 -> 42460 | D8: {=TRANSPOSE('Historical FS'!C8:L8)} -> 39192.1 | G8: =B8 -> 1 | H8: =C8 -> 42460 | I8: {=TRANSPOSE('Historical FS'!C23:L23)} -> 16014.6 | L8: =G8 -> 1 | M8: =H8 -> 42460 | N8: {=TRANSPOSE('Historical FS'!C43:L43)} -> 7.8709448
B9: 2 | C9: =C8+365 -> 42825 | D9: 42767.6 | E9: =D9/D8-1 -> 0.09123012 | G9: =B9 -> 2 | H9: =C9 -> 42825 | I9: 17228.14 | J9: =I9/I8-1 -> 0.075777103 | L9: =G9 -> 2 | M9: =H9 -> 42825 | N9: 8.6250803 | O9: =N9/N8-1 -> 0.095812578
B10: 3 | C10: =C9+365 -> 43190 | D10: 43448.94 | E10: =D10/D9-1 -> 0.015931219 | G10: =B10 -> 3 | H10: =C10 -> 43190 | I10: 18760.4 | J10: =I10/I9-1 -> 0.088939375 | L10: =G10 -> 3 | M10: =H10 -> 43190 | N10: 9.4169104 | O10: =N10/N9-1 -> 0.091805542
B11: 4 | C11: =C10+365 -> 43555 | D11: 48339.58 | E11: =D11/D10-1 -> 0.11256063 | G11: =B11 -> 4 | H11: =C11 -> 43555 | I11: 20617.83 | J11: =I11/I10-1 -> 0.099008017 | L11: =G11 -> 4 | M11: =H11 -> 43555 | N11: 10.470935 | O11: =N11/N10-1 -> 0.11192888
B12: 5 | C12: =C11+365 -> 43920 | D12: 49387.7 | E12: =D12/D11-1 -> 0.021682439 | G12: =B12 -> 5 | H12: =C12 -> 43920 | I12: 21760.86 | J12: =I12/I11-1 -> 0.055438909 | L12: =G12 -> 5 | M12: =H12 -> 43920 | N12: 12.685101 | O12: =N12/N11-1 -> 0.21145834
B13: 6 | C13: =C12+365 -> 44285 | D13: 49257.45 | E13: =D13/D12-1 -> -0.0026372963 | G13: =B13 -> 6 | H13: =C13 -> 44285 | I13: 19641.73 | J13: =I13/I12-1 -> -0.09738264 | L13: =G13 -> 6 | M13: =H13 -> 44285 | N13: 10.872611 | O13: =N13/N12-1 -> -0.14288334
B14: 7 | C14: =C13+365 -> 44650 | D14: 60644.54 | E14: =D14/D13-1 -> 0.23117498 | G14: =B14 -> 7 | H14: =C14 -> 44650 | I14: 22532.87 | J14: =I14/I13-1 -> 0.14719376 | L14: =G14 -> 7 | M14: =H14 -> 44650 | N14: 12.58034 | O14: =N14/N13-1 -> 0.15706698
B15: 8 | C15: =C14+365 -> 45015 | D15: 70919.03 | E15: =D15/D14-1 -> 0.16942152 | G15: =B15 -> 8 | H15: =C15 -> 45015 | I15: 27801.9 | J15: =I15/I14-1 -> 0.2338375 | L15: =G15 -> 8 | M15: =H15 -> 45015 | N15: 15.671645 | O15: =N15/N14-1 -> 0.24572508
B16: 9 | C16: =C15+365 -> 45380 | D16: 67931.94 | E16: =D16/D15-1 -> -0.042119724 | G16: =B16 -> 9 | H16: =C16 -> 45380 | I16: 28517.98 | J16: =I16/I15-1 -> 0.025756513 | L16: =G16 -> 9 | M16: =H16 -> 45380 | N16: 16.621433 | O16: =N16/N15-1 -> 0.060605506
B17: 10 | C17: =C16+365 -> 45745 | D17: 75323.34 | E17: =D17/D16-1 -> 0.10880596 | G17: =B17 -> 10 | H17: =C17 -> 45745 | I17: 43634.33 | J17: =I17/I16-1 -> 0.53006384 | L17: =G17 -> 10 | M17: =H17 -> 45745 | N17: 28.010388 | O17: =N17/N16-1 -> 0.68519699
B18: 11 | C18: =C17+365 -> 46110 | D18: =FORECAST(B18,D8:D17,B8:B17) -> 77236.776 | E18: =D18/D17-1 -> 0.025402963 | G18: =B18 -> 11 | H18: =C18 -> 46110 | I18: =FORECAST(G18,I8:I17,G8:G17) -> 36199.062 | J18: =I18/I17-1 -> -0.1703995 | L18: =G18 -> 11 | M18: =H18 -> 46110 | N18: =FORECAST(L18,N8:N17,L8:L17) -> 22.383167 | O18: =N18/N17-1 -> -0.20089764
B19: 12 | C19: =C18+365 -> 46475 | D19: =FORECAST(B19,D9:D18,B9:B18) -> 82101.898 | E19: =D19/D18-1 -> 0.062989714 | G19: =B19 -> 12 | H19: =C19 -> 46475 | I19: =FORECAST(G19,I9:I18,G9:G18) -> 39181.871 | J19: =I19/I18-1 -> 0.082400168 | L19: =G19 -> 12 | M19: =H19 -> 46475 | N19: =FORECAST(L19,N9:N18,L9:L18) -> 24.580327 | O19: =N19/N18-1 -> 0.098161249
B20: 13 | C20: =C19+365 -> 46840 | D20: =FORECAST(B20,D10:D19,B10:B19) -> 87330.225 | E20: =D20/D19-1 -> 0.063680943 | G20: =B20 -> 13 | H20: =C20 -> 46840 | I20: =FORECAST(G20,I10:I19,G10:G19) -> 42335.783 | J20: =I20/I19-1 -> 0.08049417 | L20: =G20 -> 13 | M20: =H20 -> 46840 | N20: =FORECAST(L20,N10:N19,L10:L19) -> 26.889972 | O20: =N20/N19-1 -> 0.093963145
B21: 14 | C21: =C20+365 -> 47205 | D21: =FORECAST(B21,D11:D20,B11:B20) -> 92209.286 | E21: =D21/D20-1 -> 0.055869098 | G21: =B21 -> 14 | H21: =C21 -> 47205 | I21: =FORECAST(G21,I11:I20,G11:G20) -> 45696.281 | J21: =I21/I20-1 -> 0.079377242 | L21: =G21 -> 14 | M21: =H21 -> 47205 | N21: =FORECAST(L21,N11:N20,L11:L20) -> 29.270946 | O21: =N21/N20-1 -> 0.088545067
B22: 15 | C22: =C21+365 -> 47570 | D22: =FORECAST(B22,D12:D21,B12:B21) -> 97418.723 | E22: =D22/D21-1 -> 0.056495796 | G22: =B22 -> 15 | H22: =C22 -> 47570 | I22: =FORECAST(G22,I12:I21,G12:G21) -> 49324.6 | J22: =I22/I21-1 -> 0.079400756 | L22: =G22 -> 15 | M22: =H22 -> 47570 | N22: =FORECAST(L22,N12:N21,L12:L21) -> 31.720513 | O22: =N22/N21-1 -> 0.083685934

Sheet Beta - Regression
B2: Calculation of Beta using Regression
B3: ='Data Sheet'!B1 -> ITC LTD
B5: ='Data Sheet'!B1&" Weekly Returns" -> ITC LTD Weekly Returns | F5: ='[2]Historical Data'!E1&" Returns" -> NIFTY Returns | I5: Beta Drifting | L5: Beta
L6: Beta 1 | M6: =SLOPE(D9:D112,G9:G112) -> 0.49821386
B7: Date | C7: Closing Price | D7: Return | F7: Closing Price | G7: Return | I7: Levered Raw Beta | J7: =M8 -> 0.49821386 | L7: Beta 2 | M7: =_xlfn.COVARIANCE.S(D9:D112,G9:G112)/_xlfn.VAR.S(G9:G112) -> 0.49821386
B8: ='Historical Data'!B3 -> 45137 | C8: ='Historical Data'!C3 -> 430.39 | F8: ='Historical Data'!F3 -> 19517 | I8: Raw Beta Weight | J8: 0.75 | L8: Beta 3 | M8: =J31 -> 0.49821386
B9: ='Historical Data'!B4 -> 45144 | C9: ='Historical Data'!C4 -> 424.52 | D9: =(C9/C8)-1 -> -0.013638793 | F9: ='Historical Data'!F4 -> 19428.3 | G9: =(F9/F8)-1 -> -0.0045447559
B10: ='Historical Data'!B5 -> 45151 | C10: ='Historical Data'!C5 -> 417.81 | D10: =(C10/C9)-1 -> -0.015806087 | F10: ='Historical Data'!F5 -> 19310.15 | G10: =(F10/F9)-1 -> -0.006081335 | I10: Market Beta | J10: 1
B11: ='Historical Data'!B6 -> 45158 | C11: ='Historical Data'!C6 -> 419.42 | D11: =(C11/C10)-1 -> 0.0038534262 | F11: ='Historical Data'!F6 -> 19265.8 | G11: =(F11/F10)-1 -> -0.0022967196 | I11: Market Beta Weight | J11: =1-J8 -> 0.25
B12: ='Historical Data'!B7 -> 45165 | C12: ='Historical Data'!C7 -> 417.24 | D12: =(C12/C11)-1 -> -0.0051976539 | F12: ='Historical Data'!F7 -> 19435.3 | G12: =(F12/F11)-1 -> 0.0087979736
B13: ='Historical Data'!B8 -> 45172 | C13: ='Historical Data'!C8 -> 418.75 | D13: =(C13/C12)-1 -> 0.0036190202 | F13: ='Historical Data'!F8 -> 19819.95 | G13: =(F13/F12)-1 -> 0.019791308 | I13: Adjusted Beta | J13: =(J7*J8)+(J10*J11) -> 0.6236604
B14: ='Historical Data'!B9 -> 45179 | C14: ='Historical Data'!C9 -> 424.14 | D14: =(C14/C13)-1 -> 0.012871642 | F14: ='Historical Data'!F9 -> 20192.35 | G14: =(F14/F13)-1 -> 0.018789149
B15: ='Historical Data'!B10 -> 45186 | C15: ='Historical Data'!C10 -> 419.18 | D15: =(C15/C14)-1 -> -0.011694252 | F15: ='Historical Data'!F10 -> 19674.25 | G15: =(F15/F14)-1 -> -0.025658232
B16: ='Historical Data'!B11 -> 45193 | C16: ='Historical Data'!C11 -> 420.41 | D16: =(C16/C15)-1 -> 0.0029343003 | F16: ='Historical Data'!F11 -> 19638.3 | G16: =(F16/F15)-1 -> -0.0018272615 | I16: Regression Statistics
B17: ='Historical Data'!B12 -> 45200 | C17: ='Historical Data'!C12 -> 418.28 | D17: =(C17/C16)-1 -> -0.0050664827 | F17: ='Historical Data'!F12 -> 19653.5 | G17: =(F17/F16)-1 -> 0.00077399775 | I17: Multiple R | J17: 0.41396685
B18: ='Historical Data'!B13 -> 45207 | C18: ='Historical Data'!C13 -> 424.14 | D18: =(C18/C17)-1 -> 0.014009754 | F18: ='Historical Data'!F13 -> 19751.05 | G18: =(F18/F17)-1 -> 0.0049634925 | I18: R Square | J18: 0.17136855
B19: ='Historical Data'!B14 -> 45214 | C19: ='Historical Data'!C14 -> 414.64 | D19: =(C19/C18)-1 -> -0.022398265 | F19: ='Historical Data'!F14 -> 19542.65 | G19: =(F19/F18)-1 -> -0.010551338 | I19: Adjusted R Square | J19: 0.16324472
B20: ='Historical Data'!B15 -> 45221 | C20: ='Historical Data'!C15 -> 410.33 | D20: =(C20/C19)-1 -> -0.010394559 | F20: ='Historical Data'!F15 -> 19047.25 | G20: =(F20/F19)-1 -> -0.025349684 | I20: Standard Error | J20: 0.018943883
B21: ='Historical Data'!B16 -> 45228 | C21: ='Historical Data'!C16 -> 409.86 | D21: =(C21/C20)-1 -> -0.0011454195 | F21: ='Historical Data'!F16 -> 19230.6 | G21: =(F21/F20)-1 -> 0.0096260615 | I21: Observations | J21: 104
B22: ='Historical Data'!B17 -> 45235 | C22: ='Historical Data'!C17 -> 412.98 | D22: =(C22/C21)-1 -> 0.0076123554 | F22: ='Historical Data'!F17 -> 19425.35 | G22: =(F22/F21)-1 -> 0.010127089
B23: ='Historical Data'!B18 -> 45242 | C23: ='Historical Data'!C18 -> 415.54 | D23: =(C23/C22)-1 -> 0.0061988474 | F23: ='Historical Data'!F18 -> 19731.8 | G23: =(F23/F22)-1 -> 0.015775778 | I23: ANOVA
B24: ='Historical Data'!B19 -> 45249 | C24: ='Historical Data'!C19 -> 414.16 | D24: =(C24/C23)-1 -> -0.0033209799 | F24: ='Historical Data'!F19 -> 19794.7 | G24: =(F24/F23)-1 -> 0.0031877477 | J24: df | K24: SS | L24: MS | M24: F | N24: Significance F
B25: ='Historical Data'!B20 -> 45256 | C25: ='Historical Data'!C20 -> 425.52 | D25: =(C25/C24)-1 -> 0.027429013 | F25: ='Historical Data'!F20 -> 20267.9 | G25: =(F25/F24)-1 -> 0.023905389 | I25: Regression | J25: 1 | K25: 0.0075702094 | L25: 0.0075702094 | M25: 21.094532 | N25: 1.2524314e-05
B26: ='Historical Data'!B21 -> 45263 | C26: ='Historical Data'!C21 -> 424.9 | D26: =(C26/C25)-1 -> -0.0014570408 | F26: ='Historical Data'!F21 -> 20969.4 | G26: =(F26/F25)-1 -> 0.034611381 | I26: Residual | J26: 102 | K26: 0.036604811 | L26: 0.0003588707
B27: ='Historical Data'!B22 -> 45270 | C27: ='Historical Data'!C22 -> 433.46 | D27: =(C27/C26)-1 -> 0.020145917 | F27: ='Historical Data'!F22 -> 21456.65 | G27: =(F27/F26)-1 -> 0.023236239 | I27: Total | J27: 103 | K27: 0.04417502
B28: ='Historical Data'!B23 -> 45277 | C28: ='Historical Data'!C23 -> 430.63 | D28: =(C28/C27)-1 -> -0.0065288608 | F28: ='Historical Data'!F23 -> 21349.4 | G28: =(F28/F27)-1 -> -0.0049984504
B29: ='Historical Data'!B24 -> 45284 | C29: ='Historical Data'!C24 -> 437.15 | D29: =(C29/C28)-1 -> 0.015140608 | F29: ='Historical Data'!F24 -> 21731.4 | G29: =(F29/F28)-1 -> 0.017892775 | J29: Coefficients | K29: Standard Error | L29: t Stat | M29: P-value | N29: Lower 95% | O29: Upper 95% | P29: Lower 95.0% | Q29: Upper 95.0%
B30: ='Historical Data'!B25 -> 45291 | C30: ='Historical Data'!C25 -> 448.36 | D30: =(C30/C29)-1 -> 0.025643372 | F30: ='Historical Data'!F25 -> 21710.8 | G30: =(F30/F29)-1 -> -0.00094793709 | I30: Intercept | J30: -0.0012803202 | K30: 0.0018751751 | L30: -0.68277365 | M30: 0.49629769 | N30: -0.0049997212 | O30: 0.0024390808 | P30: -0.0049997212 | Q30: 0.0024390808
B31: ='Historical Data'!B26 -> 45298 | C31: ='Historical Data'!C26 -> 441.5 | D31: =(C31/C30)-1 -> -0.015300205 | F31: ='Historical Data'!F26 -> 21894.55 | G31: =(F31/F30)-1 -> 0.0084635297 | I31: X Variable 1 | J31: 0.49821386 | K31: 0.1084753 | L31: 4.5928784 | M31: 1.2524314e-05 | N31: 0.28305362 | O31: 0.7133741 | P31: 0.28305362 | Q31: 0.7133741
B32: ='Historical Data'!B27 -> 45305 | C32: ='Historical Data'!C27 -> 446.05 | D32: =(C32/C31)-1 -> 0.010305776 | F32: ='Historical Data'!F27 -> 21622.4 | G32: =(F32/F31)-1 -> -0.012430034
B33: ='Historical Data'!B28 -> 45312 | C33: ='Historical Data'!C28 -> 431.05 | D33: =(C33/C32)-1 -> -0.033628517 | F33: ='Historical Data'!F28 -> 21352.6 | G33: =(F33/F32)-1 -> -0.012477801
B34: ='Historical Data'!B29 -> 45319 | C34: ='Historical Data'!C29 -> 416.34 | D34: =(C34/C33)-1 -> -0.034125971 | F34: ='Historical Data'!F29 -> 21853.8 | G34: =(F34/F33)-1 -> 0.023472551
B35: ='Historical Data'!B30 -> 45326 | C35: ='Historical Data'!C30 -> 393.07 | D35: =(C35/C34)-1 -> -0.055891819 | F35: ='Historical Data'!F30 -> 21782.5 | G35: =(F35/F34)-1 -> -0.0032625905
B36: ='Historical Data'!B31 -> 45333 | C36: ='Historical Data'!C31 -> 382.76 | D36: =(C36/C35)-1 -> -0.026229425 | F36: ='Historical Data'!F31 -> 22040.7 | G36: =(F36/F35)-1 -> 0.011853552
B37: ='Historical Data'!B32 -> 45340 | C37: ='Historical Data'!C32 -> 389.19 | D37: =(C37/C36)-1 -> 0.016799039 | F37: ='Historical Data'!F32 -> 22212.7 | G37: =(F37/F36)-1 -> 0.0078037449
B38: ='Historical Data'!B33 -> 45347 | C38: ='Historical Data'!C33 -> 387.39 | D38: =(C38/C37)-1 -> -0.0046249904 | F38: ='Historical Data'!F33 -> 22338.75 | G38: =(F38/F37)-1 -> 0.0056746816
B39: ='Historical Data'!B34 -> 45354 | C39: ='Historical Data'!C34 -> 391.22 | D39: =(C39/C38)-1 -> 0.0098866775 | F39: ='Historical Data'!F34 -> 22493.55 | G39: =(F39/F38)-1 -> 0.0069296626
B40: ='Historical Data'!B35 -> 45361 | C40: ='Historical Data'!C35 -> 396.47 | D40: =(C40/C39)-1 -> 0.013419559 | F40: ='Historical Data'!F35 -> 22023.35 | G40: =(F40/F39)-1 -> -0.02090377
B41: ='Historical Data'!B36 -> 45368 | C41: ='Historical Data'!C36 -> 405.46 | D41: =(C41/C40)-1 -> 0.022675108 | F41: ='Historical Data'!F36 -> 22096.75 | G41: =(F41/F40)-1 -> 0.0033328263
B42: ='Historical Data'!B37 -> 45375 | C42: ='Historical Data'!C37 -> 405.23 | D42: =(C42/C41)-1 -> -0.00056725694 | F42: ='Historical Data'!F37 -> 22326.9 | G42: =(F42/F41)-1 -> 0.010415559
B43: ='Historical Data'!B38 -> 45382 | C43: ='Historical Data'!C38 -> 404.47 | D43: =(C43/C42)-1 -> -0.0018754781 | F43: ='Historical Data'!F38 -> 22513.7 | G43: =(F43/F42)-1 -> 0.0083665892
... B112: ='Historical Data'!B107 -> 45865 | C112: ='Historical Data'!C107 -> 416.45 | D112: =(C112/C111)-1 -> 0.017220322 | F112: ='Historical Data'!F107 -> 24565.35 | G112: =(F112/F111)-1 -> -0.010937311

Sheet Historical Data
B1: ='Data Sheet'!B1 -> ITC LTD | E1: NIFTY
B2: Date | C2: Price | E2: Date | F2: Price
B3: 45137 | C3: 430.39 | E3: 45137 | F3: 19517
B4: 45144 | C4: 424.52 | E4: 45144 | F4: 19428.3
B5: 45151 | C5: 417.81 | E5: 45151 | F5: 19310.15
B6: 45158 | C6: 419.42 | E6: 45158 | F6: 19265.8
B7: 45165 | C7: 417.24 | E7: 45165 | F7: 19435.3
B8: 45172 | C8: 418.75 | E8: 45172 | F8: 19819.95
B9: 45179 | C9: 424.14 | E9: 45179 | F9: 20192.35
B10: 45186 | C10: 419.18 | E10: 45186 | F10: 19674.25
B11: 45193 | C11: 420.41 | E11: 45193 | F11: 19638.3
B12: 45200 | C12: 418.28 | E12: 45200 | F12: 19653.5
B13: 45207 | C13: 424.14 | E13: 45207 | F13: 19751.05
B14: 45214 | C14: 414.64 | E14: 45214 | F14: 19542.65
... B107: 45865 | C107: 416.45 | E107: 45865 | F107: 24565.35

Sheet Analysis

Sheet Dupont Analysis
B4: ITC LTD
B5: =CONCATENATE(" ","(",VLOOKUP(B4,'List of Stocks'!A2:C5442,3,1)," | ","BSE Code: ",VLOOKUP(B4,'List of Stocks'!A2:B5442,2,1),")") -> (ITC | BSE Code: 500875)
B6: INR 403
B7: 52 Week (High - INR 528 & Low - 390)
B9: About the company
B16: Financial Summary
B40: Recent Updates
B61: Return on Equity (ROE)
C62: ='Data Sheet'!E16 -> 43555 | D62: ='Data Sheet'!F16 -> 43921 | E62: ='Data Sheet'!G16 -> 44286 | F62: ='Data Sheet'!H16 -> 44651 | G62: ='Data Sheet'!I16 -> 45016 | H62: ='Data Sheet'!J16 -> 45382 | I62: ='Data Sheet'!K16 -> 45747
B63: Net Profit | C63: ='Data Sheet'!E30 -> 12592.33 | D63: ='Data Sheet'!F30 -> 15306.23 | E63: ='Data Sheet'!G30 -> 13161.19 | F63: ='Data Sheet'!H30 -> 15242.66 | G63: ='Data Sheet'!I30 -> 19191.66 | H63: ='Data Sheet'!J30 -> 20458.78 | I63: ='Data Sheet'!K30 -> 34746.63
B64: Average Shareholder Equity | C64: =(('Data Sheet'!E57+'Data Sheet'!E58)+('Data Sheet'!D57+'Data Sheet'!D58))/2 -> 55825.49 | D64: =(('Data Sheet'!F57+'Data Sheet'!F58)+('Data Sheet'!E57+'Data Sheet'!E58))/2 -> 62207.065 | E64: =(('Data Sheet'!G57+'Data Sheet'!G58)+('Data Sheet'!F57+'Data Sheet'!F58))/2 -> 62810.3 | F64: =(('Data Sheet'!H57+'Data Sheet'!H58)+('Data Sheet'!G57+'Data Sheet'!G58))/2 -> 61401.455 | G64: =(('Data Sheet'!I57+'Data Sheet'!I58)+('Data Sheet'!H57+'Data Sheet'!H58))/2 -> 65805.415 | H64: =(('Data Sheet'!J57+'Data Sheet'!J58)+('Data Sheet'!I57+'Data Sheet'!I58))/2 -> 71831.13 | I64: =(('Data Sheet'!K57+'Data Sheet'!K58)+('Data Sheet'!J57+'Data Sheet'!J58))/2 -> 72268.525
B65: Return on Equity | C65: =C63/C64 -> 0.22556596 | D65: =D63/D64 -> 0.24605292 | E65: =E63/E64 -> 0.20953872 | F65: =F63/F64 -> 0.24824591 | G65: =G63/G64 -> 0.29164256 | H65: =H63/H64 -> 0.28481774 | I65: =I63/I64 -> 0.48079894
B67: ROE - Dupont Equation
C68: =C62 -> 43555 | D68: =D62 -> 43921 | E68: =E62 -> 44286 | F68: =F62 -> 44651 | G68: =G62 -> 45016 | H68: =H62 -> 45382 | I68: =I62 -> 45747
B69: =B63 -> Net Profit | C69: =C63 -> 12592.33 | D69: =D63 -> 15306.23 | E69: =E63 -> 13161.19 | F69: =F63 -> 15242.66 | G69: =G63 -> 19191.66 | H69: =H63 -> 20458.78 | I69: =I63 -> 34746.63
B70: Revenue | C70: ='Data Sheet'!E17 -> 48339.58 | D70: ='Data Sheet'!F17 -> 49387.7 | E70: ='Data Sheet'!G17 -> 49257.45 | F70: ='Data Sheet'!H17 -> 60644.54 | G70: ='Data Sheet'!I17 -> 70919.03 | H70: ='Data Sheet'!J17 -> 67931.94 | I70: ='Data Sheet'!K17 -> 75323.34
B71: Net Profit Margin (A) | C71: =C69/C70 -> 0.2604973 | D71: =D69/D70 -> 0.30991988 | E71: =E69/E70 -> 0.26719187 | F71: =F69/F70 -> 0.25134431 | G71: =G69/G70 -> 0.27061368 | H71: =H69/H70 -> 0.30116584 | I71: =I69/I70 -> 0.46129964
B73: Revenue | C73: =C70 -> 48339.58 | D73: =D70 -> 49387.7 | E73: =E70 -> 49257.45 | F73: =F70 -> 60644.54 | G73: =G70 -> 70919.03 | H73: =H70 -> 67931.94 | I73: =I70 -> 75323.34
B74: Average Total Asset | C74: =('Data Sheet'!E66+'Data Sheet'!D66)/2 -> 67989.96 | D74: =('Data Sheet'!F66+'Data Sheet'!E66)/2 -> 74524.895 | E74: =('Data Sheet'!G66+'Data Sheet'!F66)/2 -> 75535.755 | F74: =('Data Sheet'!H66+'Data Sheet'!G66)/2 -> 75478.39 | G74: =('Data Sheet'!I66+'Data Sheet'!H66)/2 -> 81513.49 | H74: =('Data Sheet'!J66+'Data Sheet'!I66)/2 -> 88792.465 | I74: =('Data Sheet'!K66+'Data Sheet'!J66)/2 -> 89878.335
B75: Asset Turnover Ratio (B) | C75: =C73/C74 -> 0.71098115 | D75: =D73/D74 -> 0.6627007 | E75: =E73/E74 -> 0.65210773 | F75: =F73/F74 -> 0.80346891 | G75: =G73/G74 -> 0.87002814 | H75: =H73/H74 -> 0.76506424 | I75: =I73/I74 -> 0.83805892
B77: =B74 -> Average Total Asset | C77: =C74 -> 67989.96 | D77: =D74 -> 74524.895 | E77: =E74 -> 75535.755 | F77: =F74 -> 75478.39 | G77: =G74 -> 81513.49 | H77: =H74 -> 88792.465 | I77: =I74 -> 89878.335
B78: =B64 -> Average Shareholder Equity | C78: =C64 -> 55825.49 | D78: =D64 -> 62207.065 | E78: =E64 -> 62810.3 | F78: =F64 -> 61401.455 | G78: =G64 -> 65805.415 | H78: =H64 -> 71831.13 | I78: =I64 -> 72268.525
B79: Equity Multiplier (C) | C79: =C77/C78 -> 1.2179017 | D79: =D77/D78 -> 1.1980134 | E79: =E77/E78 -> 1.2026014 | F79: =F77/F78 -> 1.2292606 | G79: =G77/G78 -> 1.2387049 | H79: =H77/H78 -> 1.2361279 | I79: =I77/I78 -> 1.2436719
B81: Return on Equity (A*B*C) | C81: =C79*C75*C71 -> 0.22556596 | D81: =D79*D75*D71 -> 0.24605292 | E81: =E79*E75*E71 -> 0.20953872 | F81: =F79*F75*F71 -> 0.24824591 | G81: =G79*G75*G71 -> 0.29164256 | H81: =H79*H75*H71 -> 0.28481774 | I81: =I79*I75*I71 -> 0.48079894
B83: Return on Asset
C84: =C68 -> 43555 | D84: =D68 -> 43921 | E84: =E68 -> 44286 | F84: =F68 -> 44651 | G84: =G68 -> 45016 | H84: =H68 -> 45382 | I84: =I68 -> 45747
B85: Net Profit | C85: =C69 -> 12592.33 | D85: =D69 -> 15306.23 | E85: =E69 -> 13161.19 | F85: =F69 -> 15242.66 | G85: =G69 -> 19191.66 | H85: =H69 -> 20458.78 | I85: =I69 -> 34746.63
B86: =B77 -> Average Total Asset | C86: =C74 -> 67989.96 | D86: =D74 -> 74524.895 | E86: =E74 -> 75535.755 | F86: =F74 -> 75478.39 | G86: =G74 -> 81513.49 | H86: =H74 -> 88792.465 | I86: =I74 -> 89878.335
B87: Return on Asset | C87: =C85/C86 -> 0.18520867 | D87: =D85/D86 -> 0.20538412 | E87: =E85/E86 -> 0.17423788 | F87: =F85/F86 -> 0.20194734 | G87: =G85/G86 -> 0.23544152 | H87: =H85/H86 -> 0.23041122 | I87: =I85/I86 -> 0.38659628
B89: ROA - Dupont Equation
C90: =C84 -> 43555 | D90: =D84 -> 43921 | E90: =E84 -> 44286 | F90: =F84 -> 44651 | G90: =G84 -> 45016 | H90: =H84 -> 45382 | I90: =I84 -> 45747
B91: =B85 -> Net Profit | C91: =C85 -> 12592.33 | D91: =D85 -> 15306.23 | E91: =E85 -> 13161.19 | F91: =F85 -> 15242.66 | G91: =G85 -> 19191.66 | H91: =H85 -> 20458.78 | I91: =I85 -> 34746.63
B92: Revenue | C92: =C73 -> 48339.58 | D92: =D73 -> 49387.7 | E92: =E73 -> 49257.45 | F92: =F73 -> 60644.54 | G92: =G73 -> 70919.03 | H92: =H73 -> 67931.94 | I92: =I73 -> 75323.34
B93: Net Profit Margin (A) | C93: =C91/C92 -> 0.2604973 | D93: =D91/D92 -> 0.30991988 | E93: =E91/E92 -> 0.26719187 | F93: =F91/F92 -> 0.25134431 | G93: =G91/G92 -> 0.27061368 | H93: =H91/H92 -> 0.30116584 | I93: =I91/I92 -> 0.46129964
B95: Revenue | C95: =C92 -> 48339.58 | D95: =D92 -> 49387.7 | E95: =E92 -> 49257.45 | F95: =F92 -> 60644.54 | G95: =G92 -> 70919.03 | H95: =H92 -> 67931.94 | I95: =I92 -> 75323.34
B96: Average Total Asset | C96: =C86 -> 67989.96 | D96: =D86 -> 74524.895 | E96: =E86 -> 75535.755 | F96: =F86 -> 75478.39 | G96: =G86 -> 81513.49 | H96: =H86 -> 88792.465 | I96: =I86 -> 89878.335
B97: Asset Turnover Ratio (B) | C97: =C95/C96 -> 0.71098115 | D97: =D95/D96 -> 0.6627007 | E97: =E95/E96 -> 0.65210773 | F97: =F95/F96 -> 0.80346891 | G97: =G95/G96 -> 0.87002814 | H97: =H95/H96 -> 0.76506424 | I97: =I95/I96 -> 0.83805892
B99: Return on Asset (A*B) | C99: =C97*C93 -> 0.18520867 | D99: =D97*D93 -> 0.20538412 | E99: =E97*E93 -> 0.17423788 | F99: =F97*F93 -> 0.20194734 | G99: =G97*G93 -> 0.23544152 | H99: =H97*H93 -> 0.23041122 | I99: =I97*I93 -> 0.38659628
B101: Dupont Summary

Sheet Altman Z Score
B4: ITC LTD
B5: =CONCATENATE(" ","(",VLOOKUP(B4,'List of Stocks'!A2:C5442,3,1)," | ","BSE Code: ",VLOOKUP(B4,'List of Stocks'!A2:B5442,2,1),")") -> (ITC | BSE Code: 500875)
B6: INR 403
B7: 52 Week (High - INR 528 & Low - 390)
B9: Altman's Z Score Analysis Summary
B16: Financial Summary
B40: Recent Updates
B61: Working Capital / Total Assets
C62: ='Data Sheet'!E16 -> 43555 | D62: ='Data Sheet'!F16 -> 43921 | E62: ='Data Sheet'!G16 -> 44286 | F62: ='Data Sheet'!H16 -> 44651 | G62: ='Data Sheet'!I16 -> 45016 | H62: ='Data Sheet'!J16 -> 45382 | I62: ='Data Sheet'!K16 -> 45747
B63: Working Capital | C63: ='Data Sheet'!E65-'Data Sheet'!E60 -> 10600.21 | D63: ='Data Sheet'!F65-'Data Sheet'!F60 -> 11917.56 | E63: ='Data Sheet'!G65-'Data Sheet'!G60 -> 8437.53 | F63: ='Data Sheet'!H65-'Data Sheet'!H60 -> 10406.87 | G63: ='Data Sheet'!I65-'Data Sheet'!I60 -> 11191.71 | H63: ='Data Sheet'!J65-'Data Sheet'!J60 -> 13015.41 | I63: ='Data Sheet'!K65-'Data Sheet'!K60 -> 12549.01
B64: Total Assets | C64: ='Data Sheet'!E61 -> 71739.04 | D64: ='Data Sheet'!F61 -> 77310.75 | E64: ='Data Sheet'!G61 -> 73760.76 | F64: ='Data Sheet'!H61 -> 77196.02 | G64: ='Data Sheet'!I61 -> 85830.96 | H64: ='Data Sheet'!J61 -> 91753.97 | I64: ='Data Sheet'!K61 -> 88002.7
B65: Working Capital/Total Assets | C65: =C63/C64 -> 0.14776069 | D65: =D63/D64 -> 0.1541514 | E65: =E63/E64 -> 0.1143905 | F65: =F63/F64 -> 0.13481097 | G65: =G63/G64 -> 0.13039246 | H65: =H63/H64 -> 0.14185119 | I65: =I63/I64 -> 0.14259801
B67: Retained Earnings / Total Assets
C68: =C62 -> 43555 | D68: =D62 -> 43921 | E68: =E62 -> 44286 | F68: =F62 -> 44651 | G68: =G62 -> 45016 | H68: =H62 -> 45382 | I68: =I62 -> 45747
B69: Retained Earnings | C69: ='Historical FS'!F41*'Historical FS'!E43*'Historical FS'!E49 -> 5230.6393 | D69: ='Historical FS'!G41*'Historical FS'!F43*'Historical FS'!F49 -> 5803.0623 | E69: ='Historical FS'!H41*'Historical FS'!G43*'Historical FS'!G49 -> 3120.4083 | F69: ='Historical FS'!I41*'Historical FS'!H43*'Historical FS'!H49 -> 151.09779 | G69: ='Historical FS'!J41*'Historical FS'!I43*'Historical FS'!I49 -> 1342.6411 | H69: ='Historical FS'!K41*'Historical FS'!J43*'Historical FS'!J49 -> 214.29323 | I69: ='Historical FS'!L41*'Historical FS'!K43*'Historical FS'!K49 -> 3593.342
B70: Total Assets | C70: =C64 -> 71739.04 | D70: =D64 -> 77310.75 | E70: =E64 -> 73760.76 | F70: =F64 -> 77196.02 | G70: =G64 -> 85830.96 | H70: =H64 -> 91753.97 | I70: =I64 -> 88002.7
B71: Retained Earnings/Total Assets | C71: =C69/C70 -> 0.072912034 | D71: =D69/D70 -> 0.075061519 | E71: =E69/E70 -> 0.042304448 | F71: =F69/F70 -> 0.0019573261 | G71: =G69/G70 -> 0.015642853 | H71: =H69/H70 -> 0.0023355199 | I71: =I69/I70 -> 0.040832179
B73: EBIT/Total Assets
C74: =C68 -> 43555 | D74: =D68 -> 43921 | E74: =E68 -> 44286 | F74: =F68 -> 44651 | G74: =G68 -> 45016 | H74: =H68 -> 45382 | I74: =I68 -> 45747
B75: EBIT | C75: ='Historical FS'!F23-'Historical FS'!F29 -> 19221.22 | D75: ='Historical FS'!G23-'Historical FS'!G29 -> 20115.95 | E75: ='Historical FS'!H23-'Historical FS'!H29 -> 17996.14 | F75: ='Historical FS'!I23-'Historical FS'!I29 -> 20800.46 | G75: ='Historical FS'!J23-'Historical FS'!J29 -> 25992.89 | H75: ='Historical FS'!K23-'Historical FS'!K29 -> 26999.93 | I75: ='Historical FS'!L23-'Historical FS'!L29 -> 41988.01
B76: Total Assets | C76: =C70 -> 71739.04 | D76: =D70 -> 77310.75 | E76: =E70 -> 73760.76 | F76: =F70 -> 77196.02 | G76: =G70 -> 85830.96 | H76: =H70 -> 91753.97 | I76: =I70 -> 88002.7
B77: EBIT/Total Assets | C77: =C75/C76 -> 0.2679325 | D77: =D75/D76 -> 0.26019603 | E77: =E75/E76 -> 0.24397986 | F77: =F75/F76 -> 0.2694499 | G77: =G75/G76 -> 0.30283816 | H77: =H75/H76 -> 0.29426443 | I77: =I75/I76 -> 0.47712184
B79: Market Cap / Long term Liabilities
C80: =C74 -> 43555 | D80: =D74 -> 43921 | E80: =E74 -> 44286 | F80: =F74 -> 44651 | G80: =G74 -> 45016 | H80: =H74 -> 45382 | I80: =I74 -> 45747
B81: Market Cap | C81: =('Data Sheet'!E70*'Data Sheet'!E90)/100000000 -> 34157.451 | D81: =('Data Sheet'!F70*'Data Sheet'!F90)/100000000 -> 19784.346 | E81: =('Data Sheet'!G70*'Data Sheet'!G90)/100000000 -> 25210.975 | F81: =('Data Sheet'!H70*'Data Sheet'!H90)/100000000 -> 28954.722 | G81: =('Data Sheet'!I70*'Data Sheet'!I90)/100000000 -> 44677.481 | H81: =('Data Sheet'!J70*'Data Sheet'!J90)/100000000 -> 50129.816 | I81: =('Data Sheet'!K70*'Data Sheet'!K90)/100000000 -> 51276.606
B82: Long Term Liabilities | C82: ='Data Sheet'!E59 -> 13.44 | D82: ='Data Sheet'!F59 -> 277.45 | E82: ='Data Sheet'!G59 -> 270.83 | F82: ='Data Sheet'!H59 -> 249.44 | G82: ='Data Sheet'!I59 -> 306.04 | H82: ='Data Sheet'!J59 -> 303.43 | I82: ='Data Sheet'!K59 -> 284.54
B83: Market Cap/Long term Liabilities | C83: =C81/C82 -> 2541.477 | D83: =D81/D82 -> 71.307789 | E83: =E81/E82 -> 93.087822 | F83: =F81/F82 -> 116.07891 | G83: =G81/G82 -> 145.98576 | H83: =H81/H82 -> 165.21048 | I83: =I81/I82 -> 180.20878
B85: Revenue / Total Assets
C86: =C68 -> 43555 | D86: =D68 -> 43921 | E86: =E68 -> 44286 | F86: =F68 -> 44651 | G86: =G68 -> 45016 | H86: =H68 -> 45382 | I86: =I68 -> 45747
B87: Revenue | C87: ='Data Sheet'!E17 -> 48339.58 | D87: ='Data Sheet'!F17 -> 49387.7 | E87: ='Data Sheet'!G17 -> 49257.45 | F87: ='Data Sheet'!H17 -> 60644.54 | G87: ='Data Sheet'!I17 -> 70919.03 | H87: ='Data Sheet'!J17 -> 67931.94 | I87: ='Data Sheet'!K17 -> 75323.34
B88: Total Assets | C88: =C76 -> 71739.04 | D88: =D76 -> 77310.75 | E88: =E76 -> 73760.76 | F88: =F76 -> 77196.02 | G88: =G76 -> 85830.96 | H88: =H76 -> 91753.97 | I88: =I76 -> 88002.7
B89: Total Asset Turnover Ratio | C89: =C87/C88 -> 0.6738253 | D89: =D87/D88 -> 0.6388206 | E89: =E87/E88 -> 0.6678002 | F89: =F87/F88 -> 0.78559154 | G89: =G87/G88 -> 0.82626397 | H89: =H87/H88 -> 0.74037058 | I89: =I87/I88 -> 0.85592078
B91: Altman's Z Score
C92: =C86 -> 43555 | D92: =D86 -> 43921 | E92: =E86 -> 44286 | F92: =F86 -> 44651 | G92: =G86 -> 45016 | H92: =H86 -> 45382 | I92: =I86 -> 45747
B93: Final Score | C93: =(C65*1.2)+(C71*1.4)+(C77*3.3)+(C83*0.6)+(C89*1) -> 1526.7236 | D93: =(D65*1.2)+(D71*1.4)+(D77*3.3)+(D83*0.6)+(D89*1) -> 44.572209 | E93: =(E65*1.2)+(E71*1.4)+(E77*3.3)+(E83*0.6)+(E89*1) -> 57.522122 | F93: =(F65*1.2)+(F71*1.4)+(F77*3.3)+(F83*0.6)+(F89*1) -> 71.486633 | G93: =(G65*1.2)+(G71*1.4)+(G77*3.3)+(G83*0.6)+(G89*1) -> 89.595455 | H93: =(H65*1.2)+(H71*1.4)+(H77*3.3)+(H83*0.6)+(H89*1) -> 101.01122 | I93: =(I65*1.2)+(I71*1.4)+(I77*3.3)+(I83*0.6)+(I89*1) -> 110.78397
B94: Financial Stability | C94: =IF(C93<1.81," Distressed",IF(C93>3,"Strong","Grey Zone")) -> Strong | D94: =IF(D93<1.81," Distressed",IF(D93>3,"Strong","Grey Zone")) -> Strong | E94: =IF(E93<1.81," Distressed",IF(E93>3,"Strong","Grey Zone")) -> Strong | F94: =IF(F93<1.81," Distressed",IF(F93>3,"Strong","Grey Zone")) -> Strong | G94: =IF(G93<1.81," Distressed",IF(G93>3,"Strong","Grey Zone")) -> Strong | H94: =IF(H93<1.81," Distressed",IF(H93>3,"Strong","Grey Zone")) -> Strong | I94: =IF(I93<1.81," Distressed",IF(I93>3,"Strong","Grey Zone")) -> Strong

Sheet Altman Theory
A2: # | B2: What is Altman Z Score?
B3: It is a model that measures financial stability and solvency strength of the business
B4: The chances of business going bankrupt in the next 12 months
A6: # | B6: Ratio | F6: Weight
A7: i | B7: Working Capital/Total Assets | F7: 1.2
A8: ii | B8: Retained Earnings/Total Assets | F8: 1.4
A9: iii | B9: EBIT(Operating Profit)/Total Assets | F9: 3.3
A10: iv | B10: Market Cap/Long-term Liabilities | F10: 0.6
A11: v | B11: Sales/Total Assets | F11: 1
A13: # | B13: Less than 1.81 | E13: Distressed Zone
B14: 1.81 - 3.0 | E14: Grey Zone
B15: More than 3.0 | E15: Financially Strong
A17: # | B17: Analysis
A18: i | B18: Does the business have a huge portion of total assets as liquidable assets (WC)
B19: Company has high liquid component in the total ssets
B20: Infra
B21: FMCG
B22: Wine
B23: Rice
A25: ii | B25: Retained Earnings are those earnings that left after the shareholders have taken their dividend and rest is left for company for:
B26: Expansion
B27: Buy-back
B28: Reserves for later
A30: iii | B30: Profit that I earned solely from the business
B31: the internal ability of the business to fight insolvency
A33: iv | B33: How much times is the value of the company of the amount that it has to repay in the coming years
